Workbook

Sheet Emp Master
B1: kuldeep | C1: SE | D1: CS | L1: =SUBTOTAL(9,L4:L1516) -> 7786257 | P1: =SUBTOTAL(9,P4:P1516) -> 5725687 | T1: Put-> | U1: US, S | V1: Increament Method | Y1: =SUBTOTAL(9,Y4:Y1516) -> 5846320 | Z1: 35000 | AC1: 0.4 | AD1: 0.3 | AE1: 0.3 | AF1: For Under 30K | AK1: =COLUMN() -> 37
A2: =SUBTOTAL(3,A4:A1516) -> 255 | B2: Max No is | C2: =IFERROR(__xludf.DUMMYFUNCTION("ARRAY_CONSTRAIN(SORT(FILTER(RIGHT($A:$A,4),LEFT($A:$A,2)=C1),1,false),1,1)"),"1467") -> 1467 | D2: =IFERROR(__xludf.DUMMYFUNCTION("ARRAY_CONSTRAIN(SORT(FILTER(RIGHT($A:$A,4),LEFT($A:$A,2)=D1),1,false),1,1)"),"1265") -> 1265 | G2: DUTY TIME | L2: Current | P2: Last Sal | V2: Old | X2: N= No | Y2: 100 | Z2: =CONCAT("Base: ",(Z1*AB2)) -> Base: 17500 | AB2: 0.5 | AC2: 0.2 | AD2: 0.15 | AE2: 0.15 | AF2: For Over 30K | AM2: =today() -> 46292 | AQ2: Asset | AR2: Asset | AS2: Asset | AT2: Asset
A3: Employee Code | B3: NAME | C3: Type | D3: Department | E3: Designation | F3: Location | G3: IN | H3: OUT | I3: Working HRS | J3: DOJ | K3: COMPANY | L3: Salary | M3: Chq/Cs | N3: Status | O3: DoL inc | P3: L Sal | Q3: TDS | R3: Terminated Date | S3: ESI | T3: OT | U3: Skill Level | V3: Salary | W3: Inc % | X3: Extra Col | Y3: Inc 2025 | Z3: Remarks | AA3: New Sal for Basic+HRA | AB3: Basic | AC3: HRA | AD3: Conveyance | AE3: Others | AF3: Total Salary Ok? | AG3: Min Salary ? | AH3: Check in Advance | AI3: Sal Made? | AJ3: PF to calculate (Y/N) | AK3: Room Allowed | AL3: Aged in Year | AM3: Aged in Month | AN3: Shoe Size | AO3: T Shirt Size | AP3: jacket Size | AQ3: ID card | AR3: Tshirt | AS3: Shoe | AT3: Jacket
A4: CO1001 | B4: HARESH | C4: Comm | D4: Sales & Marketing | E4: Sales & Marketing | F4: BENG | G4: 0.375 | H4: 0.75 | I4: =IF(ISBLANK(H4),,H4-G4) -> 0.375 | K4: SE | L4: =Y4 -> 11800 | M4: Chq | N4: Employed | P4: 11800 | Q4: 200 | T4: NO | V4: =P4 -> 11800 | W4: 0 | Y4: =if(W4="",V4,round(V4*(1+W4),-1)) -> 11800 | AA4: =L4 -> 11800 | AB4: =IFS(AA4<=12000,AA4,AND(AA4>12000,AA4<=15200),15200,AND(AA4>15200,AA4<15500),AA4,AND(AA4>=15500,AA4<30000),15500,AA4>=30000,AA4*$AB$2) -> 11800 | AC4: =IF($AA4<=$Z$1,($AA4-$AB4)*AC$1,$AA4*AC$2) -> 0 | AD4: =IF($AA4<=$Z$1,($AA4-$AB4)*AD$1,$AA4*AD$2)+AA4-AB4-AC4-IF($AA4<=$Z$1,($AA4-$AB4)*AD$1,$AA4*AD$2) -> 0 | AE4: 0 | AF4: =IF(SUM(AB4:AE4)=AA4,"OK","NO") -> OK | AG4: =IF(U4="US",IF(AA4<9750,"Under","US OK"),IF(U4="S",IF(AA4<12000,"Under","S OK"),"Skill Missing")) -> Skill Missing | AH4: =VLOOKUP(A4,'Advance Sheet'!$A$4:$A$165,1,FALSE) -> #REF! | AI4: =IF(ISERROR(VLOOKUP(A4,'SNP Sal Main'!$A$3:$A1516,1,false))=FALSE,"SNP SAL",IF(ISERROR(VLOOKUP(A4,'Rest Sal Main org'!$A$3:$A1516,1,false))=FALSE,"Rest Sal","Not Found")) -> Not Found | AJ4: N | AM4: =if(J4="","",datedif(J4,$AM$2,"M"))
A5: CO1002 | B5: V UDAI SHANKAR | C5: Prof | D5: Agent | E5: Mis | F5: MUM | G5: 0.375 | H5: 0.75 | I5: =IF(ISBLANK(H5),,H5-G5) -> 0.375 | K5: SE | L5: =Y5 -> 100000 | M5: Chq | N5: Employed | P5: 100000 | Q5: 10000 | T5: NO | V5: =P5 -> 100000 | W5: 0 | Y5: =if(W5="",V5,round(V5*(1+W5),-1)) -> 100000 | Z5: =CONCATENATE(VLOOKUP(A5,'Copy of Emp Master'!$A$3:$Q$227,COLUMN(#REF!),FALSE)," ",VLOOKUP(A5,'Copy of Emp Master'!$A$3:$Q$227,COLUMN(#REF!),FALSE)) -> #REF! | AA5: =L5 -> 100000 | AB5: =IFS(AA5<=12000,AA5,AND(AA5>12000,AA5<=15200),15200,AND(AA5>15200,AA5<15500),AA5,AND(AA5>=15500,AA5<30000),15500,AA5>=30000,AA5*$AB$2) -> 50000 | AC5: =IF($AA5<=$Z$1,($AA5-$AB5)*AC$1,$AA5*AC$2) -> 20000 | AD5: =round(IF($AA5<=$Z$1,($AA5-$AB5)*AD$1,$AA5*AD$2),-1)+AA5-AB5-AC5-round(IF($AA5<=$Z$1,($AA5-$AB5)*AD$1,$AA5*AD$2),-1) -> 30000 | AE5: 0 | AF5: =IF(SUM(AB5:AE5)=AA5,"OK","NO") -> OK | AG5: =IF(U5="US",IF(AA5<9750,"Under","US OK"),IF(U5="S",IF(AA5<12000,"Under","S OK"),"Skill Missing")) -> Skill Missing | AH5: =VLOOKUP(A5,'Advance Sheet'!$A$4:$A$165,1,FALSE) -> #REF! | AI5: =IF(ISERROR(VLOOKUP(A5,'SNP Sal Main'!$A$3:$A1517,1,false))=FALSE,"SNP SAL",IF(ISERROR(VLOOKUP(A5,'Rest Sal Main org'!$A$3:$A1517,1,false))=FALSE,"Rest Sal","Not Found")) -> Not Found | AJ5: N | AM5: =if(J5="","",datedif(J5,$AM$2,"M"))
A6: CO1003 | B6: VARUN KAUSHAL | C6: Comm | D6: Sales & Marketing | E6: Sales & Marketing | F6: DEL | G6: 0.375 | H6: 0.75 | I6: =IF(ISBLANK(H6),,H6-G6) -> 0.375 | K6: SE | L6: =Y6 -> 20000 | M6: Chq | N6: Employed | P6: 20000 | Q6: 400 | T6: NO | V6: =P6 -> 20000 | W6: 0 | Y6: =if(W6="",V6,round(V6*(1+W6),-1)) -> 20000 | AA6: =L6 -> 20000 | AB6: =IFS(AA6<=12000,AA6,AND(AA6>12000,AA6<=15200),15200,AND(AA6>15200,AA6<15500),AA6,AND(AA6>=15500,AA6<30000),15500,AA6>=30000,AA6*$AB$2) -> 15500 | AC6: =IF($AA6<=$Z$1,($AA6-$AB6)*AC$1,$AA6*AC$2) -> 1800 | AD6: =round(IF($AA6<=$Z$1,($AA6-$AB6)*AD$1,$AA6*AD$2),-1)+AA6-AB6-AC6-round(IF($AA6<=$Z$1,($AA6-$AB6)*AD$1,$AA6*AD$2),-1) -> 2700 | AE6: 0 | AF6: =IF(SUM(AB6:AE6)=AA6,"OK","NO") -> OK | AG6: =IF(U6="US",IF(AA6<9750,"Under","US OK"),IF(U6="S",IF(AA6<12000,"Under","S OK"),"Skill Missing")) -> Skill Missing | AH6: =VLOOKUP(A6,'Advance Sheet'!$A$4:$A$165,1,FALSE) -> #REF! | AI6: =IF(ISERROR(VLOOKUP(A6,'SNP Sal Main'!$A$3:$A1518,1,false))=FALSE,"SNP SAL",IF(ISERROR(VLOOKUP(A6,'Rest Sal Main org'!$A$3:$A1518,1,false))=FALSE,"Rest Sal","Not Found")) -> Not Found | AJ6: N | AM6: =if(J6="","",datedif(J6,$AM$2,"M"))
A7: CS1030 | B7: SUBHASH CHAND | C7: Salary | D7: Backend Ops | E7: Executive | F7: DEL | G7: 0.39583333 | H7: 0.79166667 | I7: =IF(ISBLANK(H7),,H7-G7) -> 0.39583333 | J7: 33604 | K7: SE | L7: =Y7 -> 28580 | M7: CS | N7: Employed | O7: 45901 | P7: 25980 | T7: NO | U7: S | V7: =P7 -> 25980 | W7: 0.1 | Y7: =if(W7="",V7,round(V7*(1+W7),-1)) -> 28580 | AA7: =L7 -> 28580 | AB7: =IFS(AA7<=12000,AA7,AND(AA7>12000,AA7<=15200),15200,AND(AA7>15200,AA7<15500),AA7,AND(AA7>=15500,AA7<30000),15500,AA7>=30000,AA7*$AB$2) -> 15500 | AC7: =IF($AA7<=$Z$1,($AA7-$AB7)*AC$1,$AA7*AC$2) -> 5232 | AD7: =round(IF($AA7<=$Z$1,($AA7-$AB7)*AD$1,$AA7*AD$2),-1)+AA7-AB7-AC7-round(IF($AA7<=$Z$1,($AA7-$AB7)*AD$1,$AA7*AD$2),-1) -> 7848 | AE7: 0 | AF7: =IF(SUM(AB7:AE7)=AA7,"OK","NO") -> OK | AG7: =IF(U7="US",IF(AA7<9750,"Under","US OK"),IF(U7="S",IF(AA7<12000,"Under","S OK"),"Skill Missing")) -> S OK | AH7: =VLOOKUP(A7,'Advance Sheet'!$A$4:$A$165,1,FALSE) -> #REF! | AI7: =IF(ISERROR(VLOOKUP(A7,'SNP Sal Main'!$A$3:$A1519,1,false))=FALSE,"SNP SAL",IF(ISERROR(VLOOKUP(A7,'Rest Sal Main org'!$A$3:$A1519,1,false))=FALSE,"Rest Sal","Not Found")) -> Not Found | AJ7: N | AM7: =if(J7="","",datedif(J7,$AM$2,"M")) -> 416
A8: CS1226 | B8: Ankit | C8: Salary | D8: Machining | E8: Operator NC | F8: SNP | G8: 0.33333333 | H8: 0.75 | I8: =IF(ISBLANK(H8),,H8-G8) -> 0.41666667 | J8: 45940 | K8: SE | L8: 13200 | M8: CS | N8: Employed | P8: 12000 | V8: =P8 -> 12000 | W8: 0 | Y8: =if(W8="",V8,round(V8*(1+W8),-1)) -> 12000 | AA8: =L8 -> 13200 | AB8: =IFS(AND(AA8<=15000),15300,AND(AA8>15000,AA8<15500),AA8,AND(AA8>=15500,AA8<$Z$1),15500,AA8>=$Z$1,AA8*$AB$2) -> 15300 | AC8: =round(IF($AA8<=$Z$1,($AA8-$AB8)*AC$1,$AA8*AC$2),-1) -> -840 | AD8: =round(IF($AA8<=$Z$1,($AA8-$AB8)*AD$1,$AA8*AD$2),-1)+AA8-AB8-AC8-round(IF($AA8<=$Z$1,($AA8-$AB8)*AD$1,$AA8*AD$2),-1) -> -1260 | AE8: 0 | AF8: =IF(SUM(AB8:AE8)=AA8,"OK","NO") -> OK | AG8: =IF(U8="US",IF(AA8<9750,"Under","US OK"),IF(U8="S",IF(AA8<12000,"Under","S OK"),"Skill Missing")) -> Skill Missing | AH8: =VLOOKUP(A8,'Advance Sheet'!$A$4:$A$165,1,FALSE) -> #REF! | AI8: =IF(ISERROR(VLOOKUP(A8,'SNP Sal Main'!$A$3:$A1520,1,false))=FALSE,"SNP SAL",IF(ISERROR(VLOOKUP(A8,'Rest Sal Main org'!$A$3:$A1520,1,false))=FALSE,"Rest Sal","Not Found")) -> Not Found | AL8: =if(J8="","",datedif(J8,$AM$2,"Y")) -> 0 | AM8: =if(J8="","",datedif(J8,$AM$2,"M")) -> 11
A9: CS1248 | B9: Narayan Singh Charan | C9: Salary | E9: Misc | F9: SNP | G9: 0.375 | H9: 0.77083333 | I9: =IF(ISBLANK(H9),,H9-G9) -> 0.39583333 | J9: 46038 | K9: SE | L9: 15000 | M9: CS | N9: Employed | P9: 15000 | T9: NO | V9: =P9 -> 15000 | W9: 0 | Y9: =if(W9="",V9,round(V9*(1+W9),-1)) -> 15000 | AA9: 15000 | AB9: =IFS(AND(AA9<=15000),15300,AND(AA9>15000,AA9<15500),AA9,AND(AA9>=15500,AA9<$Z$1),15500,AA9>=$Z$1,AA9*$AB$2) -> 15300 | AC9: =round(IF($AA9<=$Z$1,($AA9-$AB9)*AC$1,$AA9*AC$2),-1) -> -120 | AD9: =round(IF($AA9<=$Z$1,($AA9-$AB9)*AD$1,$AA9*AD$2),-1)+AA9-AB9-AC9-round(IF($AA9<=$Z$1,($AA9-$AB9)*AD$1,$AA9*AD$2),-1) -> -180 | AE9: 0 | AF9: =IF(SUM(AB9:AE9)=AA9,"OK","NO") -> OK | AK9: YES | AM9: =if(J9="","",datedif(J9,$AM$2,"M")) -> 8
A10: CS1251 | B10: Manoj Kumar | C10: Salary | D10: Logistics | E10: Logistics | F10: SNP | I10: =IF(ISBLANK(H10),,H10-G10) | J10: 46064 | K10: SE | L10: 16000 | M10: CS | N10: Employed | P10: 16000 | V10: 16000 | AA10: 16000 | AB10: =IFS(AND(AA10<=15000),15300,AND(AA10>15000,AA10<15500),AA10,AND(AA10>=15500,AA10<$Z$1),15500,AA10>=$Z$1,AA10*$AB$2) -> 15500 | AC10: =round(IF($AA10<=$Z$1,($AA10-$AB10)*AC$1,$AA10*AC$2),-1) -> 200 | AD10: =round(IF($AA10<=$Z$1,($AA10-$AB10)*AD$1,$AA10*AD$2),-1)+AA10-AB10-AC10-round(IF($AA10<=$Z$1,($AA10-$AB10)*AD$1,$AA10*AD$2),-1) -> 300 | AE10: 0 | AF10: =IF(SUM(AB10:AE10)=AA10,"OK","NO") -> OK | AK10: NO | AM10: =if(J10="","",datedif(J10,$AM$2,"M")) -> 7
A11: CS1257 | B11: Dharamveer | C11: Salary | D11: Logistics | E11: Driver | F11: SNP | I11: =IF(ISBLANK(H11),,H11-G11) | J11: 46075 | K11: SE | L11: 20000 | M11: CS | N11: Employed | S11: NO | T11: NO | AA11: 25000 | AB11: =IFS(AND(AA11<=15000),15300,AND(AA11>15000,AA11<15500),AA11,AND(AA11>=15500,AA11<$Z$1),15500,AA11>=$Z$1,AA11*$AB$2) -> 15500 | AC11: =round(IF($AA11<=$Z$1,($AA11-$AB11)*AC$1,$AA11*AC$2),-1) -> 3800 | AD11: =round(IF($AA11<=$Z$1,($AA11-$AB11)*AD$1,$AA11*AD$2),-1)+AA11-AB11-AC11-round(IF($AA11<=$Z$1,($AA11-$AB11)*AD$1,$AA11*AD$2),-1) -> 5700 | AE11: 0 | AK11: NO | AM11: =if(J11="","",datedif(J11,$AM$2,"M")) -> 7
A12: CS1260 | B12: Ramkawar | C12: Salary | D12: Housekeeping | E12: Sweeper | F12: SNP | G12: 0.33333333 | H12: 0.75 | I12: =IF(ISBLANK(H12),,H12-G12) -> 0.41666667 | J12: 46101 | K12: SE | L12: 11000 | M12: CS | N12: Employed | S12: YES | T12: NO | AA12: 11000 | AB12: =IFS(AND(AA12<=15000),15300,AND(AA12>15000,AA12<15500),AA12,AND(AA12>=15500,AA12<$Z$1),15500,AA12>=$Z$1,AA12*$AB$2) -> 15300 | AC12: =round(IF($AA12<=$Z$1,($AA12-$AB12)*AC$1,$AA12*AC$2),-1) -> -1720 | AD12: =round(IF($AA12<=$Z$1,($AA12-$AB12)*AD$1,$AA12*AD$2),-1)+AA12-AB12-AC12-round(IF($AA12<=$Z$1,($AA12-$AB12)*AD$1,$AA12*AD$2),-1) -> -2580 | AE12: 0 | AF12: =IF(SUM(AB12:AE12)=AA12,"OK","NO") -> OK | AK12: NO | AM12: =if(J12="","",datedif(J12,$AM$2,"M")) -> 6
A13: CS1261 | B13: SURENDER SINGH | C13: Salary | D13: LOGISTICS | E13: DRIVER | F13: SNP | G13: 0.33333333 | H13: 0.75 | I13: =IF(ISBLANK(H13),,H13-G13) -> 0.41666667 | J13: 46148 | K13: SE | L13: 23000 | M13: CS | N13: Employed | AA13: =L13 -> 23000 | AB13: =IFS(AND(AA13<=15000),15300,AND(AA13>15000,AA13<15500),AA13,AND(AA13>=15500,AA13<$Z$1),15500,AA13>=$Z$1,AA13*$AB$2) -> 15500 | AC13: =round(IF($AA13<=$Z$1,($AA13-$AB13)*AC$1,$AA13*AC$2),-1) -> 3000 | AD13: =round(IF($AA13<=$Z$1,($AA13-$AB13)*AD$1,$AA13*AD$2),-1)+AA13-AB13-AC13-round(IF($AA13<=$Z$1,($AA13-$AB13)*AD$1,$AA13*AD$2),-1) -> 4500 | AE13: 0 | AF13: =IF(SUM(AB13:AE13)=AA13,"OK","NO") -> OK | AG13: =IF(U13="US",IF(AA13<9750,"Under","US OK"),IF(U13="S",IF(AA13<12000,"Under","S OK"),"Skill Missing")) -> Skill Missing | AI13: =IF(ISERROR(VLOOKUP(A13,'SNP Sal Main'!$A$3:$A1516,1,false))=FALSE,"SNP SAL",IF(ISERROR(VLOOKUP(A13,'Rest Sal Main org'!$A$3:$A1516,1,false))=FALSE,"Rest Sal","Not Found")) -> Not Found | AM13: =if(J13="","",datedif(J13,$AM$2,"M")) -> 4
A14: CS1262 | B14: RAJ KUMAR | C14: Salary | D14: LOGISTICS | E14: DRIVER | F14: SNP | G14: 0.33333333 | H14: 0.75 | I14: =IF(ISBLANK(H14),,H14-G14) -> 0.41666667 | J14: 46148 | K14: SE | L14: 23000 | M14: CS | N14: Employed | AA14: =L14 -> 23000 | AB14: =IFS(AND(AA14<=15000),15300,AND(AA14>15000,AA14<15500),AA14,AND(AA14>=15500,AA14<$Z$1),15500,AA14>=$Z$1,AA14*$AB$2) -> 15500 | AC14: =round(IF($AA14<=$Z$1,($AA14-$AB14)*AC$1,$AA14*AC$2),-1) -> 3000 | AD14: =round(IF($AA14<=$Z$1,($AA14-$AB14)*AD$1,$AA14*AD$2),-1)+AA14-AB14-AC14-round(IF($AA14<=$Z$1,($AA14-$AB14)*AD$1,$AA14*AD$2),-1) -> 4500 | AE14: 0 | AF14: =IF(SUM(AB14:AE14)=AA14,"OK","NO") -> OK | AG14: =IF(U14="US",IF(AA14<9750,"Under","US OK"),IF(U14="S",IF(AA14<12000,"Under","S OK"),"Skill Missing")) -> Skill Missing | AI14: =IF(ISERROR(VLOOKUP(A14,'SNP Sal Main'!$A$3:$A1517,1,false))=FALSE,"SNP SAL",IF(ISERROR(VLOOKUP(A14,'Rest Sal Main org'!$A$3:$A1517,1,false))=FALSE,"Rest Sal","Not Found")) -> Not Found | AM14: =if(J14="","",datedif(J14,$AM$2,"M")) -> 4
A15: CS1263 | B15: SANDEEP | C15: Salary | D15: LOGISTICS | E15: DRIVER | F15: SNP | G15: 0.33333333 | H15: 0.75 | I15: =IF(ISBLANK(H15),,H15-G15) -> 0.41666667 | J15: 46148 | K15: SE | L15: 23000 | M15: CS | N15: Employed | AA15: =L15 -> 23000 | AB15: =IFS(AND(AA15<=15000),15300,AND(AA15>15000,AA15<15500),AA15,AND(AA15>=15500,AA15<$Z$1),15500,AA15>=$Z$1,AA15*$AB$2) -> 15500 | AC15: =round(IF($AA15<=$Z$1,($AA15-$AB15)*AC$1,$AA15*AC$2),-1) -> 3000 | AD15: =round(IF($AA15<=$Z$1,($AA15-$AB15)*AD$1,$AA15*AD$2),-1)+AA15-AB15-AC15-round(IF($AA15<=$Z$1,($AA15-$AB15)*AD$1,$AA15*AD$2),-1) -> 4500 | AE15: 0 | AF15: =IF(SUM(AB15:AE15)=AA15,"OK","NO") -> OK | AG15: =IF(U15="US",IF(AA15<9750,"Under","US OK"),IF(U15="S",IF(AA15<12000,"Under","S OK"),"Skill Missing")) -> Skill Missing | AI15: =IF(ISERROR(VLOOKUP(A15,'SNP Sal Main'!$A$3:$A1518,1,false))=FALSE,"SNP SAL",IF(ISERROR(VLOOKUP(A15,'Rest Sal Main org'!$A$3:$A1518,1,false))=FALSE,"Rest Sal","Not Found")) -> Not Found | AM15: =if(J15="","",datedif(J15,$AM$2,"M")) -> 4
A16: CS1265 | B16: SANJEEV | C16: Salary | D16: Garden | E16: Mali | F16: SNP | G16: 0.33333333 | H16: 0.75 | I16: =IF(ISBLANK(H16),,H16-G16) -> 0.41666667 | J16: 46265 | K16: SE | L16: 13000 | M16: Chq | N16: Employed | AA16: =L16 -> 13000 | AB16: =IFS(AND(AA16<=15000),15300,AND(AA16>15000,AA16<15500),AA16,AND(AA16>=15500,AA16<$Z$1),15500,AA16>=$Z$1,AA16*$AB$2) -> 15300 | AC16: =round(IF($AA16<=$Z$1,($AA16-$AB16)*AC$1,$AA16*AC$2),-1) -> -920 | AD16: =round(IF($AA16<=$Z$1,($AA16-$AB16)*AD$1,$AA16*AD$2),-1)+AA16-AB16-AC16-round(IF($AA16<=$Z$1,($AA16-$AB16)*AD$1,$AA16*AD$2),-1) -> -1380 | AE16: 0
A17: FM1008 | B17: BALI RAM | C17: Salary | D17: Cutting | E17: Helper | F17: MUM | G17: 0.375 | H17: 0.79166667 | I17: =IF(ISBLANK(H17),,H17-G17) -> 0.41666667 | J17: 45809 | K17: FERMECH | L17: 16737 | M17: Chq | N17: Employed | O17: 45536 | P17: 15940 | T17: NO | U17: US | V17: =P17 -> 15940 | W17: 0 | Y17: =if(W17="",V17,round(V17*(1+W17),-1)) -> 15940 | AA17: 16737 | AB17: =IFS(AA17<=12000,AA17,AND(AA17>12000,AA17<=15200),15200,AND(AA17>15200,AA17<15500),AA17,AND(AA17>=15500,AA17<30000),15500,AA17>=30000,AA17*$AB$2) -> 15500 | AC17: =IF($AA17<=$Z$1,($AA17-$AB17)*AC$1,$AA17*AC$2) -> 494.8 | AD17: =round(IF($AA17<=$Z$1,($AA17-$AB17)*AD$1,$AA17*AD$2),-1)+AA17-AB17-AC17-round(IF($AA17<=$Z$1,($AA17-$AB17)*AD$1,$AA17*AD$2),-1) -> 742.2 | AE17: 0 | AF17: =IF(SUM(AB17:AE17)=AA17,"OK","NO") -> OK | AG17: =IF(U17="US",IF(AA17<9750,"Under","US OK"),IF(U17="S",IF(AA17<12000,"Under","S OK"),"Skill Missing")) -> US OK | AH17: =VLOOKUP(A17,'Advance Sheet'!$A$4:$A$165,1,FALSE) -> #REF! | AI17: =IF(ISERROR(VLOOKUP(A17,'SNP Sal Main'!$A$3:$A1516,1,false))=FALSE,"SNP SAL",IF(ISERROR(VLOOKUP(A17,'Rest Sal Main org'!$A$3:$A1516,1,false))=FALSE,"Rest Sal","Not Found")) -> Not Found | AJ17: N | AM17: =if(J17="","",datedif(J17,$AM$2,"M")) -> 15
A18: FM1012 | B18: ABDUR RAJJAK FARUK MONDAL | C18: Salary | D18: Cutting | E18: Operator | F18: MUM | G18: 0.33333333 | H18: 0.75 | I18: =IF(ISBLANK(H18),,H18-G18) -> 0.41666667 | J18: 45809 | K18: FERMECH | L18: 15400 | M18: Chq | N18: Employed | O18: 45809 | P18: 14000 | T18: NO | V18: =P18 -> 14000 | W18: 0 | Y18: =if(W18="",V18,round(V18*(1+W18),-1)) -> 14000 | AA18: =L18 -> 15400 | AB18: =IFS(AND(AA18<=15000),15300,AND(AA18>15000,AA18<15500),AA18,AND(AA18>=15500,AA18<$Z$1),15500,AA18>=$Z$1,AA18*$AB$2) -> 15400 | AC18: =round(IF($AA18<=$Z$1,($AA18-$AB18)*AC$1,$AA18*AC$2),-1) -> 0 | AD18: =round(IF($AA18<=$Z$1,($AA18-$AB18)*AD$1,$AA18*AD$2),-1)+AA18-AB18-AC18-round(IF($AA18<=$Z$1,($AA18-$AB18)*AD$1,$AA18*AD$2),-1) -> 0 | AE18: 0 | AF18: =IF(SUM(AB18:AE18)=AA18,"OK","NO") -> OK | AG18: =IF(U18="US",IF(AA18<9750,"Under","US OK"),IF(U18="S",IF(AA18<12000,"Under","S OK"),"Skill Missing")) -> Skill Missing | AH18: =VLOOKUP(A18,'Advance Sheet'!$A$4:$A$165,1,FALSE) -> #REF! | AI18: =IF(ISERROR(VLOOKUP(A18,'SNP Sal Main'!$A$3:$A1517,1,false))=FALSE,"SNP SAL",IF(ISERROR(VLOOKUP(A18,'Rest Sal Main org'!$A$3:$A1517,1,false))=FALSE,"Rest Sal","Not Found")) -> Not Found | AM18: =if(J18="","",datedif(J18,$AM$2,"M")) -> 15
A19: ITI1009 | B19: VIVEK | C19: Salary | D19: Machining | E19: ITI | F19: SNP | G19: 0.33333333 | H19: 0.75 | I19: =IF(ISBLANK(H19),,H19-G19) -> 0.41666667 | J19: 45614 | K19: SE | L19: =Y19 -> 6550 | M19: CS | N19: Employed | P19: 6550 | T19: YES | V19: =P19 -> 6550 | W19: 0 | Y19: =if(W19="",V19,round(V19*(1+W19),-1)) -> 6550 | AA19: =L19 -> 6550 | AB19: =IFS(AND(AA19<=15000),15300,AND(AA19>15000,AA19<15500),AA19,AND(AA19>=15500,AA19<$Z$1),15500,AA19>=$Z$1,AA19*$AB$2) -> 15300 | AC19: =round(IF($AA19<=$Z$1,($AA19-$AB19)*AC$1,$AA19*AC$2),-1) -> -3500 | AD19: =round(IF($AA19<=$Z$1,($AA19-$AB19)*AD$1,$AA19*AD$2),-1)+AA19-AB19-AC19-round(IF($AA19<=$Z$1,($AA19-$AB19)*AD$1,$AA19*AD$2),-1) -> -5250 | AE19: =IF($AA19<=$Z$1,($AA19-$AB19)*AE$1,$AA19*AE$2) -> -2625 | AF19: =IF(SUM(AB19:AE19)=AA19,"OK","NO") -> NO | AG19: =IF(U19="US",IF(AA19<9750,"Under","US OK"),IF(U19="S",IF(AA19<12000,"Under","S OK"),"Skill Missing")) -> Skill Missing | AH19: =VLOOKUP(A19,'Advance Sheet'!$A$4:$A$165,1,FALSE) -> #REF! | AI19: =IF(ISERROR(VLOOKUP(A19,'SNP Sal Main'!$A$3:$A1518,1,false))=FALSE,"SNP SAL",IF(ISERROR(VLOOKUP(A19,'Rest Sal Main org'!$A$3:$A1518,1,false))=FALSE,"Rest Sal","Not Found")) -> Not Found | AL19: =if(J19="","",datedif(J19,$AM$2,"Y")) -> 1 | AM19: =if(J19="","",datedif(J19,$AM$2,"M")) -> 22
A20: ITI1010 | B20: Dikshit | C20: Salary | D20: Machining | E20: ITI | F20: SNP | G20: 0.33333333 | H20: 0.75 | I20: =IF(ISBLANK(H20),,H20-G20) -> 0.41666667 | J20: 45908 | K20: SE | L20: 12500 | M20: CS | N20: Employed | P20: 12000 | T20: YES | V20: =P20 -> 12000 | W20: 0 | Y20: =if(W20="",V20,round(V20*(1+W20),-1)) -> 12000 | AA20: 12000 | AB20: =IFS(AND(AA20<=15000),15300,AND(AA20>15000,AA20<15500),AA20,AND(AA20>=15500,AA20<$Z$1),15500,AA20>=$Z$1,AA20*$AB$2) -> 15300 | AC20: =round(IF($AA20<=$Z$1,($AA20-$AB20)*AC$1,$AA20*AC$2),-1) -> -1320 | AD20: =round(IF($AA20<=$Z$1,($AA20-$AB20)*AD$1,$AA20*AD$2),-1)+AA20-AB20-AC20-round(IF($AA20<=$Z$1,($AA20-$AB20)*AD$1,$AA20*AD$2),-1) -> -1980 | AE20: 0 | AF20: =IF(SUM(AB20:AE20)=AA20,"OK","NO") -> OK | AG20: =IF(U20="US",IF(AA20<9750,"Under","US OK"),IF(U20="S",IF(AA20<12000,"Under","S OK"),"Skill Missing")) -> Skill Missing | AH20: =VLOOKUP(A20,'Advance Sheet'!$A$4:$A$165,1,FALSE) -> #REF! | AI20: =IF(ISERROR(VLOOKUP(A20,'SNP Sal Main'!$A$3:$A1519,1,false))=FALSE,"SNP SAL",IF(ISERROR(VLOOKUP(A20,'Rest Sal Main org'!$A$3:$A1519,1,false))=FALSE,"Rest Sal","Not Found")) -> Not Found | AL20: =if(J20="","",datedif(J20,$AM$2,"Y")) -> 1 | AM20: =if(J20="","",datedif(J20,$AM$2,"M")) -> 12
A21: ITI1011 | B21: Mohit | C21: Salary | D21: Machining | E21: ITI | F21: SNP | G21: 0.33333333 | H21: 0.75 | I21: =IF(ISBLANK(H21),,H21-G21) -> 0.41666667 | J21: 45908 | K21: SE | L21: 12500 | M21: CS | N21: Employed | P21: 12000 | T21: YES | V21: =P21 -> 12000 | W21: 0 | Y21: =if(W21="",V21,round(V21*(1+W21),-1)) -> 12000 | AA21: 12000 | AB21: =IFS(AND(AA21<=15000),15300,AND(AA21>15000,AA21<15500),AA21,AND(AA21>=15500,AA21<$Z$1),15500,AA21>=$Z$1,AA21*$AB$2) -> 15300 | AC21: =round(IF($AA21<=$Z$1,($AA21-$AB21)*AC$1,$AA21*AC$2),-1) -> -1320 | AD21: =round(IF($AA21<=$Z$1,($AA21-$AB21)*AD$1,$AA21*AD$2),-1)+AA21-AB21-AC21-round(IF($AA21<=$Z$1,($AA21-$AB21)*AD$1,$AA21*AD$2),-1) -> -1980 | AE21: 0 | AF21: =IF(SUM(AB21:AE21)=AA21,"OK","NO") -> OK | AG21: =IF(U21="US",IF(AA21<9750,"Under","US OK"),IF(U21="S",IF(AA21<12000,"Under","S OK"),"Skill Missing")) -> Skill Missing | AH21: =VLOOKUP(A21,'Advance Sheet'!$A$4:$A$165,1,FALSE) -> #REF! | AI21: =IF(ISERROR(VLOOKUP(A21,'SNP Sal Main'!$A$3:$A1520,1,false))=FALSE,"SNP SAL",IF(ISERROR(VLOOKUP(A21,'Rest Sal Main org'!$A$3:$A1520,1,false))=FALSE,"Rest Sal","Not Found")) -> Not Found | AL21: =if(J21="","",datedif(J21,$AM$2,"Y")) -> 1 | AM21: =if(J21="","",datedif(J21,$AM$2,"M")) -> 12
A22: ITI1012 | B22: Nitesh | C22: Salary | D22: Machining | E22: ITI | F22: SNP | G22: 0.33333333 | H22: 0.75 | I22: =IF(ISBLANK(H22),,H22-G22) -> 0.41666667 | J22: 45908 | K22: SE | L22: 14000 | M22: CS | N22: Employed | P22: 12000 | T22: YES | V22: =P22 -> 12000 | W22: 0 | Y22: =if(W22="",V22,round(V22*(1+W22),-1)) -> 12000 | AA22: 14000 | AB22: =IFS(AND(AA22<=15000),15300,AND(AA22>15000,AA22<15500),AA22,AND(AA22>=15500,AA22<$Z$1),15500,AA22>=$Z$1,AA22*$AB$2) -> 15300 | AC22: =round(IF($AA22<=$Z$1,($AA22-$AB22)*AC$1,$AA22*AC$2),-1) -> -520 | AD22: =round(IF($AA22<=$Z$1,($AA22-$AB22)*AD$1,$AA22*AD$2),-1)+AA22-AB22-AC22-round(IF($AA22<=$Z$1,($AA22-$AB22)*AD$1,$AA22*AD$2),-1) -> -780 | AE22: 0 | AF22: =IF(SUM(AB22:AE22)=AA22,"OK","NO") -> OK | AG22: =IF(U22="US",IF(AA22<9750,"Under","US OK"),IF(U22="S",IF(AA22<12000,"Under","S OK"),"Skill Missing")) -> Skill Missing | AH22: =VLOOKUP(A22,'Advance Sheet'!$A$4:$A$165,1,FALSE) -> #REF! | AI22: =IF(ISERROR(VLOOKUP(A22,'SNP Sal Main'!$A$3:$A1521,1,false))=FALSE,"SNP SAL",IF(ISERROR(VLOOKUP(A22,'Rest Sal Main org'!$A$3:$A1521,1,false))=FALSE,"Rest Sal","Not Found")) -> Not Found | AL22: =if(J22="","",datedif(J22,$AM$2,"Y")) -> 1 | AM22: =if(J22="","",datedif(J22,$AM$2,"M")) -> 12
A23: ITI1013 | B23: Saurabh | C23: Salary | D23: Machining | E23: ITI | F23: SNP | G23: 0.33333333 | H23: 0.75 | I23: =IF(ISBLANK(H23),,H23-G23) -> 0.41666667 | J23: 45940 | K23: SE | L23: 12500 | M23: CS | N23: Employed | P23: 12000 | T23: YES | V23: =P23 -> 12000 | W23: 0 | Y23: =if(W23="",V23,round(V23*(1+W23),-1)) -> 12000 | AA23: 12000 | AB23: =IFS(AND(AA23<=15000),15300,AND(AA23>15000,AA23<15500),AA23,AND(AA23>=15500,AA23<$Z$1),15500,AA23>=$Z$1,AA23*$AB$2) -> 15300 | AC23: =round(IF($AA23<=$Z$1,($AA23-$AB23)*AC$1,$AA23*AC$2),-1) -> -1320 | AD23: =round(IF($AA23<=$Z$1,($AA23-$AB23)*AD$1,$AA23*AD$2),-1)+AA23-AB23-AC23-round(IF($AA23<=$Z$1,($AA23-$AB23)*AD$1,$AA23*AD$2),-1) -> -1980 | AE23: 0 | AF23: =IF(SUM(AB23:AE23)=AA23,"OK","NO") -> OK | AG23: =IF(U23="US",IF(AA23<9750,"Under","US OK"),IF(U23="S",IF(AA23<12000,"Under","S OK"),"Skill Missing")) -> Skill Missing | AH23: =VLOOKUP(A23,'Advance Sheet'!$A$4:$A$165,1,FALSE) -> #REF! | AI23: =IF(ISERROR(VLOOKUP(A23,'SNP Sal Main'!$A$3:$A1522,1,false))=FALSE,"SNP SAL",IF(ISERROR(VLOOKUP(A23,'Rest Sal Main org'!$A$3:$A1522,1,false))=FALSE,"Rest Sal","Not Found")) -> Not Found | AL23: =if(J23="","",datedif(J23,$AM$2,"Y")) -> 0 | AM23: =if(J23="","",datedif(J23,$AM$2,"M")) -> 11
A24: ITI1014 | B24: Sorabh | C24: Salary | D24: Machining | E24: ITI | F24: SNP | G24: 0.33333333 | H24: 0.75 | I24: =IF(ISBLANK(H24),,H24-G24) -> 0.41666667 | J24: 45940 | K24: SE | L24: 12500 | M24: CS | N24: Employed | P24: 12000 | T24: YES | V24: =P24 -> 12000 | W24: 0 | Y24: =if(W24="",V24,round(V24*(1+W24),-1)) -> 12000 | AA24: 12000 | AB24: =IFS(AND(AA24<=15000),15300,AND(AA24>15000,AA24<15500),AA24,AND(AA24>=15500,AA24<$Z$1),15500,AA24>=$Z$1,AA24*$AB$2) -> 15300 | AC24: =round(IF($AA24<=$Z$1,($AA24-$AB24)*AC$1,$AA24*AC$2),-1) -> -1320 | AD24: =round(IF($AA24<=$Z$1,($AA24-$AB24)*AD$1,$AA24*AD$2),-1)+AA24-AB24-AC24-round(IF($AA24<=$Z$1,($AA24-$AB24)*AD$1,$AA24*AD$2),-1) -> -1980 | AE24: 0 | AF24: =IF(SUM(AB24:AE24)=AA24,"OK","NO") -> OK | AG24: =IF(U24="US",IF(AA24<9750,"Under","US OK"),IF(U24="S",IF(AA24<12000,"Under","S OK"),"Skill Missing")) -> Skill Missing | AH24: =VLOOKUP(A24,'Advance Sheet'!$A$4:$A$165,1,FALSE) -> #REF! | AI24: =IF(ISERROR(VLOOKUP(A24,'SNP Sal Main'!$A$3:$A1523,1,false))=FALSE,"SNP SAL",IF(ISERROR(VLOOKUP(A24,'Rest Sal Main org'!$A$3:$A1523,1,false))=FALSE,"Rest Sal","Not Found")) -> Not Found | AL24: =if(J24="","",datedif(J24,$AM$2,"Y")) -> 0 | AM24: =if(J24="","",datedif(J24,$AM$2,"M")) -> 11
A25: ITI1015 | B25: Ritesh | C25: Salary | D25: Machining | E25: ITI | F25: SNP | G25: 0.33333333 | H25: 0.75 | I25: =IF(ISBLANK(H25),,H25-G25) -> 0.41666667 | J25: 45985 | K25: SE | L25: =Y25 -> 14000 | M25: CS | N25: Employed | P25: 14000 | T25: YES | V25: =P25 -> 14000 | Y25: =if(W25="",V25,round(V25*(1+W25),-1)) -> 14000 | AA25: 14000 | AB25: =IFS(AND(AA25<=15000),15300,AND(AA25>15000,AA25<15500),AA25,AND(AA25>=15500,AA25<$Z$1),15500,AA25>=$Z$1,AA25*$AB$2) -> 15300 | AC25: =round(IF($AA25<=$Z$1,($AA25-$AB25)*AC$1,$AA25*AC$2),-1) -> -520 | AD25: =round(IF($AA25<=$Z$1,($AA25-$AB25)*AD$1,$AA25*AD$2),-1)+AA25-AB25-AC25-round(IF($AA25<=$Z$1,($AA25-$AB25)*AD$1,$AA25*AD$2),-1) -> -780 | AE25: 0 | AF25: =IF(SUM(AB25:AE25)=AA25,"OK","NO") -> OK | AG25: =IF(U25="US",IF(AA25<9750,"Under","US OK"),IF(U25="S",IF(AA25<12000,"Under","S OK"),"Skill Missing")) -> Skill Missing | AH25: =VLOOKUP(A25,'Advance Sheet'!$A$4:$A$165,1,FALSE) -> #REF! | AI25: =IF(ISERROR(VLOOKUP(A25,'SNP Sal Main'!$A$3:$A1524,1,false))=FALSE,"SNP SAL",IF(ISERROR(VLOOKUP(A25,'Rest Sal Main org'!$A$3:$A1524,1,false))=FALSE,"Rest Sal","Not Found")) -> Not Found | AL25: =if(J25="","",datedif(J25,$AM$2,"Y")) -> 0 | AM25: =if(J25="","",datedif(J25,$AM$2,"M")) -> 10
A26: ITI1016 | B26: Monu | C26: Salary | D26: Machining | E26: ITI | F26: SNP | G26: 0.33333333 | H26: 0.75 | I26: =IF(ISBLANK(H26),,H26-G26) -> 0.41666667 | J26: 45979 | K26: SE | L26: =Y26 -> 14000 | M26: CS | N26: Employed | P26: 14000 | T26: YES | V26: =P26 -> 14000 | Y26: =if(W26="",V26,round(V26*(1+W26),-1)) -> 14000 | AA26: 14000 | AB26: =IFS(AND(AA26<=15000),15300,AND(AA26>15000,AA26<15500),AA26,AND(AA26>=15500,AA26<$Z$1),15500,AA26>=$Z$1,AA26*$AB$2) -> 15300 | AC26: =round(IF($AA26<=$Z$1,($AA26-$AB26)*AC$1,$AA26*AC$2),-1) -> -520 | AD26: =round(IF($AA26<=$Z$1,($AA26-$AB26)*AD$1,$AA26*AD$2),-1)+AA26-AB26-AC26-round(IF($AA26<=$Z$1,($AA26-$AB26)*AD$1,$AA26*AD$2),-1) -> -780 | AE26: 0 | AF26: =IF(SUM(AB26:AE26)=AA26,"OK","NO") -> OK | AG26: =IF(U26="US",IF(AA26<9750,"Under","US OK"),IF(U26="S",IF(AA26<12000,"Under","S OK"),"Skill Missing")) -> Skill Missing | AH26: =VLOOKUP(A26,'Advance Sheet'!$A$4:$A$165,1,FALSE) -> #REF! | AI26: =IF(ISERROR(VLOOKUP(A26,'SNP Sal Main'!$A$3:$A1525,1,false))=FALSE,"SNP SAL",IF(ISERROR(VLOOKUP(A26,'Rest Sal Main org'!$A$3:$A1525,1,false))=FALSE,"Rest Sal","Not Found")) -> Not Found | AL26: =if(J26="","",datedif(J26,$AM$2,"Y")) -> 0 | AM26: =if(J26="","",datedif(J26,$AM$2,"M")) -> 10
A27: MP1001 | B27: JASWANT SINGH MALI | C27: Salary | D27: Garden | E27: Mali | F27: SNP | G27: 0.33333333 | H27: 0.75 | I27: =IF(ISBLANK(H27),,H27-G27) -> 0.41666667 | J27: 43269 | K27: MULTIPACK | L27: =Y27 -> 17140 | M27: Chq | N27: Employed | O27: 45901 | P27: 15440 | T27: NO | U27: US | V27: =P27 -> 15440 | W27: 0.11 | Y27: =if(W27="",V27,round(V27*(1+W27),-1)) -> 17140 | AA27: =L27 -> 17140 | AB27: =IFS(AA27<=12000,AA27,AND(AA27>12000,AA27<=15200),15200,AND(AA27>15200,AA27<15500),AA27,AND(AA27>=15500,AA27<30000),15500,AA27>=30000,AA27*$AB$2) -> 15500 | AC27: =IF($AA27<=$Z$1,($AA27-$AB27)*AC$1,$AA27*AC$2) -> 656 | AD27: =round(IF($AA27<=$Z$1,($AA27-$AB27)*AD$1,$AA27*AD$2),-1)+AA27-AB27-AC27-round(IF($AA27<=$Z$1,($AA27-$AB27)*AD$1,$AA27*AD$2),-1) -> 984 | AE27: 0 | AF27: =IF(SUM(AB27:AE27)=AA27,"OK","NO") -> OK | AG27: =IF(U27="US",IF(AA27<9750,"Under","US OK"),IF(U27="S",IF(AA27<12000,"Under","S OK"),"Skill Missing")) -> US OK | AH27: =VLOOKUP(A27,'Advance Sheet'!$A$4:$A$165,1,FALSE) -> #REF! | AI27: =IF(ISERROR(VLOOKUP(A27,'SNP Sal Main'!$A$3:$A1526,1,false))=FALSE,"SNP SAL",IF(ISERROR(VLOOKUP(A27,'Rest Sal Main org'!$A$3:$A1526,1,false))=FALSE,"Rest Sal","Not Found")) -> Not Found | AJ27: N | AK27: Y | AM27: =if(J27="","",datedif(J27,$AM$2,"M")) -> 99
A28: SA1001 | B28: RAJESH PURI | C28: Prof | D28: Accounts & Finance | E28: Executive Accounts | F28: DEL | G28: 0.375 | H28: 0.77083333 | I28: =IF(ISBLANK(H28),,H28-G28) -> 0.39583333 | J28: 36678 | K28: SE | L28: =Y28 -> 75620 | M28: Chq | N28: Employed | O28: 45901 | P28: 70020 | Q28: 756 | T28: NO | V28: =P28 -> 70020 | W28: 0.08 | Y28: =if(W28="",V28,round(V28*(1+W28),-1)) -> 75620 | AA28: =L28 -> 75620 | AB28: =IFS(AA28<=12000,AA28,AND(AA28>12000,AA28<=15200),15200,AND(AA28>15200,AA28<15500),AA28,AND(AA28>=15500,AA28<30000),15500,AA28>=30000,AA28*$AB$2) -> 37810 | AC28: =IF($AA28<=$Z$1,($AA28-$AB28)*AC$1,$AA28*AC$2) -> 15124 | AD28: =round(IF($AA28<=$Z$1,($AA28-$AB28)*AD$1,$AA28*AD$2),-1)+AA28-AB28-AC28-round(IF($AA28<=$Z$1,($AA28-$AB28)*AD$1,$AA28*AD$2),-1) -> 22686 | AE28: 0 | AF28: =IF(SUM(AB28:AE28)=AA28,"OK","NO") -> OK | AG28: =IF(U28="US",IF(AA28<9750,"Under","US OK"),IF(U28="S",IF(AA28<12000,"Under","S OK"),"Skill Missing")) -> Skill Missing | AH28: =VLOOKUP(A28,'Advance Sheet'!$A$4:$A$165,1,FALSE) -> #REF! | AI28: =IF(ISERROR(VLOOKUP(A28,'SNP Sal Main'!$A$3:$A1527,1,false))=FALSE,"SNP SAL",IF(ISERROR(VLOOKUP(A28,'Rest Sal Main org'!$A$3:$A1527,1,false))=FALSE,"Rest Sal","Not Found")) -> Not Found | AJ28: N | AM28: =if(J28="","",datedif(J28,$AM$2,"M")) -> 315
A29: SE1001 | B29: NAVEEN CHANDRA | C29: Salary | D29: Cutting | E29: Supervisior | F29: SNP | G29: 0.33333333 | H29: 0.75 | I29: =IF(ISBLANK(H29),,H29-G29) -> 0.41666667 | J29: 41974 | K29: SE | L29: 37383 | M29: Chq | N29: Employed | O29: 45901 | P29: 36650 | T29: YES | U29: S | V29: =P29 -> 36650 | W29: 0.1 | Y29: =if(W29="",V29,round(V29*(1+W29),-1)) -> 40320 | AA29: =L29 -> 37383 | AB29: =roundup(IFS(AND(AA29<=15000),15300,AND(AA29>15000,AA29<15500),AA29,AND(AA29>=15500,AA29<$Z$1),15500,AA29>=$Z$1,AA29*$AB$2),0) -> 18692 | AC29: =round(IF($AA29<=$Z$1,($AA29-$AB29)*AC$1,$AA29*AC$2),-1) -> 7480 | AD29: =round(IF($AA29<=$Z$1,($AA29-$AB29)*AD$1,$AA29*AD$2),-1)+AA29-AB29-AC29-round(IF($AA29<=$Z$1,($AA29-$AB29)*AD$1,$AA29*AD$2),-1) -> 11211 | AE29: 0 | AF29: =IF(SUM(AB29:AE29)=AA29,"OK","NO") -> OK | AG29: =IF(U29="US",IF(AA29<9750,"Under","US OK"),IF(U29="S",IF(AA29<12000,"Under","S OK"),"Skill Missing")) -> S OK | AH29: =VLOOKUP(A29,'Advance Sheet'!$A$4:$A$165,1,FALSE) -> #REF! | AI29: =IF(ISERROR(VLOOKUP(A29,'SNP Sal Main'!$A$3:$A1528,1,false))=FALSE,"SNP SAL",IF(ISERROR(VLOOKUP(A29,'Rest Sal Main org'!$A$3:$A1528,1,false))=FALSE,"Rest Sal","Not Found")) -> Not Found | AK29: Y | AM29: =if(J29="","",datedif(J29,$AM$2,"M")) -> 141
A30: SE1002 | B30: KHAJAN SINGH RAWAT | C30: Salary | D30: Cutting | E30: Operator | F30: SNP | G30: 0.33333333 | H30: 0.75 | I30: =IF(ISBLANK(H30),,H30-G30) -> 0.41666667 | J30: 44275 | K30: SE | L30: 28470 | M30: Chq | N30: Employed | O30: 45901 | P30: 27640 | S30: YES | T30: YES | U30: S | V30: =P30 -> 27640 | W30: 0.1 | Y30: =if(W30="",V30,round(V30*(1+W30),-1)) -> 30400 | AA30: =L30 -> 28470 | AB30: =IFS(AND(AA30<=15000),15300,AND(AA30>15000,AA30<15500),AA30,AND(AA30>=15500,AA30<$Z$1),15500,AA30>=$Z$1,AA30*$AB$2) -> 15500 | AC30: =round(IF($AA30<=$Z$1,($AA30-$AB30)*AC$1,$AA30*AC$2),-1) -> 5190 | AD30: =round(IF($AA30<=$Z$1,($AA30-$AB30)*AD$1,$AA30*AD$2),-1)+AA30-AB30-AC30-round(IF($AA30<=$Z$1,($AA30-$AB30)*AD$1,$AA30*AD$2),-1) -> 7780 | AE30: 0 | AF30: =IF(SUM(AB30:AE30)=AA30,"OK","NO") -> OK | AG30: =IF(U30="US",IF(AA30<9750,"Under","US OK"),IF(U30="S",IF(AA30<12000,"Under","S OK"),"Skill Missing")) -> S OK | AH30: =VLOOKUP(A30,'Advance Sheet'!$A$4:$A$165,1,FALSE) -> #REF! | AI30: =IF(ISERROR(VLOOKUP(A30,'SNP Sal Main'!$A$3:$A1529,1,false))=FALSE,"SNP SAL",IF(ISERROR(VLOOKUP(A30,'Rest Sal Main org'!$A$3:$A1529,1,false))=FALSE,"Rest Sal","Not Found")) -> Not Found | AK30: Y | AM30: =if(J30="","",datedif(J30,$AM$2,"M")) -> 66
A31: SE1005 | B31: DEEPAK JOSHI | C31: Salary | D31: Cutting | E31: Operator | F31: SNP | G31: 0.33333333 | H31: 0.75 | I31: =IF(ISBLANK(H31),,H31-G31) -> 0.41666667 | J31: 41974 | K31: SE | L31: 31426 | M31: Chq | N31: Employed | O31: 45901 | P31: 30510 | T31: YES | U31: S | V31: =P31 -> 30510 | W31: 0.1 | Y31: =if(W31="",V31,round(V31*(1+W31),-1)) -> 33560 | AA31: =L31 -> 31426 | AB31: =IFS(AND(AA31<=15000),15300,AND(AA31>15000,AA31<15500),AA31,AND(AA31>=15500,AA31<$Z$1),15500,AA31>=$Z$1,AA31*$AB$2) -> 15500 | AC31: =round(IF($AA31<=$Z$1,($AA31-$AB31)*AC$1,$AA31*AC$2),-1) -> 6370 | AD31: =round(IF($AA31<=$Z$1,($AA31-$AB31)*AD$1,$AA31*AD$2),-1)+AA31-AB31-AC31-round(IF($AA31<=$Z$1,($AA31-$AB31)*AD$1,$AA31*AD$2),-1) -> 9556 | AE31: 0 | AF31: =IF(SUM(AB31:AE31)=AA31,"OK","NO") -> OK | AG31: =IF(U31="US",IF(AA31<9750,"Under","US OK"),IF(U31="S",IF(AA31<12000,"Under","S OK"),"Skill Missing")) -> S OK | AH31: =VLOOKUP(A31,'Advance Sheet'!$A$4:$A$165,1,FALSE) -> #REF! | AI31: =IF(ISERROR(VLOOKUP(A31,'SNP Sal Main'!$A$3:$A1530,1,false))=FALSE,"SNP SAL",IF(ISERROR(VLOOKUP(A31,'Rest Sal Main org'!$A$3:$A1530,1,false))=FALSE,"Rest Sal","Not Found")) -> Not Found | AK31: Y | AM31: =if(J31="","",datedif(J31,$AM$2,"M")) -> 141
A32: SE1007 | B32: AMBICA YADAV | C32: Salary | D32: Cutting | E32: Helper | F32: SNP | G32: 0.33333333 | H32: 0.75 | I32: =IF(ISBLANK(H32),,H32-G32) -> 0.41666667 | J32: 41974 | K32: SE | L32: 28573 | M32: Chq | N32: Employed | O32: 45901 | P32: 27740 | S32: YES | T32: YES | U32: US | V32: =P32 -> 27740 | W32: 0.11 | Y32: =if(W32="",V32,round(V32*(1+W32),-1)) -> 30790 | AA32: =L32 -> 28573 | AB32: =IFS(AND(AA32<=15000),15300,AND(AA32>15000,AA32<15500),AA32,AND(AA32>=15500,AA32<$Z$1),15500,AA32>=$Z$1,AA32*$AB$2) -> 15500 | AC32: =round(IF($AA32<=$Z$1,($AA32-$AB32)*AC$1,$AA32*AC$2),-1) -> 5230 | AD32: =round(IF($AA32<=$Z$1,($AA32-$AB32)*AD$1,$AA32*AD$2),-1)+AA32-AB32-AC32-round(IF($AA32<=$Z$1,($AA32-$AB32)*AD$1,$AA32*AD$2),-1) -> 7843 | AE32: 0 | AF32: =IF(SUM(AB32:AE32)=AA32,"OK","NO") -> OK | AG32: =IF(U32="US",IF(AA32<9750,"Under","US OK"),IF(U32="S",IF(AA32<12000,"Under","S OK"),"Skill Missing")) -> US OK | AH32: =VLOOKUP(A32,'Advance Sheet'!$A$4:$A$165,1,FALSE) -> #REF! | AI32: =IF(ISERROR(VLOOKUP(A32,'SNP Sal Main'!$A$3:$A1531,1,false))=FALSE,"SNP SAL",IF(ISERROR(VLOOKUP(A32,'Rest Sal Main org'!$A$3:$A1531,1,false))=FALSE,"Rest Sal","Not Found")) -> Not Found | AM32: =if(J32="","",datedif(J32,$AM$2,"M")) -> 141
A33: SE1008 | B33: ERADHEY SHYAM | C33: Salary | D33: Cutting | E33: Supervisior | F33: SNP | G33: 0.33333333 | H33: 0.75 | I33: =IF(ISBLANK(H33),,H33-G33) -> 0.41666667 | J33: 41977 | K33: SE | L33: 26894 | M33: Chq | N33: Employed | O33: 45901 | P33: 26110 | S33: YES | T33: YES | U33: US | V33: =P33 -> 26110 | W33: 0.11 | Y33: =if(W33="",V33,round(V33*(1+W33),-1)) -> 28980 | AA33: =L33 -> 26894 | AB33: =IFS(AND(AA33<=15000),15300,AND(AA33>15000,AA33<15500),AA33,AND(AA33>=15500,AA33<$Z$1),15500,AA33>=$Z$1,AA33*$AB$2) -> 15500 | AC33: =round(IF($AA33<=$Z$1,($AA33-$AB33)*AC$1,$AA33*AC$2),-1) -> 4560 | AD33: =round(IF($AA33<=$Z$1,($AA33-$AB33)*AD$1,$AA33*AD$2),-1)+AA33-AB33-AC33-round(IF($AA33<=$Z$1,($AA33-$AB33)*AD$1,$AA33*AD$2),-1) -> 6834 | AE33: 0 | AF33: =IF(SUM(AB33:AE33)=AA33,"OK","NO") -> OK | AG33: =IF(U33="US",IF(AA33<9750,"Under","US OK"),IF(U33="S",IF(AA33<12000,"Under","S OK"),"Skill Missing")) -> US OK | AH33: =VLOOKUP(A33,'Advance Sheet'!$A$4:$A$165,1,FALSE) -> #REF! | AI33: =IF(ISERROR(VLOOKUP(A33,'SNP Sal Main'!$A$3:$A1532,1,false))=FALSE,"SNP SAL",IF(ISERROR(VLOOKUP(A33,'Rest Sal Main org'!$A$3:$A1532,1,false))=FALSE,"Rest Sal","Not Found")) -> Not Found | AK33: Y | AM33: =if(J33="","",datedif(J33,$AM$2,"M")) -> 141
A34: SE1009 | B34: SATYENDRA RAM | C34: Salary | D34: Cutting | E34: Supervisior | F34: SNP | G34: 0.33333333 | H34: 0.75 | I34: =IF(ISBLANK(H34),,H34-G34) -> 0.41666667 | J34: 41974 | K34: SE | L34: 31364 | M34: Chq | N34: Employed | O34: 45901 | P34: 30450 | T34: YES | U34: S | V34: =P34 -> 30450 | W34: 0.1 | Y34: =if(W34="",V34,round(V34*(1+W34),-1)) -> 33500 | AA34: =L34 -> 31364 | AB34: =IFS(AND(AA34<=15000),15300,AND(AA34>15000,AA34<15500),AA34,AND(AA34>=15500,AA34<$Z$1),15500,AA34>=$Z$1,AA34*$AB$2) -> 15500 | AC34: =round(IF($AA34<=$Z$1,($AA34-$AB34)*AC$1,$AA34*AC$2),-1) -> 6350 | AD34: =round(IF($AA34<=$Z$1,($AA34-$AB34)*AD$1,$AA34*AD$2),-1)+AA34-AB34-AC34-round(IF($AA34<=$Z$1,($AA34-$AB34)*AD$1,$AA34*AD$2),-1) -> 9514 | AE34: 0 | AF34: =IF(SUM(AB34:AE34)=AA34,"OK","NO") -> OK | AG34: =IF(U34="US",IF(AA34<9750,"Under","US OK"),IF(U34="S",IF(AA34<12000,"Under","S OK"),"Skill Missing")) -> S OK | AH34: =VLOOKUP(A34,'Advance Sheet'!$A$4:$A$165,1,FALSE) -> #REF! | AI34: =IF(ISERROR(VLOOKUP(A34,'SNP Sal Main'!$A$3:$A1533,1,false))=FALSE,"SNP SAL",IF(ISERROR(VLOOKUP(A34,'Rest Sal Main org'!$A$3:$A1533,1,false))=FALSE,"Rest Sal","Not Found")) -> Not Found | AK34: Y | AM34: =if(J34="","",datedif(J34,$AM$2,"M")) -> 141
A35: SE1012 | B35: DADAN SHARMA | C35: Salary | D35: Cutting | E35: Operator | F35: SNP | G35: 0.33333333 | H35: 0.75 | I35: =IF(ISBLANK(H35),,H35-G35) -> 0.41666667 | J35: 41978 | K35: SE | L35: 31364 | M35: Chq | N35: Employed | O35: 45901 | P35: 30450 | T35: YES | U35: S | V35: =P35 -> 30450 | W35: 0.1 | Y35: =if(W35="",V35,round(V35*(1+W35),-1)) -> 33500 | AA35: =L35 -> 31364 | AB35: =IFS(AND(AA35<=15000),15300,AND(AA35>15000,AA35<15500),AA35,AND(AA35>=15500,AA35<$Z$1),15500,AA35>=$Z$1,AA35*$AB$2) -> 15500 | AC35: =round(IF($AA35<=$Z$1,($AA35-$AB35)*AC$1,$AA35*AC$2),-1) -> 6350 | AD35: =round(IF($AA35<=$Z$1,($AA35-$AB35)*AD$1,$AA35*AD$2),-1)+AA35-AB35-AC35-round(IF($AA35<=$Z$1,($AA35-$AB35)*AD$1,$AA35*AD$2),-1) -> 9514 | AE35: 0 | AF35: =IF(SUM(AB35:AE35)=AA35,"OK","NO") -> OK | AG35: =IF(U35="US",IF(AA35<9750,"Under","US OK"),IF(U35="S",IF(AA35<12000,"Under","S OK"),"Skill Missing")) -> S OK | AH35: =VLOOKUP(A35,'Advance Sheet'!$A$4:$A$165,1,FALSE) -> #REF! | AI35: =IF(ISERROR(VLOOKUP(A35,'SNP Sal Main'!$A$3:$A1534,1,false))=FALSE,"SNP SAL",IF(ISERROR(VLOOKUP(A35,'Rest Sal Main org'!$A$3:$A1534,1,false))=FALSE,"Rest Sal","Not Found")) -> Not Found | AJ35: Y | AK35: Y | AM35: =if(J35="","",datedif(J35,$AM$2,"M")) -> 141
A36: SE1020 | B36: RAJENDRA PRASHAD JOSHI | C36: Salary | D36: Cutting | E36: Operator | F36: SNP | G36: 0.33333333 | H36: 0.75 | I36: =IF(ISBLANK(H36),,H36-G36) -> 0.41666667 | J36: 41944 | K36: SE | L36: 22134 | M36: Chq | N36: Employed | O36: 45901 | P36: 18990 | S36: YES | T36: YES | U36: S | V36: =P36 -> 18990 | W36: 0.11 | Y36: =if(W36="",V36,round(V36*(1+W36),-1)) -> 21080 | AA36: 22134 | AB36: =IFS(AND(AA36<=15000),15300,AND(AA36>15000,AA36<15500),AA36,AND(AA36>=15500,AA36<$Z$1),15500,AA36>=$Z$1,AA36*$AB$2) -> 15500 | AC36: =round(IF($AA36<=$Z$1,($AA36-$AB36)*AC$1,$AA36*AC$2),-1) -> 2650 | AD36: =round(IF($AA36<=$Z$1,($AA36-$AB36)*AD$1,$AA36*AD$2),-1)+AA36-AB36-AC36-round(IF($AA36<=$Z$1,($AA36-$AB36)*AD$1,$AA36*AD$2),-1) -> 3984 | AE36: 0 | AF36: =IF(SUM(AB36:AE36)=AA36,"OK","NO") -> OK | AG36: =IF(U36="US",IF(AA36<9750,"Under","US OK"),IF(U36="S",IF(AA36<12000,"Under","S OK"),"Skill Missing")) -> S OK | AH36: =VLOOKUP(A36,'Advance Sheet'!$A$4:$A$165,1,FALSE) -> #REF! | AI36: =IF(ISERROR(VLOOKUP(A36,'SNP Sal Main'!$A$3:$A1535,1,false))=FALSE,"SNP SAL",IF(ISERROR(VLOOKUP(A36,'Rest Sal Main org'!$A$3:$A1535,1,false))=FALSE,"Rest Sal","Not Found")) -> Not Found | AK36: Y | AM36: =if(J36="","",datedif(J36,$AM$2,"M")) -> 142
A37: SE1021 | B37: RAVI RAUSHAN KUMAR | C37: Salary | D37: Cutting | E37: Helper | F37: SNP | G37: 0.33333333 | H37: 0.75 | I37: =IF(ISBLANK(H37),,H37-G37) -> 0.41666667 | J37: 41621 | K37: SE | L37: 22470 | M37: Chq | N37: Employed | O37: 45901 | P37: 19280 | S37: YES | T37: YES | U37: US | V37: =P37 -> 19280 | W37: 0.11 | Y37: =if(W37="",V37,round(V37*(1+W37),-1)) -> 21400 | AA37: =L37 -> 22470 | AB37: =IFS(AND(AA37<=15000),15300,AND(AA37>15000,AA37<15500),AA37,AND(AA37>=15500,AA37<$Z$1),15500,AA37>=$Z$1,AA37*$AB$2) -> 15500 | AC37: =round(IF($AA37<=$Z$1,($AA37-$AB37)*AC$1,$AA37*AC$2),-1) -> 2790 | AD37: =round(IF($AA37<=$Z$1,($AA37-$AB37)*AD$1,$AA37*AD$2),-1)+AA37-AB37-AC37-round(IF($AA37<=$Z$1,($AA37-$AB37)*AD$1,$AA37*AD$2),-1) -> 4180 | AE37: 0 | AF37: =IF(SUM(AB37:AE37)=AA37,"OK","NO") -> OK | AG37: =IF(U37="US",IF(AA37<9750,"Under","US OK"),IF(U37="S",IF(AA37<12000,"Under","S OK"),"Skill Missing")) -> US OK | AH37: =VLOOKUP(A37,'Advance Sheet'!$A$4:$A$165,1,FALSE) -> #REF! | AI37: =IF(ISERROR(VLOOKUP(A37,'SNP Sal Main'!$A$3:$A1536,1,false))=FALSE,"SNP SAL",IF(ISERROR(VLOOKUP(A37,'Rest Sal Main org'!$A$3:$A1536,1,false))=FALSE,"Rest Sal","Not Found")) -> Not Found | AK37: Y | AM37: =if(J37="","",datedif(J37,$AM$2,"M")) -> 153
A38: SE1024 | B38: PRABHAT KUMAR SHRIVASTWA | C38: Salary | D38: Sales & Marketing | E38: Sales & Marketing | F38: DEL | G38: 0.41666667 | H38: 0.79166667 | I38: =IF(ISBLANK(H38),,H38-G38) -> 0.375 | J38: 41634 | K38: SE | L38: =Y38 -> 46770 | M38: Chq | N38: Employed | O38: 45901 | P38: 42910 | T38: NO | U38: S | V38: =P38 -> 42910 | W38: 0.09 | Y38: =if(W38="",V38,round(V38*(1+W38),-1)) -> 46770 | AA38: =L38 -> 46770 | AB38: =IFS(AND(AA38<=15000),15300,AND(AA38>15000,AA38<15500),AA38,AND(AA38>=15500,AA38<$Z$1),15500,AA38>=$Z$1,AA38*$AB$2) -> 23385 | AC38: =round(IF($AA38<=$Z$1,($AA38-$AB38)*AC$1,$AA38*AC$2),-1) -> 9350 | AD38: =round(IF($AA38<=$Z$1,($AA38-$AB38)*AD$1,$AA38*AD$2),-1)+AA38-AB38-AC38-round(IF($AA38<=$Z$1,($AA38-$AB38)*AD$1,$AA38*AD$2),-1) -> 14035 | AE38: 0 | AF38: =IF(SUM(AB38:AE38)=AA38,"OK","NO") -> OK | AG38: =IF(U38="US",IF(AA38<9750,"Under","US OK"),IF(U38="S",IF(AA38<12000,"Under","S OK"),"Skill Missing")) -> S OK | AH38: =VLOOKUP(A38,'Advance Sheet'!$A$4:$A$165,1,FALSE) -> #REF! | AI38: =IF(ISERROR(VLOOKUP(A38,'SNP Sal Main'!$A$3:$A1537,1,false))=FALSE,"SNP SAL",IF(ISERROR(VLOOKUP(A38,'Rest Sal Main org'!$A$3:$A1537,1,false))=FALSE,"Rest Sal","Not Found")) -> Not Found | AM38: =if(J38="","",datedif(J38,$AM$2,"M")) -> 153
A39: SE1031 | B39: JAGDISH RAI BAHL | C39: Salary | D39: Management | E39: Sales & Marketing | F39: DEL | G39: 0.375 | H39: 0.75 | I39: =IF(ISBLANK(H39),,H39-G39) -> 0.375 | J39: 42248 | K39: SE | L39: =Y39 -> 221230 | M39: Chq | N39: Employed | O39: 45901 | P39: 204840 | Q39: 39870 | T39: NO | V39: =P39 -> 204840 | W39: 0.08 | Y39: =if(W39="",V39,round(V39*(1+W39),-1)) -> 221230 | AA39: =L39 -> 221230 | AB39: =IFS(AND(AA39<=15000),15300,AND(AA39>15000,AA39<15500),AA39,AND(AA39>=15500,AA39<$Z$1),15500,AA39>=$Z$1,AA39*$AB$2) -> 110615 | AC39: =round(IF($AA39<=$Z$1,($AA39-$AB39)*AC$1,$AA39*AC$2),-1) -> 44250 | AD39: =round(IF($AA39<=$Z$1,($AA39-$AB39)*AD$1,$AA39*AD$2),-1)+AA39-AB39-AC39-round(IF($AA39<=$Z$1,($AA39-$AB39)*AD$1,$AA39*AD$2),-1) -> 66365 | AE39: 0 | AF39: =IF(SUM(AB39:AE39)=AA39,"OK","NO") -> OK | AG39: =IF(U39="US",IF(AA39<9750,"Under","US OK"),IF(U39="S",IF(AA39<12000,"Under","S OK"),"Skill Missing")) -> Skill Missing | AH39: =VLOOKUP(A39,'Advance Sheet'!$A$4:$A$165,1,FALSE) -> #REF! | AI39: =IF(ISERROR(VLOOKUP(A39,'SNP Sal Main'!$A$3:$A1538,1,false))=FALSE,"SNP SAL",IF(ISERROR(VLOOKUP(A39,'Rest Sal Main org'!$A$3:$A1538,1,false))=FALSE,"Rest Sal","Not Found")) -> Not Found | AM39: =if(J39="","",datedif(J39,$AM$2,"M")) -> 132
A40: SE1036 | B40: PRANAV JAIN | C40: Salary | D40: Office | E40: Misc | F40: DEL | G40: 0.375 | H40: 0.75 | I40: =IF(ISBLANK(H40),,H40-G40) -> 0.375 | J40: 42248 | K40: SE | L40: 80000 | M40: Chq | N40: Employed | O40: 45748 | P40: 75000 | T40: NO | V40: =P40 -> 75000 | W40: 0 | Y40: =if(W40="",V40,round(V40*(1+W40),-1)) -> 75000 | AA40: =L40 -> 80000 | AB40: 58850 | AC40: 16150 | AD40: =round(IF($AA40<=$Z$1,($AA40-$AB40)*AD$1,$AA40*AD$2),-1)+AA40-AB40-AC40-round(IF($AA40<=$Z$1,($AA40-$AB40)*AD$1,$AA40*AD$2),-1) -> 5000 | AE40: 0 | AF40: =IF(SUM(AB40:AE40)=AA40,"OK","NO") -> OK | AG40: =IF(U40="US",IF(AA40<9750,"Under","US OK"),IF(U40="S",IF(AA40<12000,"Under","S OK"),"Skill Missing")) -> Skill Missing | AH40: =VLOOKUP(A40,'Advance Sheet'!$A$4:$A$165,1,FALSE) -> #REF! | AI40: =IF(ISERROR(VLOOKUP(A40,'SNP Sal Main'!$A$3:$A1539,1,false))=FALSE,"SNP SAL",IF(ISERROR(VLOOKUP(A40,'Rest Sal Main org'!$A$3:$A1539,1,false))=FALSE,"Rest Sal","Not Found")) -> Not Found | AM40: =if(J40="","",datedif(J40,$AM$2,"M")) -> 132
A41: SE1037 | B41: SHWETA JAIN | C41: Salary | D41: Office | E41: Misc | F41: DEL | G41: 0.375 | H41: 0.75 | I41: =IF(ISBLANK(H41),,H41-G41) -> 0.375 | J41: 42248 | K41: SE | L41: 60000 | M41: Chq | N41: Employed | O41: 45170 | P41: 47520 | T41: NO | V41: =P41 -> 47520 | W41: 0 | Y41: =if(W41="",V41,round(V41*(1+W41),-1)) -> 47520 | AA41: =L41 -> 60000 | AB41: 60000 | AE41: 0 | AF41: =IF(SUM(AB41:AE41)=AA41,"OK","NO") -> OK | AG41: =IF(U41="US",IF(AA41<9750,"Under","US OK"),IF(U41="S",IF(AA41<12000,"Under","S OK"),"Skill Missing")) -> Skill Missing | AH41: =VLOOKUP(A41,'Advance Sheet'!$A$4:$A$165,1,FALSE) -> #REF! | AI41: =IF(ISERROR(VLOOKUP(A41,'SNP Sal Main'!$A$3:$A1540,1,false))=FALSE,"SNP SAL",IF(ISERROR(VLOOKUP(A41,'Rest Sal Main org'!$A$3:$A1540,1,false))=FALSE,"Rest Sal","Not Found")) -> Not Found | AM41: =if(J41="","",datedif(J41,$AM$2,"M")) -> 132
A42: SE1040 | B42: SONU MALI | C42: Salary | D42: Driver | E42: Hydra | F42: SNP | G42: 0.33333333 | H42: 0.75 | I42: =IF(ISBLANK(H42),,H42-G42) -> 0.41666667 | J42: 42278 | K42: SE | L42: 31106 | M42: Chq | N42: Employed | O42: 45901 | P42: 30200 | S42: YES | T42: YES | U42: S | V42: =P42 -> 30200 | W42: 0.1 | Y42: =if(W42="",V42,round(V42*(1+W42),-1)) -> 33220 | AA42: =L42 -> 31106 | AB42: =IFS(AND(AA42<=15000),15300,AND(AA42>15000,AA42<15500),AA42,AND(AA42>=15500,AA42<$Z$1),15500,AA42>=$Z$1,AA42*$AB$2) -> 15500 | AC42: =round(IF($AA42<=$Z$1,($AA42-$AB42)*AC$1,$AA42*AC$2),-1) -> 6240 | AD42: =round(IF($AA42<=$Z$1,($AA42-$AB42)*AD$1,$AA42*AD$2),-1)+AA42-AB42-AC42-round(IF($AA42<=$Z$1,($AA42-$AB42)*AD$1,$AA42*AD$2),-1) -> 9366 | AE42: 0 | AF42: =IF(SUM(AB42:AE42)=AA42,"OK","NO") -> OK | AG42: =IF(U42="US",IF(AA42<9750,"Under","US OK"),IF(U42="S",IF(AA42<12000,"Under","S OK"),"Skill Missing")) -> S OK | AH42: =VLOOKUP(A42,'Advance Sheet'!$A$4:$A$165,1,FALSE) -> #REF! | AI42: =IF(ISERROR(VLOOKUP(A42,'SNP Sal Main'!$A$3:$A1541,1,false))=FALSE,"SNP SAL",IF(ISERROR(VLOOKUP(A42,'Rest Sal Main org'!$A$3:$A1541,1,false))=FALSE,"Rest Sal","Not Found")) -> Not Found | AM42: =if(J42="","",datedif(J42,$AM$2,"M")) -> 131
A43: SE1043 | B43: AMIT KUMAR | C43: Salary | D43: Accounts & Finance | E43: Executive Accounts | F43: SNP | G43: 0.375 | H43: 0.77083333 | I43: =IF(ISBLANK(H43),,H43-G43) -> 0.39583333 | J43: 42058 | K43: SE | L43: =Y43 -> 34620 | M43: Chq | N43: Employed | O43: 45901 | P43: 31470 | S43: YES | T43: NO | U43: S | V43: =P43 -> 31470 | W43: 0.1 | Y43: =if(W43="",V43,round(V43*(1+W43),-1)) -> 34620 | AA43: =L43 -> 34620 | AB43: =IFS(AND(AA43<=15000),15300,AND(AA43>15000,AA43<15500),AA43,AND(AA43>=15500,AA43<$Z$1),15500,AA43>=$Z$1,AA43*$AB$2) -> 15500 | AC43: =round(IF($AA43<=$Z$1,($AA43-$AB43)*AC$1,$AA43*AC$2),-1) -> 7650 | AD43: =round(IF($AA43<=$Z$1,($AA43-$AB43)*AD$1,$AA43*AD$2),-1)+AA43-AB43-AC43-round(IF($AA43<=$Z$1,($AA43-$AB43)*AD$1,$AA43*AD$2),-1) -> 11470 | AE43: 0 | AF43: =IF(SUM(AB43:AE43)=AA43,"OK","NO") -> OK | AG43: =IF(U43="US",IF(AA43<9750,"Under","US OK"),IF(U43="S",IF(AA43<12000,"Under","S OK"),"Skill Missing")) -> S OK | AH43: =VLOOKUP(A43,'Advance Sheet'!$A$4:$A$165,1,FALSE) -> #REF! | AI43: =IF(ISERROR(VLOOKUP(A43,'SNP Sal Main'!$A$3:$A1542,1,false))=FALSE,"SNP SAL",IF(ISERROR(VLOOKUP(A43,'Rest Sal Main org'!$A$3:$A1542,1,false))=FALSE,"Rest Sal","Not Found")) -> Not Found | AJ43: N | AM43: =if(J43="","",datedif(J43,$AM$2,"M")) -> 139
A44: SE1048 | B44: ANIL YADAV | C44: Salary | D44: Cutting | E44: Operator | F44: MUM | G44: 0.375 | H44: 0.79166667 | I44: =IF(ISBLANK(H44),,H44-G44) -> 0.41666667 | J44: 42230 | K44: SE | L44: =Y44 -> 25130 | M44: Chq | N44: Employed | O44: 45901 | P44: 22640 | S44: YES | T44: YES | U44: S | V44: =P44 -> 22640 | W44: 0.11 | Y44: =if(W44="",V44,round(V44*(1+W44),-1)) -> 25130 | AA44: =L44 -> 25130 | AB44: 11700 | AC44: =round(IF($AA44<=$Z$1,($AA44-$AB44)*AC$1,$AA44*AC$2),-1) -> 5370 | AD44: =round(IF($AA44<=$Z$1,($AA44-$AB44)*AD$1,$AA44*AD$2),-1)+AA44-AB44-AC44-round(IF($AA44<=$Z$1,($AA44-$AB44)*AD$1,$AA44*AD$2),-1) -> 8060 | AE44: 0 | AF44: =IF(SUM(AB44:AE44)=AA44,"OK","NO") -> OK | AG44: =IF(U44="US",IF(AA44<9750,"Under","US OK"),IF(U44="S",IF(AA44<12000,"Under","S OK"),"Skill Missing")) -> S OK | AH44: =VLOOKUP(A44,'Advance Sheet'!$A$4:$A$165,1,FALSE) -> #REF! | AI44: =IF(ISERROR(VLOOKUP(A44,'SNP Sal Main'!$A$3:$A1543,1,false))=FALSE,"SNP SAL",IF(ISERROR(VLOOKUP(A44,'Rest Sal Main org'!$A$3:$A1543,1,false))=FALSE,"Rest Sal","Not Found")) -> Not Found | AM44: =if(J44="","",datedif(J44,$AM$2,"M")) -> 133
A45: SE1049 | B45: BABOO RAM | C45: Salary | D45: Backend Ops | E45: Executive | F45: DEL | G45: 0.375 | H45: 0.77083333 | I45: =IF(ISBLANK(H45),,H45-G45) -> 0.39583333 | J45: 42583 | K45: SE | L45: =Y45 -> 22320 | M45: Chq | N45: Employed | O45: 45901 | P45: 20110 | S45: YES | T45: NO | U45: S | V45: =P45 -> 20110 | W45: 0.11 | Y45: =if(W45="",V45,round(V45*(1+W45),-1)) -> 22320 | AA45: =L45 -> 22320 | AB45: 11700 | AC45: =round(IF($AA45<=$Z$1,($AA45-$AB45)*AC$1,$AA45*AC$2),-1) -> 4250 | AD45: =round(IF($AA45<=$Z$1,($AA45-$AB45)*AD$1,$AA45*AD$2),-1)+AA45-AB45-AC45-round(IF($AA45<=$Z$1,($AA45-$AB45)*AD$1,$AA45*AD$2),-1) -> 6370 | AE45: 0 | AF45: =IF(SUM(AB45:AE45)=AA45,"OK","NO") -> OK | AG45: =IF(U45="US",IF(AA45<9750,"Under","US OK"),IF(U45="S",IF(AA45<12000,"Under","S OK"),"Skill Missing")) -> S OK | AH45: =VLOOKUP(A45,'Advance Sheet'!$A$4:$A$165,1,FALSE) -> #REF! | AI45: =IF(ISERROR(VLOOKUP(A45,'SNP Sal Main'!$A$3:$A1544,1,false))=FALSE,"SNP SAL",IF(ISERROR(VLOOKUP(A45,'Rest Sal Main org'!$A$3:$A1544,1,false))=FALSE,"Rest Sal","Not Found")) -> Not Found | AM45: =if(J45="","",datedif(J45,$AM$2,"M")) -> 121
A46: SE1052 | B46: DILIP KUMAR MANDAL | C46: Salary | D46: Backend Ops | E46: Field | F46: DEL | G46: 0.39583333 | H46: 0.79166667 | I46: =IF(ISBLANK(H46),,H46-G46) -> 0.39583333 | J46: 42095 | K46: SE | L46: =Y46 -> 27240 | M46: Chq | N46: Employed | O46: 45901 | P46: 24540 | S46: YES | T46: NO | U46: S | V46: =P46 -> 24540 | W46: 0.11 | Y46: =if(W46="",V46,round(V46*(1+W46),-1)) -> 27240 | AA46: =L46 -> 27240 | AB46: 12000 | AC46: =round(IF($AA46<=$Z$1,($AA46-$AB46)*AC$1,$AA46*AC$2),-1) -> 6100 | AD46: =round(IF($AA46<=$Z$1,($AA46-$AB46)*AD$1,$AA46*AD$2),-1)+AA46-AB46-AC46-round(IF($AA46<=$Z$1,($AA46-$AB46)*AD$1,$AA46*AD$2),-1) -> 9140 | AE46: 0 | AF46: =IF(SUM(AB46:AE46)=AA46,"OK","NO") -> OK | AG46: =IF(U46="US",IF(AA46<9750,"Under","US OK"),IF(U46="S",IF(AA46<12000,"Under","S OK"),"Skill Missing")) -> S OK | AH46: =VLOOKUP(A46,'Advance Sheet'!$A$4:$A$165,1,FALSE) -> #REF! | AI46: =IF(ISERROR(VLOOKUP(A46,'SNP Sal Main'!$A$3:$A1545,1,false))=FALSE,"SNP SAL",IF(ISERROR(VLOOKUP(A46,'Rest Sal Main org'!$A$3:$A1545,1,false))=FALSE,"Rest Sal","Not Found")) -> Not Found | AM46: =if(J46="","",datedif(J46,$AM$2,"M")) -> 137
A47: SE1056 | B47: JITENDER | C47: Salary | D47: Backend Sales & Ops | E47: HOD | F47: SNP | G47: 0.375 | H47: 0.77083333 | I47: =IF(ISBLANK(H47),,H47-G47) -> 0.39583333 | J47: 42548 | K47: SE | L47: =Y47 -> 29960 | M47: Chq | N47: Employed | O47: 45901 | P47: 27240 | T47: NO | U47: S | V47: =P47 -> 27240 | W47: 0.1 | Y47: =if(W47="",V47,round(V47*(1+W47),-1)) -> 29960 | AA47: =L47 -> 29960 | AB47: 13200 | AC47: =round(IF($AA47<=$Z$1,($AA47-$AB47)*AC$1,$AA47*AC$2),-1) -> 6700 | AD47: =round(IF($AA47<=$Z$1,($AA47-$AB47)*AD$1,$AA47*AD$2),-1)+AA47-AB47-AC47-round(IF($AA47<=$Z$1,($AA47-$AB47)*AD$1,$AA47*AD$2),-1) -> 10060 | AE47: 0 | AF47: =IF(SUM(AB47:AE47)=AA47,"OK","NO") -> OK | AG47: =IF(U47="US",IF(AA47<9750,"Under","US OK"),IF(U47="S",IF(AA47<12000,"Under","S OK"),"Skill Missing")) -> S OK | AH47: =VLOOKUP(A47,'Advance Sheet'!$A$4:$A$165,1,FALSE) -> #REF! | AI47: =IF(ISERROR(VLOOKUP(A47,'SNP Sal Main'!$A$3:$A1546,1,false))=FALSE,"SNP SAL",IF(ISERROR(VLOOKUP(A47,'Rest Sal Main org'!$A$3:$A1546,1,false))=FALSE,"Rest Sal","Not Found")) -> Not Found | AM47: =if(J47="","",datedif(J47,$AM$2,"M")) -> 123
A48: SE1065 | B48: LALAN MEHTO | C48: Salary | D48: Cutting | E48: Helper | F48: SNP | G48: 0.33333333 | H48: 0.75 | I48: =IF(ISBLANK(H48),,H48-G48) -> 0.41666667 | J48: 42033 | K48: SE | L48: 18333 | M48: Chq | N48: Employed | O48: 45901 | P48: 15730 | S48: YES | T48: YES | U48: US | V48: =P48 -> 15730 | W48: 0.11 | Y48: =if(W48="",V48,round(V48*(1+W48),-1)) -> 17460 | AA48: =L48 -> 18333 | AB48: =IFS(AND(AA48<=15000),15300,AND(AA48>15000,AA48<15500),AA48,AND(AA48>=15500,AA48<$Z$1),15500,AA48>=$Z$1,AA48*$AB$2) -> 15500 | AC48: =round(IF($AA48<=$Z$1,($AA48-$AB48)*AC$1,$AA48*AC$2),-1) -> 1130 | AD48: =round(IF($AA48<=$Z$1,($AA48-$AB48)*AD$1,$AA48*AD$2),-1)+AA48-AB48-AC48-round(IF($AA48<=$Z$1,($AA48-$AB48)*AD$1,$AA48*AD$2),-1) -> 1703 | AE48: 0 | AF48: =IF(SUM(AB48:AE48)=AA48,"OK","NO") -> OK | AG48: =IF(U48="US",IF(AA48<9750,"Under","US OK"),IF(U48="S",IF(AA48<12000,"Under","S OK"),"Skill Missing")) -> US OK | AH48: =VLOOKUP(A48,'Advance Sheet'!$A$4:$A$165,1,FALSE) -> #REF! | AI48: =IF(ISERROR(VLOOKUP(A48,'SNP Sal Main'!$A$3:$A1547,1,false))=FALSE,"SNP SAL",IF(ISERROR(VLOOKUP(A48,'Rest Sal Main org'!$A$3:$A1547,1,false))=FALSE,"Rest Sal","Not Found")) -> Not Found | AK48: Y | AM48: =if(J48="","",datedif(J48,$AM$2,"M")) -> 139
A49: SE1069 | B49: VINAY KUMAR | C49: Salary | D49: Accounts & Finance | E49: GST | F49: DEL | G49: 0.375 | H49: 0.77083333 | I49: =IF(ISBLANK(H49),,H49-G49) -> 0.39583333 | J49: 40940 | K49: SE | L49: =Y49 -> 55540 | M49: Chq | N49: Employed | O49: 45901 | P49: 51430 | T49: NO | U49: S | V49: =P49 -> 51430 | W49: 0.08 | Y49: =if(W49="",V49,round(V49*(1+W49),-1)) -> 55540 | AA49: =L49 -> 55540 | AB49: =IFS(AND(AA49<=15000),15300,AND(AA49>15000,AA49<15500),AA49,AND(AA49>=15500,AA49<$Z$1),15500,AA49>=$Z$1,AA49*$AB$2) -> 27770 | AC49: =round(IF($AA49<=$Z$1,($AA49-$AB49)*AC$1,$AA49*AC$2),-1) -> 11110 | AD49: =round(IF($AA49<=$Z$1,($AA49-$AB49)*AD$1,$AA49*AD$2),-1)+AA49-AB49-AC49-round(IF($AA49<=$Z$1,($AA49-$AB49)*AD$1,$AA49*AD$2),-1) -> 16660 | AE49: 0 | AF49: =IF(SUM(AB49:AE49)=AA49,"OK","NO") -> OK | AG49: =IF(U49="US",IF(AA49<9750,"Under","US OK"),IF(U49="S",IF(AA49<12000,"Under","S OK"),"Skill Missing")) -> S OK | AH49: =VLOOKUP(A49,'Advance Sheet'!$A$4:$A$165,1,FALSE) -> #REF! | AI49: =IF(ISERROR(VLOOKUP(A49,'SNP Sal Main'!$A$3:$A1548,1,false))=FALSE,"SNP SAL",IF(ISERROR(VLOOKUP(A49,'Rest Sal Main org'!$A$3:$A1548,1,false))=FALSE,"Rest Sal","Not Found")) -> Not Found | AM49: =if(J49="","",datedif(J49,$AM$2,"M")) -> 175
A50: SE1070 | B50: VIKASH SHARMA | C50: Salary | D50: Cutting | E50: Manager | F50: SNP | G50: 0.375 | H50: 0.77083333 | I50: =IF(ISBLANK(H50),,H50-G50) -> 0.39583333 | J50: 41000 | K50: SE | L50: =Y50 -> 56410 | M50: Chq | N50: Employed | O50: 45901 | P50: 52230 | T50: NO | U50: S | V50: =P50 -> 52230 | W50: 0.08 | Y50: =if(W50="",V50,round(V50*(1+W50),-1)) -> 56410 | AA50: =L50 -> 56410 | AB50: =IFS(AND(AA50<=15000),15300,AND(AA50>15000,AA50<15500),AA50,AND(AA50>=15500,AA50<$Z$1),15500,AA50>=$Z$1,AA50*$AB$2) -> 28205 | AC50: =round(IF($AA50<=$Z$1,($AA50-$AB50)*AC$1,$AA50*AC$2),-1) -> 11280 | AD50: =round(IF($AA50<=$Z$1,($AA50-$AB50)*AD$1,$AA50*AD$2),-1)+AA50-AB50-AC50-round(IF($AA50<=$Z$1,($AA50-$AB50)*AD$1,$AA50*AD$2),-1) -> 16925 | AE50: 0 | AF50: =IF(SUM(AB50:AE50)=AA50,"OK","NO") -> OK | AG50: =IF(U50="US",IF(AA50<9750,"Under","US OK"),IF(U50="S",IF(AA50<12000,"Under","S OK"),"Skill Missing")) -> S OK | AH50: =VLOOKUP(A50,'Advance Sheet'!$A$4:$A$165,1,FALSE) -> #REF! | AI50: =IF(ISERROR(VLOOKUP(A50,'SNP Sal Main'!$A$3:$A1549,1,false))=FALSE,"SNP SAL",IF(ISERROR(VLOOKUP(A50,'Rest Sal Main org'!$A$3:$A1549,1,false))=FALSE,"Rest Sal","Not Found")) -> Not Found | AM50: =if(J50="","",datedif(J50,$AM$2,"M")) -> 173
A51: SE1073 | B51: SANDEEP JAIN | C51: Salary | D51: Management | E51: MD | F51: DEL | G51: 0.375 | H51: 0.75 | I51: =IF(ISBLANK(H51),,H51-G51) -> 0.375 | J51: 41000 | K51: SE | L51: =Y51 -> 250000 | M51: Chq | N51: Employed | P51: 250000 | Q51: 72150 | T51: NO | V51: =P51 -> 250000 | W51: 0 | Y51: =if(W51="",V51,round(V51*(1+W51),-1)) -> 250000 | AA51: =L51 -> 250000 | AB51: =150000+100000 -> 250000 | AE51: 0 | AF51: =IF(SUM(AB51:AE51)=AA51,"OK","NO") -> OK | AG51: =IF(U51="US",IF(AA51<9750,"Under","US OK"),IF(U51="S",IF(AA51<12000,"Under","S OK"),"Skill Missing")) -> Skill Missing | AH51: =VLOOKUP(A51,'Advance Sheet'!$A$4:$A$165,1,FALSE) -> #REF! | AI51: =IF(ISERROR(VLOOKUP(A51,'SNP Sal Main'!$A$3:$A1550,1,false))=FALSE,"SNP SAL",IF(ISERROR(VLOOKUP(A51,'Rest Sal Main org'!$A$3:$A1550,1,false))=FALSE,"Rest Sal","Not Found")) -> Not Found | AM51: =if(J51="","",datedif(J51,$AM$2,"M")) -> 173
A52: SE1082 | B52: REKHA B.S. | C52: Salary | D52: Office | E52: Mis | F52: DEL | G52: 0.375 | H52: 0.75 | I52: =IF(ISBLANK(H52),,H52-G52) -> 0.375 | J52: 42156 | K52: SE | L52: =Y52 -> 30000 | M52: Chq | N52: Employed | O52: 45170 | P52: 30000 | T52: NO | V52: =P52 -> 30000 | W52: 0 | Y52: =if(W52="",V52,round(V52*(1+W52),-1)) -> 30000 | AA52: =L52 -> 30000 | AB52: 25000 | AC52: =round(IF($AA52<=$Z$1,($AA52-$AB52)*AC$1,$AA52*AC$2),-1) -> 2000 | AD52: =round(IF($AA52<=$Z$1,($AA52-$AB52)*AD$1,$AA52*AD$2),-1)+AA52-AB52-AC52-round(IF($AA52<=$Z$1,($AA52-$AB52)*AD$1,$AA52*AD$2),-1) -> 3000 | AE52: 0 | AF52: =IF(SUM(AB52:AE52)=AA52,"OK","NO") -> OK | AG52: =IF(U52="US",IF(AA52<9750,"Under","US OK"),IF(U52="S",IF(AA52<12000,"Under","S OK"),"Skill Missing")) -> Skill Missing | AH52: =VLOOKUP(A52,'Advance Sheet'!$A$4:$A$165,1,FALSE) -> #REF! | AI52: =IF(ISERROR(VLOOKUP(A52,'SNP Sal Main'!$A$3:$A1551,1,false))=FALSE,"SNP SAL",IF(ISERROR(VLOOKUP(A52,'Rest Sal Main org'!$A$3:$A1551,1,false))=FALSE,"Rest Sal","Not Found")) -> Not Found | AJ52: Y | AM52: =if(J52="","",datedif(J52,$AM$2,"M")) -> 135
A53: SE1084 | B53: NIDHI SAXENA | C53: Salary | D53: Backend Sales & Ops | E53: Executive | F53: DEL | G53: 0.41666667 | H53: 0.77083333 | I53: =IF(ISBLANK(H53),,H53-G53) -> 0.35416667 | J53: 42675 | K53: SE | L53: =Y53 -> 51110 | M53: Chq | N53: Employed | O53: 45901 | P53: 46890 | T53: NO | U53: S | V53: =P53 -> 46890 | W53: 0.09 | Y53: =if(W53="",V53,round(V53*(1+W53),-1)) -> 51110 | AA53: =L53 -> 51110 | AB53: =IFS(AND(AA53<=15000),15300,AND(AA53>15000,AA53<15500),AA53,AND(AA53>=15500,AA53<$Z$1),15500,AA53>=$Z$1,AA53*$AB$2) -> 25555 | AC53: =round(IF($AA53<=$Z$1,($AA53-$AB53)*AC$1,$AA53*AC$2),-1) -> 10220 | AD53: =round(IF($AA53<=$Z$1,($AA53-$AB53)*AD$1,$AA53*AD$2),-1)+AA53-AB53-AC53-round(IF($AA53<=$Z$1,($AA53-$AB53)*AD$1,$AA53*AD$2),-1) -> 15335 | AE53: 0 | AF53: =IF(SUM(AB53:AE53)=AA53,"OK","NO") -> OK | AG53: =IF(U53="US",IF(AA53<9750,"Under","US OK"),IF(U53="S",IF(AA53<12000,"Under","S OK"),"Skill Missing")) -> S OK | AH53: =VLOOKUP(A53,'Advance Sheet'!$A$4:$A$165,1,FALSE) -> #REF! | AI53: =IF(ISERROR(VLOOKUP(A53,'SNP Sal Main'!$A$3:$A1552,1,false))=FALSE,"SNP SAL",IF(ISERROR(VLOOKUP(A53,'Rest Sal Main org'!$A$3:$A1552,1,false))=FALSE,"Rest Sal","Not Found")) -> Not Found | AM53: =if(J53="","",datedif(J53,$AM$2,"M")) -> 118
A54: SE1095 | B54: SURBHI BAHL | C54: Salary | D54: Office | E54: Mis | F54: DEL | G54: 0.375 | H54: 0.75 | I54: =IF(ISBLANK(H54),,H54-G54) -> 0.375 | J54: 43070 | K54: SE | L54: =Y54 -> 47300 | M54: Chq | N54: Employed | O54: 45536 | P54: 47300 | T54: NO | V54: =P54 -> 47300 | W54: 0 | Y54: =if(W54="",V54,round(V54*(1+W54),-1)) -> 47300 | AA54: =L54 -> 47300 | AB54: =IFS(AND(AA54<=15000),15300,AND(AA54>15000,AA54<15500),AA54,AND(AA54>=15500,AA54<$Z$1),15500,AA54>=$Z$1,AA54*$AB$2) -> 23650 | AC54: =round(IF($AA54<=$Z$1,($AA54-$AB54)*AC$1,$AA54*AC$2),-1) -> 9460 | AD54: =round(IF($AA54<=$Z$1,($AA54-$AB54)*AD$1,$AA54*AD$2),-1)+AA54-AB54-AC54-round(IF($AA54<=$Z$1,($AA54-$AB54)*AD$1,$AA54*AD$2),-1) -> 14190 | AE54: 0 | AF54: =IF(SUM(AB54:AE54)=AA54,"OK","NO") -> OK | AG54: =IF(U54="US",IF(AA54<9750,"Under","US OK"),IF(U54="S",IF(AA54<12000,"Under","S OK"),"Skill Missing")) -> Skill Missing | AH54: =VLOOKUP(A54,'Advance Sheet'!$A$4:$A$165,1,FALSE) -> #REF! | AI54: =IF(ISERROR(VLOOKUP(A54,'SNP Sal Main'!$A$3:$A1553,1,false))=FALSE,"SNP SAL",IF(ISERROR(VLOOKUP(A54,'Rest Sal Main org'!$A$3:$A1553,1,false))=FALSE,"Rest Sal","Not Found")) -> Not Found | AM54: =if(J54="","",datedif(J54,$AM$2,"M")) -> 105
A55: SE1096 | B55: RAJEEV KUMAR | C55: Salary | D55: Cutting | E55: Supervisior | F55: MUM | G55: 0.375 | H55: 0.79166667 | I55: =IF(ISBLANK(H55),,H55-G55) -> 0.41666667 | J55: 43070 | K55: SE | L55: =Y55 -> 35660 | M55: Chq | N55: Employed | O55: 45901 | P55: 32420 | S55: YES | T55: NO | U55: S | V55: =P55 -> 32420 | W55: 0.1 | Y55: =if(W55="",V55,round(V55*(1+W55),-1)) -> 35660 | AA55: =L55 -> 35660 | AB55: =IFS(AA55<=12000,AA55,AND(AA55>12000,AA55<=15200),15200,AND(AA55>15200,AA55<15500),AA55,AND(AA55>=15500,AA55<30000),15500,AA55>=30000,AA55*$AB$2) -> 17830 | AC55: =round(IF($AA55<=$Z$1,($AA55-$AB55)*AC$1,$AA55*AC$2),-1) -> 7130 | AD55: =round(IF($AA55<=$Z$1,($AA55-$AB55)*AD$1,$AA55*AD$2),-1)+AA55-AB55-AC55-round(IF($AA55<=$Z$1,($AA55-$AB55)*AD$1,$AA55*AD$2),-1) -> 10700 | AE55: 0 | AF55: =IF(SUM(AB55:AE55)=AA55,"OK","NO") -> OK | AG55: =IF(U55="US",IF(AA55<9750,"Under","US OK"),IF(U55="S",IF(AA55<12000,"Under","S OK"),"Skill Missing")) -> S OK | AH55: =VLOOKUP(A55,'Advance Sheet'!$A$4:$A$165,1,FALSE) -> #REF! | AI55: =IF(ISERROR(VLOOKUP(A55,'SNP Sal Main'!$A$3:$A1554,1,false))=FALSE,"SNP SAL",IF(ISERROR(VLOOKUP(A55,'Rest Sal Main org'!$A$3:$A1554,1,false))=FALSE,"Rest Sal","Not Found")) -> Not Found | AM55: =if(J55="","",datedif(J55,$AM$2,"M")) -> 105
A56: SE1098 | B56: NARESH SOLANKI | C56: Salary | D56: Accounts & Finance | E56: HOD | F56: SNP | G56: 0.375 | H56: 0.77083333 | I56: =IF(ISBLANK(H56),,H56-G56) -> 0.39583333 | J56: 43070 | K56: SE | L56: 76130 | M56: Chq | N56: Employed | O56: 45901 | P56: 53150 | T56: NO | U56: S | V56: =P56 -> 53150 | W56: 0.08 | Y56: =if(W56="",V56,round(V56*(1+W56),-1)) -> 57400 | AA56: =L56 -> 76130 | AB56: =IFS(AND(AA56<=15000),15300,AND(AA56>15000,AA56<15500),AA56,AND(AA56>=15500,AA56<$Z$1),15500,AA56>=$Z$1,AA56*$AB$2) -> 38065 | AC56: =round(IF($AA56<=$Z$1,($AA56-$AB56)*AC$1,$AA56*AC$2),-1) -> 15230 | AD56: =round(IF($AA56<=$Z$1,($AA56-$AB56)*AD$1,$AA56*AD$2),-1)+AA56-AB56-AC56-round(IF($AA56<=$Z$1,($AA56-$AB56)*AD$1,$AA56*AD$2),-1) -> 22835 | AE56: 0 | AF56: =IF(SUM(AB56:AE56)=AA56,"OK","NO") -> OK | AG56: =IF(U56="US",IF(AA56<9750,"Under","US OK"),IF(U56="S",IF(AA56<12000,"Under","S OK"),"Skill Missing")) -> S OK | AH56: =VLOOKUP(A56,'Advance Sheet'!$A$4:$A$165,1,FALSE) -> #REF! | AI56: =IF(ISERROR(VLOOKUP(A56,'SNP Sal Main'!$A$3:$A1555,1,false))=FALSE,"SNP SAL",IF(ISERROR(VLOOKUP(A56,'Rest Sal Main org'!$A$3:$A1555,1,false))=FALSE,"Rest Sal","Not Found")) -> Not Found | AM56: =if(J56="","",datedif(J56,$AM$2,"M")) -> 105
A57: SE1101 | B57: RAJ KUMAR | C57: Salary | D57: Cutting | E57: Helper | F57: SNP | G57: 0.33333333 | H57: 0.75 | I57: =IF(ISBLANK(H57),,H57-G57) -> 0.41666667 | J57: 43116 | K57: SE | L57: 21294 | M57: Chq | N57: Employed | O57: 45901 | P57: 18270 | S57: YES | T57: YES | U57: US | V57: =P57 -> 18270 | W57: 0.11 | Y57: =if(W57="",V57,round(V57*(1+W57),-1)) -> 20280 | AA57: =L57 -> 21294 | AB57: =IFS(AND(AA57<=15000),15300,AND(AA57>15000,AA57<15500),AA57,AND(AA57>=15500,AA57<$Z$1),15500,AA57>=$Z$1,AA57*$AB$2) -> 15500 | AC57: =round(IF($AA57<=$Z$1,($AA57-$AB57)*AC$1,$AA57*AC$2),-1) -> 2320 | AD57: =round(IF($AA57<=$Z$1,($AA57-$AB57)*AD$1,$AA57*AD$2),-1)+AA57-AB57-AC57-round(IF($AA57<=$Z$1,($AA57-$AB57)*AD$1,$AA57*AD$2),-1) -> 3474 | AE57: 0 | AF57: =IF(SUM(AB57:AE57)=AA57,"OK","NO") -> OK | AG57: =IF(U57="US",IF(AA57<9750,"Under","US OK"),IF(U57="S",IF(AA57<12000,"Under","S OK"),"Skill Missing")) -> US OK | AH57: =VLOOKUP(A57,'Advance Sheet'!$A$4:$A$165,1,FALSE) -> #REF! | AI57: =IF(ISERROR(VLOOKUP(A57,'SNP Sal Main'!$A$3:$A1556,1,false))=FALSE,"SNP SAL",IF(ISERROR(VLOOKUP(A57,'Rest Sal Main org'!$A$3:$A1556,1,false))=FALSE,"Rest Sal","Not Found")) -> Not Found | AM57: =if(J57="","",datedif(J57,$AM$2,"M")) -> 104
A58: SE1102 | B58: SUMIT OPERATOR | C58: Salary | D58: Machining | E58: Supervisior | F58: SNP | G58: 0.33333333 | H58: 0.75 | I58: =IF(ISBLANK(H58),,H58-G58) -> 0.41666667 | J58: 43115 | K58: SE | L58: 29355 | M58: Chq | N58: Employed | O58: 45901 | P58: 28500 | S58: YES | T58: NO | U58: S | V58: =P58 -> 28500 | W58: 0.11 | Y58: =if(W58="",V58,round(V58*(1+W58),-1)) -> 31640 | AA58: =L58 -> 29355 | AB58: =IFS(AND(AA58<=15000),15300,AND(AA58>15000,AA58<15500),AA58,AND(AA58>=15500,AA58<$Z$1),15500,AA58>=$Z$1,AA58*$AB$2) -> 15500 | AC58: =round(IF($AA58<=$Z$1,($AA58-$AB58)*AC$1,$AA58*AC$2),-1) -> 5540 | AD58: =round(IF($AA58<=$Z$1,($AA58-$AB58)*AD$1,$AA58*AD$2),-1)+AA58-AB58-AC58-round(IF($AA58<=$Z$1,($AA58-$AB58)*AD$1,$AA58*AD$2),-1) -> 8315 | AE58: 0 | AF58: =IF(SUM(AB58:AE58)=AA58,"OK","NO") -> OK | AG58: =IF(U58="US",IF(AA58<9750,"Under","US OK"),IF(U58="S",IF(AA58<12000,"Under","S OK"),"Skill Missing")) -> S OK | AH58: =VLOOKUP(A58,'Advance Sheet'!$A$4:$A$165,1,FALSE) -> #REF! | AI58: =IF(ISERROR(VLOOKUP(A58,'SNP Sal Main'!$A$3:$A1557,1,false))=FALSE,"SNP SAL",IF(ISERROR(VLOOKUP(A58,'Rest Sal Main org'!$A$3:$A1557,1,false))=FALSE,"Rest Sal","Not Found")) -> Not Found | AL58: =AM58/12 -> 8.6666667 | AM58: =if(J58="","",datedif(J58,$AM$2,"M")) -> 104
A59: SE1114 | B59: RAKESH KUMAR | C59: Salary | D59: STOCK | E59: EXECUTIVE | F59: SNP | G59: 0.375 | H59: 0.77083333 | I59: =IF(ISBLANK(H59),,H59-G59) -> 0.39583333 | J59: 43241 | K59: SE | L59: =Y59 -> 26570 | M59: Chq | N59: Employed | O59: 45901 | P59: 23940 | S59: YES | T59: NO | U59: S | V59: =P59 -> 23940 | W59: 0.11 | Y59: =if(W59="",V59,round(V59*(1+W59),-1)) -> 26570 | AA59: =L59 -> 26570 | AB59: =IFS(AND(AA59<=15000),15300,AND(AA59>15000,AA59<15500),AA59,AND(AA59>=15500,AA59<$Z$1),15500,AA59>=$Z$1,AA59*$AB$2) -> 15500 | AC59: =round(IF($AA59<=$Z$1,($AA59-$AB59)*AC$1,$AA59*AC$2),-1) -> 4430 | AD59: =round(IF($AA59<=$Z$1,($AA59-$AB59)*AD$1,$AA59*AD$2),-1)+AA59-AB59-AC59-round(IF($AA59<=$Z$1,($AA59-$AB59)*AD$1,$AA59*AD$2),-1) -> 6640 | AE59: 0 | AF59: =IF(SUM(AB59:AE59)=AA59,"OK","NO") -> OK | AG59: =IF(U59="US",IF(AA59<9750,"Under","US OK"),IF(U59="S",IF(AA59<12000,"Under","S OK"),"Skill Missing")) -> S OK | AH59: =VLOOKUP(A59,'Advance Sheet'!$A$4:$A$165,1,FALSE) -> #REF! | AI59: =IF(ISERROR(VLOOKUP(A59,'SNP Sal Main'!$A$3:$A1558,1,false))=FALSE,"SNP SAL",IF(ISERROR(VLOOKUP(A59,'Rest Sal Main org'!$A$3:$A1558,1,false))=FALSE,"Rest Sal","Not Found")) -> Not Found | AM59: =if(J59="","",datedif(J59,$AM$2,"M")) -> 100
A60: SE1125 | B60: PARVESH | C60: Salary | D60: Cutting | E60: Supervisior | F60: SNP | G60: 0.35416667 | H60: 0.75 | I60: =IF(ISBLANK(H60),,H60-G60) -> 0.39583333 | J60: 43586 | K60: SE | L60: 26739 | M60: Chq | N60: Employed | O60: 45901 | P60: 25960 | S60: YES | T60: YES | U60: S | V60: =P60 -> 25960 | W60: 0.11 | Y60: =if(W60="",V60,round(V60*(1+W60),-1)) -> 28820 | Z60: july 450 | AA60: =L60 -> 26739 | AB60: =IFS(AND(AA60<=15000),15300,AND(AA60>15000,AA60<15500),AA60,AND(AA60>=15500,AA60<$Z$1),15500,AA60>=$Z$1,AA60*$AB$2) -> 15500 | AC60: =round(IF($AA60<=$Z$1,($AA60-$AB60)*AC$1,$AA60*AC$2),-1) -> 4500 | AD60: =round(IF($AA60<=$Z$1,($AA60-$AB60)*AD$1,$AA60*AD$2),-1)+AA60-AB60-AC60-round(IF($AA60<=$Z$1,($AA60-$AB60)*AD$1,$AA60*AD$2),-1) -> 6739 | AE60: 0 | AF60: =IF(SUM(AB60:AE60)=AA60,"OK","NO") -> OK | AG60: =IF(U60="US",IF(AA60<9750,"Under","US OK"),IF(U60="S",IF(AA60<12000,"Under","S OK"),"Skill Missing")) -> S OK | AH60: =VLOOKUP(A60,'Advance Sheet'!$A$4:$A$165,1,FALSE) -> #REF! | AI60: =IF(ISERROR(VLOOKUP(A60,'SNP Sal Main'!$A$3:$A1559,1,false))=FALSE,"SNP SAL",IF(ISERROR(VLOOKUP(A60,'Rest Sal Main org'!$A$3:$A1559,1,false))=FALSE,"Rest Sal","Not Found")) -> Not Found | AM60: =if(J60="","",datedif(J60,$AM$2,"M")) -> 88
A61: SE1131 | B61: TEJINDER KAUR | C61: Salary | D61: Admin | E61: Executive Assistant | F61: DEL | G61: 0.41666667 | H61: 0.77083333 | I61: =IF(ISBLANK(H61),,H61-G61) -> 0.35416667 | J61: 43680 | K61: SE | L61: =Y61 -> 81130 | M61: Chq | N61: Employed | O61: 45901 | P61: 75120 | T61: NO | U61: S | V61: =P61 -> 75120 | W61: 0.08 | Y61: =if(W61="",V61,round(V61*(1+W61),-1)) -> 81130 | AA61: =L61 -> 81130 | AB61: =IFS(AND(AA61<=15000),15300,AND(AA61>15000,AA61<15500),AA61,AND(AA61>=15500,AA61<$Z$1),15500,AA61>=$Z$1,AA61*$AB$2) -> 40565 | AC61: =round(IF($AA61<=$Z$1,($AA61-$AB61)*AC$1,$AA61*AC$2),-1) -> 16230 | AD61: =round(IF($AA61<=$Z$1,($AA61-$AB61)*AD$1,$AA61*AD$2),-1)+AA61-AB61-AC61-round(IF($AA61<=$Z$1,($AA61-$AB61)*AD$1,$AA61*AD$2),-1) -> 24335 | AE61: 0 | AF61: =IF(SUM(AB61:AE61)=AA61,"OK","NO") -> OK | AG61: =IF(U61="US",IF(AA61<9750,"Under","US OK"),IF(U61="S",IF(AA61<12000,"Under","S OK"),"Skill Missing")) -> S OK | AH61: =VLOOKUP(A61,'Advance Sheet'!$A$4:$A$165,1,FALSE) -> #REF! | AI61: =IF(ISERROR(VLOOKUP(A61,'SNP Sal Main'!$A$3:$A1560,1,false))=FALSE,"SNP SAL",IF(ISERROR(VLOOKUP(A61,'Rest Sal Main org'!$A$3:$A1560,1,false))=FALSE,"Rest Sal","Not Found")) -> Not Found | AM61: =if(J61="","",datedif(J61,$AM$2,"M")) -> 85
A62: SE1132 | B62: SANJEEV KUMAR | C62: Salary | D62: Cutting | E62: Operator | F62: MUM | G62: 0.375 | H62: 0.79166667 | I62: =IF(ISBLANK(H62),,H62-G62) -> 0.41666667 | J62: 43694 | K62: SE | L62: 21231 | M62: Chq | N62: Employed | O62: 45901 | P62: 18220 | S62: YES | T62: NO | U62: S | V62: =P62 -> 18220 | W62: 0.11 | Y62: =if(W62="",V62,round(V62*(1+W62),-1)) -> 20220 | AA62: =L62 -> 21231 | AB62: =IFS(AND(AA62<=15000),15300,AND(AA62>15000,AA62<15500),AA62,AND(AA62>=15500,AA62<$Z$1),15500,AA62>=$Z$1,AA62*$AB$2) -> 15500 | AC62: =round(IF($AA62<=$Z$1,($AA62-$AB62)*AC$1,$AA62*AC$2),-1) -> 2290 | AD62: =round(IF($AA62<=$Z$1,($AA62-$AB62)*AD$1,$AA62*AD$2),-1)+AA62-AB62-AC62-round(IF($AA62<=$Z$1,($AA62-$AB62)*AD$1,$AA62*AD$2),-1) -> 3441 | AE62: 0 | AF62: =IF(SUM(AB62:AE62)=AA62,"OK","NO") -> OK | AG62: =IF(U62="US",IF(AA62<9750,"Under","US OK"),IF(U62="S",IF(AA62<12000,"Under","S OK"),"Skill Missing")) -> S OK | AH62: =VLOOKUP(A62,'Advance Sheet'!$A$4:$A$165,1,FALSE) -> #REF! | AI62: =IF(ISERROR(VLOOKUP(A62,'SNP Sal Main'!$A$3:$A1561,1,false))=FALSE,"SNP SAL",IF(ISERROR(VLOOKUP(A62,'Rest Sal Main org'!$A$3:$A1561,1,false))=FALSE,"Rest Sal","Not Found")) -> Not Found | AM62: =if(J62="","",datedif(J62,$AM$2,"M")) -> 85
A63: SE1140 | B63: DEEPAK | C63: Salary | D63: Accounts & Finance | E63: Executive Accounts | F63: SNP | G63: 0.375 | H63: 0.77083333 | I63: =IF(ISBLANK(H63),,H63-G63) -> 0.39583333 | J63: 43739 | K63: SE | L63: =Y63 -> 40010 | M63: Chq | N63: Employed | O63: 45901 | P63: 36710 | T63: NO | U63: S | V63: =P63 -> 36710 | W63: 0.09 | Y63: =if(W63="",V63,round(V63*(1+W63),-1)) -> 40010 | AA63: =L63 -> 40010 | AB63: =IFS(AND(AA63<=15000),15300,AND(AA63>15000,AA63<15500),AA63,AND(AA63>=15500,AA63<$Z$1),15500,AA63>=$Z$1,AA63*$AB$2) -> 20005 | AC63: =round(IF($AA63<=$Z$1,($AA63-$AB63)*AC$1,$AA63*AC$2),-1) -> 8000 | AD63: =round(IF($AA63<=$Z$1,($AA63-$AB63)*AD$1,$AA63*AD$2),-1)+AA63-AB63-AC63-round(IF($AA63<=$Z$1,($AA63-$AB63)*AD$1,$AA63*AD$2),-1) -> 12005 | AE63: 0 | AF63: =IF(SUM(AB63:AE63)=AA63,"OK","NO") -> OK | AG63: =IF(U63="US",IF(AA63<9750,"Under","US OK"),IF(U63="S",IF(AA63<12000,"Under","S OK"),"Skill Missing")) -> S OK | AH63: =VLOOKUP(A63,'Advance Sheet'!$A$4:$A$165,1,FALSE) -> #REF! | AI63: =IF(ISERROR(VLOOKUP(A63,'SNP Sal Main'!$A$3:$A1562,1,false))=FALSE,"SNP SAL",IF(ISERROR(VLOOKUP(A63,'Rest Sal Main org'!$A$3:$A1562,1,false))=FALSE,"Rest Sal","Not Found")) -> Not Found | AJ63: N | AM63: =if(J63="","",datedif(J63,$AM$2,"M")) -> 83
A64: SE1141 | B64: POOJA | C64: Salary | D64: Backend Ops | E64: Executive | F64: DEL | G64: 0.41666667 | H64: 0.77083333 | I64: =IF(ISBLANK(H64),,H64-G64) -> 0.35416667 | J64: 43780 | K64: SE | L64: =Y64 -> 46710 | M64: Chq | N64: Employed | O64: 45901 | P64: 42850 | T64: NO | U64: S | V64: =P64 -> 42850 | W64: 0.09 | Y64: =if(W64="",V64,round(V64*(1+W64),-1)) -> 46710 | AA64: =L64 -> 46710 | AB64: =IFS(AND(AA64<=15000),15300,AND(AA64>15000,AA64<15500),AA64,AND(AA64>=15500,AA64<$Z$1),15500,AA64>=$Z$1,AA64*$AB$2) -> 23355 | AC64: =round(IF($AA64<=$Z$1,($AA64-$AB64)*AC$1,$AA64*AC$2),-1) -> 9340 | AD64: =round(IF($AA64<=$Z$1,($AA64-$AB64)*AD$1,$AA64*AD$2),-1)+AA64-AB64-AC64-round(IF($AA64<=$Z$1,($AA64-$AB64)*AD$1,$AA64*AD$2),-1) -> 14015 | AE64: 0 | AF64: =IF(SUM(AB64:AE64)=AA64,"OK","NO") -> OK | AG64: =IF(U64="US",IF(AA64<9750,"Under","US OK"),IF(U64="S",IF(AA64<12000,"Under","S OK"),"Skill Missing")) -> S OK | AH64: =VLOOKUP(A64,'Advance Sheet'!$A$4:$A$165,1,FALSE) -> #REF! | AI64: =IF(ISERROR(VLOOKUP(A64,'SNP Sal Main'!$A$3:$A1563,1,false))=FALSE,"SNP SAL",IF(ISERROR(VLOOKUP(A64,'Rest Sal Main org'!$A$3:$A1563,1,false))=FALSE,"Rest Sal","Not Found")) -> Not Found | AM64: =if(J64="","",datedif(J64,$AM$2,"M")) -> 82
A65: SE1142 | B65: suman kumar | C65: Salary | D65: Cutting | E65: Operator | F65: SNP | G65: 0.33333333 | H65: 0.75 | I65: =IF(ISBLANK(H65),,H65-G65) -> 0.41666667 | J65: 43535 | K65: SE | L65: 21500 | M65: Chq | N65: Employed | O65: 45901 | P65: 19362 | S65: YES | T65: YES | U65: S | V65: =P65 -> 19362 | W65: 0.11 | Y65: =if(W65="",V65,round(V65*(1+W65),-1)) -> 21490 | AA65: =L65 -> 21500 | AB65: =IFS(AND(AA65<=15000),15300,AND(AA65>15000,AA65<15500),AA65,AND(AA65>=15500,AA65<$Z$1),15500,AA65>=$Z$1,AA65*$AB$2) -> 15500 | AC65: =round(IF($AA65<=$Z$1,($AA65-$AB65)*AC$1,$AA65*AC$2),-1) -> 2400 | AD65: =round(IF($AA65<=$Z$1,($AA65-$AB65)*AD$1,$AA65*AD$2),-1)+AA65-AB65-AC65-round(IF($AA65<=$Z$1,($AA65-$AB65)*AD$1,$AA65*AD$2),-1) -> 3600 | AE65: 0 | AF65: =IF(SUM(AB65:AE65)=AA65,"OK","NO") -> OK | AG65: =IF(U65="US",IF(AA65<9750,"Under","US OK"),IF(U65="S",IF(AA65<12000,"Under","S OK"),"Skill Missing")) -> S OK | AH65: =VLOOKUP(A65,'Advance Sheet'!$A$4:$A$165,1,FALSE) -> #REF! | AI65: =IF(ISERROR(VLOOKUP(A65,'SNP Sal Main'!$A$3:$A1564,1,false))=FALSE,"SNP SAL",IF(ISERROR(VLOOKUP(A65,'Rest Sal Main org'!$A$3:$A1564,1,false))=FALSE,"Rest Sal","Not Found")) -> Not Found | AM65: =if(J65="","",datedif(J65,$AM$2,"M")) -> 90
A66: SE1144 | B66: KANIKA SOLANKI | C66: Salary | D66: ACCOUNTS & FINANCE | E66: EXECUTIVE | F66: SNP | G66: 0.375 | H66: 0.77083333 | I66: =IF(ISBLANK(H66),,H66-G66) -> 0.39583333 | J66: 43897 | K66: SE | L66: 21500 | M66: Chq | N66: Employed | O66: 45170 | P66: 15830 | R66: 45711 | T66: NO | U66: S | V66: =P66 -> 15830 | Y66: =if(W66="",V66,round(V66*(1+W66),-1)) -> 15830 | AA66: =L66 -> 21500 | AB66: =IFS(AND(AA66<=15000),15300,AND(AA66>15000,AA66<15500),AA66,AND(AA66>=15500,AA66<$Z$1),15500,AA66>=$Z$1,AA66*$AB$2) -> 15500 | AC66: =round(IF($AA66<=$Z$1,($AA66-$AB66)*AC$1,$AA66*AC$2),-1) -> 2400 | AD66: =round(IF($AA66<=$Z$1,($AA66-$AB66)*AD$1,$AA66*AD$2),-1)+AA66-AB66-AC66-round(IF($AA66<=$Z$1,($AA66-$AB66)*AD$1,$AA66*AD$2),-1) -> 3600 | AE66: 0 | AF66: =IF(SUM(AB66:AE66)=AA66,"OK","NO") -> OK | AG66: =IF(U66="US",IF(AA66<9750,"Under","US OK"),IF(U66="S",IF(AA66<12000,"Under","S OK"),"Skill Missing")) -> S OK | AH66: =VLOOKUP(A66,'Advance Sheet'!$A$4:$A$165,1,FALSE) -> #REF! | AI66: =IF(ISERROR(VLOOKUP(A66,'SNP Sal Main'!$A$3:$A1565,1,false))=FALSE,"SNP SAL",IF(ISERROR(VLOOKUP(A66,'Rest Sal Main org'!$A$3:$A1565,1,false))=FALSE,"Rest Sal","Not Found")) -> Not Found | AM66: =if(J66="","",datedif(J66,$AM$2,"M")) -> 78
A67: SE1145 | B67: GUDDU KUMAR RAM | C67: Salary | D67: Cutting | E67: Helper | F67: MUM | G67: 0.375 | H67: 0.79166667 | I67: =IF(ISBLANK(H67),,H67-G67) -> 0.41666667 | J67: 43677 | K67: SE | L67: 21231 | M67: Chq | N67: Employed | O67: 45901 | P67: 18220 | S67: YES | T67: NO | U67: US | V67: =P67 -> 18220 | W67: 0.11 | Y67: =if(W67="",V67,round(V67*(1+W67),-1)) -> 20220 | AA67: =L67 -> 21231 | AB67: =IFS(AND(AA67<=15000),15300,AND(AA67>15000,AA67<15500),AA67,AND(AA67>=15500,AA67<$Z$1),15500,AA67>=$Z$1,AA67*$AB$2) -> 15500 | AC67: =round(IF($AA67<=$Z$1,($AA67-$AB67)*AC$1,$AA67*AC$2),-1) -> 2290 | AD67: =round(IF($AA67<=$Z$1,($AA67-$AB67)*AD$1,$AA67*AD$2),-1)+AA67-AB67-AC67-round(IF($AA67<=$Z$1,($AA67-$AB67)*AD$1,$AA67*AD$2),-1) -> 3441 | AE67: 0 | AF67: =IF(SUM(AB67:AE67)=AA67,"OK","NO") -> OK | AG67: =IF(U67="US",IF(AA67<9750,"Under","US OK"),IF(U67="S",IF(AA67<12000,"Under","S OK"),"Skill Missing")) -> US OK | AH67: =VLOOKUP(A67,'Advance Sheet'!$A$4:$A$165,1,FALSE) -> #REF! | AI67: =IF(ISERROR(VLOOKUP(A67,'SNP Sal Main'!$A$3:$A1566,1,false))=FALSE,"SNP SAL",IF(ISERROR(VLOOKUP(A67,'Rest Sal Main org'!$A$3:$A1566,1,false))=FALSE,"Rest Sal","Not Found")) -> Not Found | AM67: =if(J67="","",datedif(J67,$AM$2,"M")) -> 85
A68: SE1149 | B68: VICKEY JANGRA | C68: Salary | D68: Machining | E68: Programmer | F68: SNP | G68: 0.33333333 | H68: 0.75 | I68: =IF(ISBLANK(H68),,H68-G68) -> 0.41666667 | J68: 44081 | K68: SE | L68: 44523 | M68: Chq | N68: Employed | O68: 45901 | P68: 43650 | T68: YES | U68: S | V68: =P68 -> 43650 | W68: 0.09 | Y68: =if(W68="",V68,round(V68*(1+W68),-1)) -> 47580 | AA68: =L68 -> 44523 | AB68: =roundup(IFS(AND(AA68<=15000),15300,AND(AA68>15000,AA68<15500),AA68,AND(AA68>=15500,AA68<$Z$1),15500,AA68>=$Z$1,AA68*$AB$2),0) -> 22262 | AC68: =round(IF($AA68<=$Z$1,($AA68-$AB68)*AC$1,$AA68*AC$2),-1) -> 8900 | AD68: =round(IF($AA68<=$Z$1,($AA68-$AB68)*AD$1,$AA68*AD$2),-1)+AA68-AB68-AC68-round(IF($AA68<=$Z$1,($AA68-$AB68)*AD$1,$AA68*AD$2),-1) -> 13361 | AE68: 0 | AF68: =IF(SUM(AB68:AE68)=AA68,"OK","NO") -> OK | AG68: =IF(U68="US",IF(AA68<9750,"Under","US OK"),IF(U68="S",IF(AA68<12000,"Under","S OK"),"Skill Missing")) -> S OK | AH68: =VLOOKUP(A68,'Advance Sheet'!$A$4:$A$165,1,FALSE) -> #REF! | AI68: =IF(ISERROR(VLOOKUP(A68,'SNP Sal Main'!$A$3:$A1567,1,false))=FALSE,"SNP SAL",IF(ISERROR(VLOOKUP(A68,'Rest Sal Main org'!$A$3:$A1567,1,false))=FALSE,"Rest Sal","Not Found")) -> Not Found | AL68: =AM68/12 -> 6 | AM68: =if(J68="","",datedif(J68,$AM$2,"M")) -> 72
A69: SE1151 | B69: VINAY SHANKER PRASAD | C69: Salary | D69: Cutting | E69: Supervisior | F69: SNP | G69: 0.33333333 | H69: 0.75 | I69: =IF(ISBLANK(H69),,H69-G69) -> 0.41666667 | J69: 43378 | K69: SE | L69: 25704 | M69: Chq | N69: Employed | O69: 45901 | P69: 22050 | S69: YES | T69: YES | U69: S | V69: =P69 -> 22050 | W69: 0.11 | Y69: =if(W69="",V69,round(V69*(1+W69),-1)) -> 24480 | AA69: =L69 -> 25704 | AB69: =IFS(AND(AA69<=15000),15300,AND(AA69>15000,AA69<15500),AA69,AND(AA69>=15500,AA69<$Z$1),15500,AA69>=$Z$1,AA69*$AB$2) -> 15500 | AC69: =round(IF($AA69<=$Z$1,($AA69-$AB69)*AC$1,$AA69*AC$2),-1) -> 4080 | AD69: =round(IF($AA69<=$Z$1,($AA69-$AB69)*AD$1,$AA69*AD$2),-1)+AA69-AB69-AC69-round(IF($AA69<=$Z$1,($AA69-$AB69)*AD$1,$AA69*AD$2),-1) -> 6124 | AE69: 0 | AF69: =IF(SUM(AB69:AE69)=AA69,"OK","NO") -> OK | AG69: =IF(U69="US",IF(AA69<9750,"Under","US OK"),IF(U69="S",IF(AA69<12000,"Under","S OK"),"Skill Missing")) -> S OK | AH69: =VLOOKUP(A69,'Advance Sheet'!$A$4:$A$165,1,FALSE) -> #REF! | AI69: =IF(ISERROR(VLOOKUP(A69,'SNP Sal Main'!$A$3:$A1568,1,false))=FALSE,"SNP SAL",IF(ISERROR(VLOOKUP(A69,'Rest Sal Main org'!$A$3:$A1568,1,false))=FALSE,"Rest Sal","Not Found")) -> Not Found | AK69: Y | AM69: =if(J69="","",datedif(J69,$AM$2,"M")) -> 95
A70: SE1152 | B70: SUKESH | C70: Salary | D70: Backend Ops | E70: Executive | F70: DEL | G70: 0.375 | H70: 0.77083333 | I70: =IF(ISBLANK(H70),,H70-G70) -> 0.39583333 | J70: 44136 | K70: SE | L70: =Y70 -> 29110 | M70: Chq | N70: Employed | O70: 45901 | P70: 26460 | T70: NO | U70: S | V70: =P70 -> 26460 | W70: 0.1 | Y70: =if(W70="",V70,round(V70*(1+W70),-1)) -> 29110 | AA70: =L70 -> 29110 | AB70: =IFS(AND(AA70<=15000),15300,AND(AA70>15000,AA70<15500),AA70,AND(AA70>=15500,AA70<$Z$1),15500,AA70>=$Z$1,AA70*$AB$2) -> 15500 | AC70: =round(IF($AA70<=$Z$1,($AA70-$AB70)*AC$1,$AA70*AC$2),-1) -> 5440 | AD70: =round(IF($AA70<=$Z$1,($AA70-$AB70)*AD$1,$AA70*AD$2),-1)+AA70-AB70-AC70-round(IF($AA70<=$Z$1,($AA70-$AB70)*AD$1,$AA70*AD$2),-1) -> 8170 | AE70: 0 | AF70: =IF(SUM(AB70:AE70)=AA70,"OK","NO") -> OK | AG70: =IF(U70="US",IF(AA70<9750,"Under","US OK"),IF(U70="S",IF(AA70<12000,"Under","S OK"),"Skill Missing")) -> S OK | AH70: =VLOOKUP(A70,'Advance Sheet'!$A$4:$A$165,1,FALSE) -> #REF! | AI70: =IF(ISERROR(VLOOKUP(A70,'SNP Sal Main'!$A$3:$A1569,1,false))=FALSE,"SNP SAL",IF(ISERROR(VLOOKUP(A70,'Rest Sal Main org'!$A$3:$A1569,1,false))=FALSE,"Rest Sal","Not Found")) -> Not Found | AM70: =if(J70="","",datedif(J70,$AM$2,"M")) -> 70
A71: SE1154 | B71: ANKIT | C71: Salary | D71: Machining | E71: Operator NC | F71: SNP | G71: 0.33333333 | H71: 0.75 | I71: =IF(ISBLANK(H71),,H71-G71) -> 0.41666667 | J71: 44032 | K71: SE | L71: 28820 | M71: Chq | N71: Employed | O71: 45901 | P71: 27980 | S71: YES | T71: YES | U71: S | V71: =P71 -> 27980 | W71: 0.1 | Y71: =if(W71="",V71,round(V71*(1+W71),-1)) -> 30780 | AA71: =L71 -> 28820 | AB71: =IFS(AND(AA71<=15000),15300,AND(AA71>15000,AA71<15500),AA71,AND(AA71>=15500,AA71<$Z$1),15500,AA71>=$Z$1,AA71*$AB$2) -> 15500 | AC71: =round(IF($AA71<=$Z$1,($AA71-$AB71)*AC$1,$AA71*AC$2),-1) -> 5330 | AD71: =round(IF($AA71<=$Z$1,($AA71-$AB71)*AD$1,$AA71*AD$2),-1)+AA71-AB71-AC71-round(IF($AA71<=$Z$1,($AA71-$AB71)*AD$1,$AA71*AD$2),-1) -> 7990 | AE71: 0 | AF71: =IF(SUM(AB71:AE71)=AA71,"OK","NO") -> OK | AG71: =IF(U71="US",IF(AA71<9750,"Under","US OK"),IF(U71="S",IF(AA71<12000,"Under","S OK"),"Skill Missing")) -> S OK | AH71: =VLOOKUP(A71,'Advance Sheet'!$A$4:$A$165,1,FALSE) -> #REF! | AI71: =IF(ISERROR(VLOOKUP(A71,'SNP Sal Main'!$A$3:$A1570,1,false))=FALSE,"SNP SAL",IF(ISERROR(VLOOKUP(A71,'Rest Sal Main org'!$A$3:$A1570,1,false))=FALSE,"Rest Sal","Not Found")) -> Not Found | AJ71: N | AL71: =AM71/12 -> 6.1666667 | AM71: =if(J71="","",datedif(J71,$AM$2,"M")) -> 74
A72: SE1159 | B72: RAVINDER | C72: Salary | D72: Machining | E72: Operator Grinder | F72: SNP | G72: 0.33333333 | H72: 0.75 | I72: =IF(ISBLANK(H72),,H72-G72) -> 0.41666667 | J72: 44243 | K72: SE | L72: 19247 | M72: Chq | N72: Employed | O72: 45901 | P72: 16510 | S72: YES | T72: YES | U72: S | V72: =P72 -> 16510 | W72: 0.11 | Y72: =if(W72="",V72,round(V72*(1+W72),-1)) -> 18330 | Z72: april 1000 | AA72: =L72 -> 19247 | AB72: =IFS(AND(AA72<=15000),15300,AND(AA72>15000,AA72<15500),AA72,AND(AA72>=15500,AA72<$Z$1),15500,AA72>=$Z$1,AA72*$AB$2) -> 15500 | AC72: =round(IF($AA72<=$Z$1,($AA72-$AB72)*AC$1,$AA72*AC$2),-1) -> 1500 | AD72: =round(IF($AA72<=$Z$1,($AA72-$AB72)*AD$1,$AA72*AD$2),-1)+AA72-AB72-AC72-round(IF($AA72<=$Z$1,($AA72-$AB72)*AD$1,$AA72*AD$2),-1) -> 2247 | AE72: 0 | AF72: =IF(SUM(AB72:AE72)=AA72,"OK","NO") -> OK | AG72: =IF(U72="US",IF(AA72<9750,"Under","US OK"),IF(U72="S",IF(AA72<12000,"Under","S OK"),"Skill Missing")) -> S OK | AH72: =VLOOKUP(A72,'Advance Sheet'!$A$4:$A$165,1,FALSE) -> #REF! | AI72: =IF(ISERROR(VLOOKUP(A72,'SNP Sal Main'!$A$3:$A1571,1,false))=FALSE,"SNP SAL",IF(ISERROR(VLOOKUP(A72,'Rest Sal Main org'!$A$3:$A1571,1,false))=FALSE,"Rest Sal","Not Found")) -> Not Found | AL72: =AM72/12 -> 5.5833333 | AM72: =if(J72="","",datedif(J72,$AM$2,"M")) -> 67
A73: SE1162 | B73: SANDEEP | C73: Salary | D73: Machining | E73: Operator Multi | F73: SNP | G73: 0.33333333 | H73: 0.75 | I73: =IF(ISBLANK(H73),,H73-G73) -> 0.41666667 | J73: 44207 | K73: SE | L73: 19667 | M73: Chq | N73: Employed | O73: 45901 | P73: 16870 | S73: YES | T73: YES | U73: S | V73: =P73 -> 16870 | W73: 0.11 | Y73: =if(W73="",V73,round(V73*(1+W73),-1)) -> 18730 | Z73: april 500 | AA73: =L73 -> 19667 | AB73: =IFS(AND(AA73<=15000),15300,AND(AA73>15000,AA73<15500),AA73,AND(AA73>=15500,AA73<$Z$1),15500,AA73>=$Z$1,AA73*$AB$2) -> 15500 | AC73: =round(IF($AA73<=$Z$1,($AA73-$AB73)*AC$1,$AA73*AC$2),-1) -> 1670 | AD73: =round(IF($AA73<=$Z$1,($AA73-$AB73)*AD$1,$AA73*AD$2),-1)+AA73-AB73-AC73-round(IF($AA73<=$Z$1,($AA73-$AB73)*AD$1,$AA73*AD$2),-1) -> 2497 | AE73: 0 | AF73: =IF(SUM(AB73:AE73)=AA73,"OK","NO") -> OK | AG73: =IF(U73="US",IF(AA73<9750,"Under","US OK"),IF(U73="S",IF(AA73<12000,"Under","S OK"),"Skill Missing")) -> S OK | AH73: =VLOOKUP(A73,'Advance Sheet'!$A$4:$A$165,1,FALSE) -> #REF! | AI73: =IF(ISERROR(VLOOKUP(A73,'SNP Sal Main'!$A$3:$A1572,1,false))=FALSE,"SNP SAL",IF(ISERROR(VLOOKUP(A73,'Rest Sal Main org'!$A$3:$A1572,1,false))=FALSE,"Rest Sal","Not Found")) -> Not Found | AL73: =AM73/12 -> 5.6666667 | AM73: =if(J73="","",datedif(J73,$AM$2,"M")) -> 68
A74: SE1164 | B74: ADARSH | C74: Salary | D74: Cutting | E74: Operator | F74: SNP | G74: 0.33333333 | H74: 0.75 | I74: =IF(ISBLANK(H74),,H74-G74) -> 0.41666667 | J74: 43525 | K74: SE | L74: 21500 | M74: Chq | N74: Employed | O74: 45901 | P74: 19362 | S74: YES | T74: YES | U74: S | V74: =P74 -> 19362 | W74: 0.11 | Y74: =if(W74="",V74,round(V74*(1+W74),-1)) -> 21490 | AA74: =L74 -> 21500 | AB74: =IFS(AND(AA74<=15000),15300,AND(AA74>15000,AA74<15500),AA74,AND(AA74>=15500,AA74<$Z$1),15500,AA74>=$Z$1,AA74*$AB$2) -> 15500 | AC74: =round(IF($AA74<=$Z$1,($AA74-$AB74)*AC$1,$AA74*AC$2),-1) -> 2400 | AD74: =round(IF($AA74<=$Z$1,($AA74-$AB74)*AD$1,$AA74*AD$2),-1)+AA74-AB74-AC74-round(IF($AA74<=$Z$1,($AA74-$AB74)*AD$1,$AA74*AD$2),-1) -> 3600 | AE74: 0 | AF74: =IF(SUM(AB74:AE74)=AA74,"OK","NO") -> OK | AG74: =IF(U74="US",IF(AA74<9750,"Under","US OK"),IF(U74="S",IF(AA74<12000,"Under","S OK"),"Skill Missing")) -> S OK | AH74: =VLOOKUP(A74,'Advance Sheet'!$A$4:$A$165,1,FALSE) -> #REF! | AI74: =IF(ISERROR(VLOOKUP(A74,'SNP Sal Main'!$A$3:$A1573,1,false))=FALSE,"SNP SAL",IF(ISERROR(VLOOKUP(A74,'Rest Sal Main org'!$A$3:$A1573,1,false))=FALSE,"Rest Sal","Not Found")) -> Not Found | AJ74: N | AM74: =if(J74="","",datedif(J74,$AM$2,"M")) -> 90
A75: SE1167 | B75: GOVIND THAKUR | C75: Salary | D75: Machining | E75: Operator NC | F75: SNP | G75: 0.33333333 | H75: 0.75 | I75: =IF(ISBLANK(H75),,H75-G75) -> 0.41666667 | J75: 43705 | K75: SE | L75: 19541 | M75: Chq | N75: Employed | O75: 45901 | P75: 16770 | S75: YES | T75: YES | U75: S | V75: =P75 -> 16770 | W75: 0.11 | Y75: =if(W75="",V75,round(V75*(1+W75),-1)) -> 18610 | AA75: =L75 -> 19541 | AB75: =IFS(AND(AA75<=15000),15300,AND(AA75>15000,AA75<15500),AA75,AND(AA75>=15500,AA75<$Z$1),15500,AA75>=$Z$1,AA75*$AB$2) -> 15500 | AC75: =round(IF($AA75<=$Z$1,($AA75-$AB75)*AC$1,$AA75*AC$2),-1) -> 1620 | AD75: =round(IF($AA75<=$Z$1,($AA75-$AB75)*AD$1,$AA75*AD$2),-1)+AA75-AB75-AC75-round(IF($AA75<=$Z$1,($AA75-$AB75)*AD$1,$AA75*AD$2),-1) -> 2421 | AE75: 0 | AF75: =IF(SUM(AB75:AE75)=AA75,"OK","NO") -> OK | AG75: =IF(U75="US",IF(AA75<9750,"Under","US OK"),IF(U75="S",IF(AA75<12000,"Under","S OK"),"Skill Missing")) -> S OK | AH75: =VLOOKUP(A75,'Advance Sheet'!$A$4:$A$165,1,FALSE) -> #REF! | AI75: =IF(ISERROR(VLOOKUP(A75,'SNP Sal Main'!$A$3:$A1574,1,false))=FALSE,"SNP SAL",IF(ISERROR(VLOOKUP(A75,'Rest Sal Main org'!$A$3:$A1574,1,false))=FALSE,"Rest Sal","Not Found")) -> Not Found | AL75: =AM75/12 -> 7 | AM75: =if(J75="","",datedif(J75,$AM$2,"M")) -> 84
A76: SE1168 | B76: VIPIN | C76: Salary | D76: Machining | E76: Operator NC | F76: SNP | G76: 0.33333333 | H76: 0.75 | I76: =IF(ISBLANK(H76),,H76-G76) -> 0.41666667 | J76: 43462 | K76: SE | L76: 19635 | M76: Chq | N76: Employed | O76: 45901 | P76: 16850 | S76: YES | T76: YES | U76: S | V76: =P76 -> 16850 | W76: 0.11 | Y76: =if(W76="",V76,round(V76*(1+W76),-1)) -> 18700 | AA76: =L76 -> 19635 | AB76: =IFS(AND(AA76<=15000),15300,AND(AA76>15000,AA76<15500),AA76,AND(AA76>=15500,AA76<$Z$1),15500,AA76>=$Z$1,AA76*$AB$2) -> 15500 | AC76: =round(IF($AA76<=$Z$1,($AA76-$AB76)*AC$1,$AA76*AC$2),-1) -> 1650 | AD76: =round(IF($AA76<=$Z$1,($AA76-$AB76)*AD$1,$AA76*AD$2),-1)+AA76-AB76-AC76-round(IF($AA76<=$Z$1,($AA76-$AB76)*AD$1,$AA76*AD$2),-1) -> 2485 | AE76: 0 | AF76: =IF(SUM(AB76:AE76)=AA76,"OK","NO") -> OK | AG76: =IF(U76="US",IF(AA76<9750,"Under","US OK"),IF(U76="S",IF(AA76<12000,"Under","S OK"),"Skill Missing")) -> S OK | AH76: =VLOOKUP(A76,'Advance Sheet'!$A$4:$A$165,1,FALSE) -> #REF! | AI76: =IF(ISERROR(VLOOKUP(A76,'SNP Sal Main'!$A$3:$A1575,1,false))=FALSE,"SNP SAL",IF(ISERROR(VLOOKUP(A76,'Rest Sal Main org'!$A$3:$A1575,1,false))=FALSE,"Rest Sal","Not Found")) -> Not Found | AL76: =AM76/12 -> 7.6666667 | AM76: =if(J76="","",datedif(J76,$AM$2,"M")) -> 92
A77: SE1169 | B77: SUSHANT JAIN | C77: Salary | D77: Management | E77: Business Devlopment | F77: DEL | G77: 0.375 | H77: 0.75 | I77: =IF(ISBLANK(H77),,H77-G77) -> 0.375 | J77: 44652 | K77: SE | L77: 200000 | M77: Chq | N77: Employed | O77: 45536 | P77: 200000 | Q77: 30375 | T77: NO | V77: =P77 -> 200000 | W77: 0 | Y77: =if(W77="",V77,round(V77*(1+W77),-1)) -> 200000 | AA77: =L77 -> 200000 | AB77: 200000 | AF77: =IF(SUM(AB77:AE77)=AA77,"OK","NO") -> OK | AG77: =IF(U77="US",IF(AA77<9750,"Under","US OK"),IF(U77="S",IF(AA77<12000,"Under","S OK"),"Skill Missing")) -> Skill Missing | AH77: =VLOOKUP(A77,'Advance Sheet'!$A$4:$A$165,1,FALSE) -> #REF! | AI77: =IF(ISERROR(VLOOKUP(A77,'SNP Sal Main'!$A$3:$A1576,1,false))=FALSE,"SNP SAL",IF(ISERROR(VLOOKUP(A77,'Rest Sal Main org'!$A$3:$A1576,1,false))=FALSE,"Rest Sal","Not Found")) -> Not Found | AM77: =if(J77="","",datedif(J77,$AM$2,"M")) -> 53
A78: SE1170 | B78: SAMYAK JAIN | C78: Salary | D78: Management | E78: Business Devlopment | F78: DEL | G78: 0.375 | H78: 0.75 | I78: =IF(ISBLANK(H78),,H78-G78) -> 0.375 | J78: 44652 | K78: SE | L78: 200000 | M78: Chq | N78: Employed | P78: 200000 | Q78: 30375 | T78: NO | V78: =P78 -> 200000 | W78: 0 | Y78: =if(W78="",V78,round(V78*(1+W78),-1)) -> 200000 | AA78: =L78 -> 200000 | AB78: 200000 | AF78: =IF(SUM(AB78:AE78)=AA78,"OK","NO") -> OK | AG78: =IF(U78="US",IF(AA78<9750,"Under","US OK"),IF(U78="S",IF(AA78<12000,"Under","S OK"),"Skill Missing")) -> Skill Missing | AH78: =VLOOKUP(A78,'Advance Sheet'!$A$4:$A$165,1,FALSE) -> #REF! | AI78: =IF(ISERROR(VLOOKUP(A78,'SNP Sal Main'!$A$3:$A1577,1,false))=FALSE,"SNP SAL",IF(ISERROR(VLOOKUP(A78,'Rest Sal Main org'!$A$3:$A1577,1,false))=FALSE,"Rest Sal","Not Found")) -> Not Found | AJ78: N | AM78: =if(J78="","",datedif(J78,$AM$2,"M")) -> 53
A79: SE1171 | B79: VISHU JAIN | C79: Salary | D79: Management | E79: Sales & Marketing | F79: DEL | G79: 0.375 | H79: 0.75 | I79: =IF(ISBLANK(H79),,H79-G79) -> 0.375 | J79: 44287 | K79: SE | L79: 225000 | M79: Chq | N79: Employed | P79: 210000 | Q79: 37395 | T79: NO | V79: =P79 -> 210000 | W79: 0 | Y79: =if(W79="",V79,round(V79*(1+W79),-1)) -> 210000 | AA79: =L79 -> 225000 | AB79: 225000 | AE79: 0 | AF79: =IF(SUM(AB79:AE79)=AA79,"OK","NO") -> OK | AG79: =IF(U79="US",IF(AA79<9750,"Under","US OK"),IF(U79="S",IF(AA79<12000,"Under","S OK"),"Skill Missing")) -> Skill Missing | AH79: =VLOOKUP(A79,'Advance Sheet'!$A$4:$A$165,1,FALSE) -> #REF! | AI79: =IF(ISERROR(VLOOKUP(A79,'SNP Sal Main'!$A$3:$A1578,1,false))=FALSE,"SNP SAL",IF(ISERROR(VLOOKUP(A79,'Rest Sal Main org'!$A$3:$A1578,1,false))=FALSE,"Rest Sal","Not Found")) -> Not Found | AJ79: N | AM79: =if(J79="","",datedif(J79,$AM$2,"M")) -> 65
A80: SE1172 | B80: SWATI JAIN | C80: Salary | D80: Office | E80: Mis | F80: DEL | G80: 0.375 | H80: 0.75 | I80: =IF(ISBLANK(H80),,H80-G80) -> 0.375 | J80: 44348 | K80: SE | L80: =Y80 -> 54000 | M80: Chq | N80: Employed | O80: 45170 | P80: 54000 | Q80: 0 | T80: NO | V80: =P80 -> 54000 | W80: 0 | Y80: =if(W80="",V80,round(V80*(1+W80),-1)) -> 54000 | AA80: =L80 -> 54000 | AB80: 54000 | AC80: 0 | AD80: 0 | AE80: 0 | AF80: =IF(SUM(AB80:AE80)=AA80,"OK","NO") -> OK | AG80: =IF(U80="US",IF(AA80<9750,"Under","US OK"),IF(U80="S",IF(AA80<12000,"Under","S OK"),"Skill Missing")) -> Skill Missing | AH80: =VLOOKUP(A80,'Advance Sheet'!$A$4:$A$165,1,FALSE) -> #REF! | AI80: =IF(ISERROR(VLOOKUP(A80,'SNP Sal Main'!$A$3:$A1579,1,false))=FALSE,"SNP SAL",IF(ISERROR(VLOOKUP(A80,'Rest Sal Main org'!$A$3:$A1579,1,false))=FALSE,"Rest Sal","Not Found")) -> Not Found | AJ80: N | AM80: =if(J80="","",datedif(J80,$AM$2,"M")) -> 63
A81: SE1175 | B81: RAJEEV KUMAR | C81: Salary | D81: Machining | E81: Operator NC | F81: SNP | G81: 0.33333333 | H81: 0.75 | I81: =IF(ISBLANK(H81),,H81-G81) -> 0.41666667 | J81: 43672 | K81: SE | L81: 23762 | M81: Chq | N81: Employed | O81: 45901 | P81: 20390 | S81: YES | T81: YES | U81: S | V81: =P81 -> 20390 | W81: 0.11 | Y81: =if(W81="",V81,round(V81*(1+W81),-1)) -> 22630 | AA81: =L81 -> 23762 | AB81: =IFS(AND(AA81<=15000),15300,AND(AA81>15000,AA81<15500),AA81,AND(AA81>=15500,AA81<$Z$1),15500,AA81>=$Z$1,AA81*$AB$2) -> 15500 | AC81: =round(IF($AA81<=$Z$1,($AA81-$AB81)*AC$1,$AA81*AC$2),-1) -> 3300 | AD81: =round(IF($AA81<=$Z$1,($AA81-$AB81)*AD$1,$AA81*AD$2),-1)+AA81-AB81-AC81-round(IF($AA81<=$Z$1,($AA81-$AB81)*AD$1,$AA81*AD$2),-1) -> 4962 | AE81: 0 | AF81: =IF(SUM(AB81:AE81)=AA81,"OK","NO") -> OK | AG81: =IF(U81="US",IF(AA81<9750,"Under","US OK"),IF(U81="S",IF(AA81<12000,"Under","S OK"),"Skill Missing")) -> S OK | AH81: =VLOOKUP(A81,'Advance Sheet'!$A$4:$A$165,1,FALSE) -> #REF! | AI81: =IF(ISERROR(VLOOKUP(A81,'SNP Sal Main'!$A$3:$A1580,1,false))=FALSE,"SNP SAL",IF(ISERROR(VLOOKUP(A81,'Rest Sal Main org'!$A$3:$A1580,1,false))=FALSE,"Rest Sal","Not Found")) -> Not Found | AK81: Y | AL81: =AM81/12 -> 7.1666667 | AM81: =if(J81="","",datedif(J81,$AM$2,"M")) -> 86
A82: SE1176 | B82: SHARVAN | C82: Salary | D82: Cutting | E82: Operator | F82: SNP | G82: 0.33333333 | H82: 0.75 | I82: =IF(ISBLANK(H82),,H82-G82) -> 0.41666667 | J82: 44271 | K82: SE | L82: 21500 | M82: Chq | N82: Employed | O82: 45901 | P82: 19646 | S82: YES | T82: YES | U82: S | V82: =P82 -> 19646 | W82: 0.11 | Y82: =if(W82="",V82,round(V82*(1+W82),-1)) -> 21810 | Z82: march 1000 | AA82: =L82 -> 21500 | AB82: =IFS(AND(AA82<=15000),15300,AND(AA82>15000,AA82<15500),AA82,AND(AA82>=15500,AA82<$Z$1),15500,AA82>=$Z$1,AA82*$AB$2) -> 15500 | AC82: =round(IF($AA82<=$Z$1,($AA82-$AB82)*AC$1,$AA82*AC$2),-1) -> 2400 | AD82: =round(IF($AA82<=$Z$1,($AA82-$AB82)*AD$1,$AA82*AD$2),-1)+AA82-AB82-AC82-round(IF($AA82<=$Z$1,($AA82-$AB82)*AD$1,$AA82*AD$2),-1) -> 3600 | AE82: 0 | AF82: =IF(SUM(AB82:AE82)=AA82,"OK","NO") -> OK | AG82: =IF(U82="US",IF(AA82<9750,"Under","US OK"),IF(U82="S",IF(AA82<12000,"Under","S OK"),"Skill Missing")) -> S OK | AH82: =VLOOKUP(A82,'Advance Sheet'!$A$4:$A$165,1,FALSE) -> #REF! | AI82: =IF(ISERROR(VLOOKUP(A82,'SNP Sal Main'!$A$3:$A1581,1,false))=FALSE,"SNP SAL",IF(ISERROR(VLOOKUP(A82,'Rest Sal Main org'!$A$3:$A1581,1,false))=FALSE,"Rest Sal","Not Found")) -> Not Found | AM82: =if(J82="","",datedif(J82,$AM$2,"M")) -> 66
A83: SE1179 | B83: SUNITA DEVI | C83: Salary | D83: Floor Shop | E83: Helper | F83: SNP | G83: 0.33333333 | H83: 0.70833333 | I83: =IF(ISBLANK(H83),,H83-G83) -> 0.375 | J83: 43223 | K83: SE | L83: 16489 | M83: Chq | N83: Employed | O83: 45901 | P83: 13380 | S83: YES | T83: YES | U83: US | V83: =P83 -> 13380 | W83: 0.12 | Y83: =if(W83="",V83,round(V83*(1+W83),-1)) -> 14990 | AA83: =L83 -> 16489 | AB83: =IFS(AND(AA83<=15000),15300,AND(AA83>15000,AA83<15500),AA83,AND(AA83>=15500,AA83<$Z$1),15500,AA83>=$Z$1,AA83*$AB$2) -> 15500 | AC83: =round(IF($AA83<=$Z$1,($AA83-$AB83)*AC$1,$AA83*AC$2),-1) -> 400 | AD83: =round(IF($AA83<=$Z$1,($AA83-$AB83)*AD$1,$AA83*AD$2),-1)+AA83-AB83-AC83-round(IF($AA83<=$Z$1,($AA83-$AB83)*AD$1,$AA83*AD$2),-1) -> 589 | AE83: 0 | AF83: =IF(SUM(AB83:AE83)=AA83,"OK","NO") -> OK | AG83: =IF(U83="US",IF(AA83<9750,"Under","US OK"),IF(U83="S",IF(AA83<12000,"Under","S OK"),"Skill Missing")) -> US OK | AH83: =VLOOKUP(A83,'Advance Sheet'!$A$4:$A$165,1,FALSE) -> #REF! | AI83: =IF(ISERROR(VLOOKUP(A83,'SNP Sal Main'!$A$3:$A1582,1,false))=FALSE,"SNP SAL",IF(ISERROR(VLOOKUP(A83,'Rest Sal Main org'!$A$3:$A1582,1,false))=FALSE,"Rest Sal","Not Found")) -> Not Found | AM83: =if(J83="","",datedif(J83,$AM$2,"M")) -> 100
A84: SE1182 | B84: RITA DEVI | C84: Salary | D84: Cutting | E84: Helper | F84: SNP | G84: 0.33333333 | H84: 0.75 | I84: =IF(ISBLANK(H84),,H84-G84) -> 0.41666667 | J84: 44384 | K84: SE | L84: 16664 | M84: Chq | N84: Employed | O84: 45901 | P84: 14170 | S84: YES | T84: YES | U84: US | V84: =P84 -> 14170 | W84: 0.12 | Y84: =if(W84="",V84,round(V84*(1+W84),-1)) -> 15870 | AA84: =L84 -> 16664 | AB84: =IFS(AND(AA84<=15000),15300,AND(AA84>15000,AA84<15500),AA84,AND(AA84>=15500,AA84<$Z$1),15500,AA84>=$Z$1,AA84*$AB$2) -> 15500 | AC84: =round(IF($AA84<=$Z$1,($AA84-$AB84)*AC$1,$AA84*AC$2),-1) -> 470 | AD84: =round(IF($AA84<=$Z$1,($AA84-$AB84)*AD$1,$AA84*AD$2),-1)+AA84-AB84-AC84-round(IF($AA84<=$Z$1,($AA84-$AB84)*AD$1,$AA84*AD$2),-1) -> 694 | AE84: 0 | AF84: =IF(SUM(AB84:AE84)=AA84,"OK","NO") -> OK | AG84: =IF(U84="US",IF(AA84<9750,"Under","US OK"),IF(U84="S",IF(AA84<12000,"Under","S OK"),"Skill Missing")) -> US OK | AH84: =VLOOKUP(A84,'Advance Sheet'!$A$4:$A$165,1,FALSE) -> #REF! | AI84: =IF(ISERROR(VLOOKUP(A84,'SNP Sal Main'!$A$3:$A1583,1,false))=FALSE,"SNP SAL",IF(ISERROR(VLOOKUP(A84,'Rest Sal Main org'!$A$3:$A1583,1,false))=FALSE,"Rest Sal","Not Found")) -> Not Found | AK84: Y | AM84: =if(J84="","",datedif(J84,$AM$2,"M")) -> 62
A85: SE1183 | B85: SANJAY YADAV | C85: Salary | D85: Cutting | E85: Operator Gas Cutting | F85: SNP | G85: 0.33333333 | H85: 0.75 | I85: =IF(ISBLANK(H85),,H85-G85) -> 0.41666667 | J85: 44375 | K85: SE | L85: 20181 | M85: Chq | N85: Employed | O85: 45901 | P85: 16860 | S85: YES | T85: YES | U85: S | V85: =P85 -> 16860 | W85: 0.11 | Y85: =if(W85="",V85,round(V85*(1+W85),-1)) -> 18710 | Z85: july 500 | AA85: =L85 -> 20181 | AB85: =IFS(AND(AA85<=15000),15300,AND(AA85>15000,AA85<15500),AA85,AND(AA85>=15500,AA85<$Z$1),15500,AA85>=$Z$1,AA85*$AB$2) -> 15500 | AC85: =round(IF($AA85<=$Z$1,($AA85-$AB85)*AC$1,$AA85*AC$2),-1) -> 1870 | AD85: =round(IF($AA85<=$Z$1,($AA85-$AB85)*AD$1,$AA85*AD$2),-1)+AA85-AB85-AC85-round(IF($AA85<=$Z$1,($AA85-$AB85)*AD$1,$AA85*AD$2),-1) -> 2811 | AE85: 0 | AF85: =IF(SUM(AB85:AE85)=AA85,"OK","NO") -> OK | AG85: =IF(U85="US",IF(AA85<9750,"Under","US OK"),IF(U85="S",IF(AA85<12000,"Under","S OK"),"Skill Missing")) -> S OK | AH85: =VLOOKUP(A85,'Advance Sheet'!$A$4:$A$165,1,FALSE) -> #REF! | AI85: =IF(ISERROR(VLOOKUP(A85,'SNP Sal Main'!$A$3:$A1584,1,false))=FALSE,"SNP SAL",IF(ISERROR(VLOOKUP(A85,'Rest Sal Main org'!$A$3:$A1584,1,false))=FALSE,"Rest Sal","Not Found")) -> Not Found | AK85: Y | AM85: =if(J85="","",datedif(J85,$AM$2,"M")) -> 62
A86: SE1185 | B86: MANOJ KUMAR | C86: Salary | D86: Cutting | E86: Helper | F86: SNP | G86: 0.33333333 | H86: 0.75 | I86: =IF(ISBLANK(H86),,H86-G86) -> 0.41666667 | J86: 43736 | K86: SE | L86: 16538 | M86: Chq | N86: Employed | O86: 45901 | P86: 14060 | S86: YES | T86: YES | U86: US | V86: =P86 -> 14060 | W86: 0.12 | Y86: =if(W86="",V86,round(V86*(1+W86),-1)) -> 15750 | AA86: =L86 -> 16538 | AB86: =IFS(AND(AA86<=15000),15300,AND(AA86>15000,AA86<15500),AA86,AND(AA86>=15500,AA86<$Z$1),15500,AA86>=$Z$1,AA86*$AB$2) -> 15500 | AC86: =round(IF($AA86<=$Z$1,($AA86-$AB86)*AC$1,$AA86*AC$2),-1) -> 420 | AD86: =round(IF($AA86<=$Z$1,($AA86-$AB86)*AD$1,$AA86*AD$2),-1)+AA86-AB86-AC86-round(IF($AA86<=$Z$1,($AA86-$AB86)*AD$1,$AA86*AD$2),-1) -> 618 | AE86: 0 | AF86: =IF(SUM(AB86:AE86)=AA86,"OK","NO") -> OK | AG86: =IF(U86="US",IF(AA86<9750,"Under","US OK"),IF(U86="S",IF(AA86<12000,"Under","S OK"),"Skill Missing")) -> US OK | AH86: =VLOOKUP(A86,'Advance Sheet'!$A$4:$A$165,1,FALSE) -> #REF! | AI86: =IF(ISERROR(VLOOKUP(A86,'SNP Sal Main'!$A$3:$A1585,1,false))=FALSE,"SNP SAL",IF(ISERROR(VLOOKUP(A86,'Rest Sal Main org'!$A$3:$A1585,1,false))=FALSE,"Rest Sal","Not Found")) -> Not Found | AK86: Y | AM86: =if(J86="","",datedif(J86,$AM$2,"M")) -> 83
A87: SE1190 | B87: SAURABH | C87: Salary | D87: Machining | E87: Supervisior | F87: SNP | G87: 0.33333333 | H87: 0.75 | I87: =IF(ISBLANK(H87),,H87-G87) -> 0.41666667 | J87: 44440 | K87: SE | L87: 27615 | M87: Chq | N87: Employed | O87: 45901 | P87: 26810 | S87: YES | T87: YES | U87: S | V87: =P87 -> 26810 | W87: 0.11 | Y87: =if(W87="",V87,round(V87*(1+W87),-1)) -> 29760 | AA87: =L87 -> 27615 | AB87: =IFS(AND(AA87<=15000),15300,AND(AA87>15000,AA87<15500),AA87,AND(AA87>=15500,AA87<$Z$1),15500,AA87>=$Z$1,AA87*$AB$2) -> 15500 | AC87: =round(IF($AA87<=$Z$1,($AA87-$AB87)*AC$1,$AA87*AC$2),-1) -> 4850 | AD87: =round(IF($AA87<=$Z$1,($AA87-$AB87)*AD$1,$AA87*AD$2),-1)+AA87-AB87-AC87-round(IF($AA87<=$Z$1,($AA87-$AB87)*AD$1,$AA87*AD$2),-1) -> 7265 | AE87: 0 | AF87: =IF(SUM(AB87:AE87)=AA87,"OK","NO") -> OK | AG87: =IF(U87="US",IF(AA87<9750,"Under","US OK"),IF(U87="S",IF(AA87<12000,"Under","S OK"),"Skill Missing")) -> S OK | AH87: =VLOOKUP(A87,'Advance Sheet'!$A$4:$A$165,1,FALSE) -> #REF! | AI87: =IF(ISERROR(VLOOKUP(A87,'SNP Sal Main'!$A$3:$A1586,1,false))=FALSE,"SNP SAL",IF(ISERROR(VLOOKUP(A87,'Rest Sal Main org'!$A$3:$A1586,1,false))=FALSE,"Rest Sal","Not Found")) -> Not Found | AL87: =AM87/12 -> 5 | AM87: =if(J87="","",datedif(J87,$AM$2,"M")) -> 60
A88: SE1197 | B88: AARTI ARORA | C88: Salary | D88: Office | E88: Mis | F88: DEL | G88: 0.375 | H88: 0.75 | I88: =IF(ISBLANK(H88),,H88-G88) -> 0.375 | J88: 44440 | K88: SE | L88: =Y88 -> 33000 | M88: Chq | N88: Employed | O88: 45170 | P88: 33000 | T88: NO | V88: =P88 -> 33000 | W88: 0 | Y88: =if(W88="",V88,round(V88*(1+W88),-1)) -> 33000 | AA88: =L88 -> 33000 | AB88: =IFS(AND(AA88<=15000),15300,AND(AA88>15000,AA88<15500),AA88,AND(AA88>=15500,AA88<$Z$1),15500,AA88>=$Z$1,AA88*$AB$2) -> 15500 | AC88: =round(IF($AA88<=$Z$1,($AA88-$AB88)*AC$1,$AA88*AC$2),-1) -> 7000 | AD88: =round(IF($AA88<=$Z$1,($AA88-$AB88)*AD$1,$AA88*AD$2),-1)+AA88-AB88-AC88-round(IF($AA88<=$Z$1,($AA88-$AB88)*AD$1,$AA88*AD$2),-1) -> 10500 | AE88: 0 | AF88: =IF(SUM(AB88:AE88)=AA88,"OK","NO") -> OK | AG88: =IF(U88="US",IF(AA88<9750,"Under","US OK"),IF(U88="S",IF(AA88<12000,"Under","S OK"),"Skill Missing")) -> Skill Missing | AH88: =VLOOKUP(A88,'Advance Sheet'!$A$4:$A$165,1,FALSE) -> #REF! | AI88: =IF(ISERROR(VLOOKUP(A88,'SNP Sal Main'!$A$3:$A1587,1,false))=FALSE,"SNP SAL",IF(ISERROR(VLOOKUP(A88,'Rest Sal Main org'!$A$3:$A1587,1,false))=FALSE,"Rest Sal","Not Found")) -> Not Found | AJ88: N | AM88: =if(J88="","",datedif(J88,$AM$2,"M")) -> 60
A89: SE1199 | B89: RAM AWADH PANDE | C89: Salary | D89: HR & ADMIN | E89: HOD | F89: DEL | G89: 0.35416667 | H89: 0.75 | I89: =IF(ISBLANK(H89),,H89-G89) -> 0.39583333 | J89: 39652 | K89: SE | L89: =Y89 -> 61030 | M89: Chq | N89: Employed | O89: 45901 | P89: 56510 | T89: NO | U89: S | V89: =P89 -> 56510 | W89: 0.08 | Y89: =if(W89="",V89,round(V89*(1+W89),-1)) -> 61030 | AA89: =L89 -> 61030 | AB89: =IFS(AND(AA89<=15000),15300,AND(AA89>15000,AA89<15500),AA89,AND(AA89>=15500,AA89<$Z$1),15500,AA89>=$Z$1,AA89*$AB$2) -> 30515 | AC89: =round(IF($AA89<=$Z$1,($AA89-$AB89)*AC$1,$AA89*AC$2),-1) -> 12210 | AD89: =round(IF($AA89<=$Z$1,($AA89-$AB89)*AD$1,$AA89*AD$2),-1)+AA89-AB89-AC89-round(IF($AA89<=$Z$1,($AA89-$AB89)*AD$1,$AA89*AD$2),-1) -> 18305 | AE89: 0 | AF89: =IF(SUM(AB89:AE89)=AA89,"OK","NO") -> OK | AG89: =IF(U89="US",IF(AA89<9750,"Under","US OK"),IF(U89="S",IF(AA89<12000,"Under","S OK"),"Skill Missing")) -> S OK | AH89: =VLOOKUP(A89,'Advance Sheet'!$A$4:$A$165,1,FALSE) -> #REF! | AI89: =IF(ISERROR(VLOOKUP(A89,'SNP Sal Main'!$A$3:$A1588,1,false))=FALSE,"SNP SAL",IF(ISERROR(VLOOKUP(A89,'Rest Sal Main org'!$A$3:$A1588,1,false))=FALSE,"Rest Sal","Not Found")) -> Not Found | AM89: =if(J89="","",datedif(J89,$AM$2,"M")) -> 218
A90: SE1200 | B90: KRISHNNANDAN KUMAR | C90: Salary | D90: MIS | E90: Executive | F90: SNP | G90: 0.375 | H90: 0.77083333 | I90: =IF(ISBLANK(H90),,H90-G90) -> 0.39583333 | J90: 43816 | K90: SE | L90: =Y90 -> 16000 | M90: Chq | N90: Employed | O90: 45901 | P90: 14290 | S90: YES | T90: NO | U90: S | V90: =P90 -> 14290 | W90: 0.12 | Y90: =if(W90="",V90,round(V90*(1+W90),-1)) -> 16000 | Z90: june 1100 | AA90: =L90 -> 16000 | AB90: =IFS(AND(AA90<=15000),15300,AND(AA90>15000,AA90<15500),AA90,AND(AA90>=15500,AA90<$Z$1),15500,AA90>=$Z$1,AA90*$AB$2) -> 15500 | AC90: =round(IF($AA90<=$Z$1,($AA90-$AB90)*AC$1,$AA90*AC$2),-1) -> 200 | AD90: =round(IF($AA90<=$Z$1,($AA90-$AB90)*AD$1,$AA90*AD$2),-1)+AA90-AB90-AC90-round(IF($AA90<=$Z$1,($AA90-$AB90)*AD$1,$AA90*AD$2),-1) -> 300 | AE90: 0 | AF90: =IF(SUM(AB90:AE90)=AA90,"OK","NO") -> OK | AG90: =IF(U90="US",IF(AA90<9750,"Under","US OK"),IF(U90="S",IF(AA90<12000,"Under","S OK"),"Skill Missing")) -> S OK | AH90: =VLOOKUP(A90,'Advance Sheet'!$A$4:$A$165,1,FALSE) -> #REF! | AI90: =IF(ISERROR(VLOOKUP(A90,'SNP Sal Main'!$A$3:$A1589,1,false))=FALSE,"SNP SAL",IF(ISERROR(VLOOKUP(A90,'Rest Sal Main org'!$A$3:$A1589,1,false))=FALSE,"Rest Sal","Not Found")) -> Not Found | AK90: Y | AM90: =if(J90="","",datedif(J90,$AM$2,"M")) -> 81
A91: SE1202 | B91: NAIPAL SINGH | C91: Salary | D91: Cutting | E91: Helper | F91: SNP | G91: 0.33333333 | H91: 0.75 | I91: =IF(ISBLANK(H91),,H91-G91) -> 0.41666667 | J91: 44531 | K91: SE | L91: 19709 | M91: Chq | N91: Employed | O91: 45901 | P91: 16910 | S91: YES | T91: YES | U91: US | V91: =P91 -> 16910 | W91: 0.11 | Y91: =if(W91="",V91,round(V91*(1+W91),-1)) -> 18770 | AA91: =L91 -> 19709 | AB91: =IFS(AND(AA91<=15000),15300,AND(AA91>15000,AA91<15500),AA91,AND(AA91>=15500,AA91<$Z$1),15500,AA91>=$Z$1,AA91*$AB$2) -> 15500 | AC91: =round(IF($AA91<=$Z$1,($AA91-$AB91)*AC$1,$AA91*AC$2),-1) -> 1680 | AD91: =round(IF($AA91<=$Z$1,($AA91-$AB91)*AD$1,$AA91*AD$2),-1)+AA91-AB91-AC91-round(IF($AA91<=$Z$1,($AA91-$AB91)*AD$1,$AA91*AD$2),-1) -> 2529 | AE91: 0 | AF91: =IF(SUM(AB91:AE91)=AA91,"OK","NO") -> OK | AG91: =IF(U91="US",IF(AA91<9750,"Under","US OK"),IF(U91="S",IF(AA91<12000,"Under","S OK"),"Skill Missing")) -> US OK | AH91: =VLOOKUP(A91,'Advance Sheet'!$A$4:$A$165,1,FALSE) -> #REF! | AI91: =IF(ISERROR(VLOOKUP(A91,'SNP Sal Main'!$A$3:$A1590,1,false))=FALSE,"SNP SAL",IF(ISERROR(VLOOKUP(A91,'Rest Sal Main org'!$A$3:$A1590,1,false))=FALSE,"Rest Sal","Not Found")) -> Not Found | AK91: Y | AM91: =if(J91="","",datedif(J91,$AM$2,"M")) -> 57
A92: SE1203 | B92: RAHUL | C92: Salary | D92: Machining | E92: Operator Grinder | F92: SNP | G92: 0.33333333 | H92: 0.75 | I92: =IF(ISBLANK(H92),,H92-G92) -> 0.41666667 | J92: 43883 | K92: SE | L92: 22208 | M92: Chq | N92: Employed | O92: 45901 | P92: 19050 | Q92: 0 | S92: YES | T92: YES | U92: S | V92: =P92 -> 19050 | W92: 0.11 | Y92: =if(W92="",V92,round(V92*(1+W92),-1)) -> 21150 | AA92: =L92 -> 22208 | AB92: =IFS(AND(AA92<=15000),15300,AND(AA92>15000,AA92<15500),AA92,AND(AA92>=15500,AA92<$Z$1),15500,AA92>=$Z$1,AA92*$AB$2) -> 15500 | AC92: =round(IF($AA92<=$Z$1,($AA92-$AB92)*AC$1,$AA92*AC$2),-1) -> 2680 | AD92: =round(IF($AA92<=$Z$1,($AA92-$AB92)*AD$1,$AA92*AD$2),-1)+AA92-AB92-AC92-round(IF($AA92<=$Z$1,($AA92-$AB92)*AD$1,$AA92*AD$2),-1) -> 4028 | AE92: 0 | AF92: =IF(SUM(AB92:AE92)=AA92,"OK","NO") -> OK | AG92: =IF(U92="US",IF(AA92<9750,"Under","US OK"),IF(U92="S",IF(AA92<12000,"Under","S OK"),"Skill Missing")) -> S OK | AH92: =VLOOKUP(A92,'Advance Sheet'!$A$4:$A$165,1,FALSE) -> #REF! | AI92: =IF(ISERROR(VLOOKUP(A92,'SNP Sal Main'!$A$3:$A1591,1,false))=FALSE,"SNP SAL",IF(ISERROR(VLOOKUP(A92,'Rest Sal Main org'!$A$3:$A1591,1,false))=FALSE,"Rest Sal","Not Found")) -> Not Found | AJ92: Y | AL92: =AM92/12 -> 6.5833333 | AM92: =if(J92="","",datedif(J92,$AM$2,"M")) -> 79
A93: SE1204 | B93: RAM KIRPAL | C93: Salary | D93: Cutting | E93: Helper | F93: SNP | G93: 0.33333333 | H93: 0.75 | I93: =IF(ISBLANK(H93),,H93-G93) -> 0.41666667 | J93: 43354 | K93: SE | L93: 19541 | M93: Chq | N93: Employed | O93: 45901 | P93: 16770 | S93: YES | T93: YES | U93: US | V93: =P93 -> 16770 | W93: 0.11 | Y93: =if(W93="",V93,round(V93*(1+W93),-1)) -> 18610 | AA93: =L93 -> 19541 | AB93: =IFS(AND(AA93<=15000),15300,AND(AA93>15000,AA93<15500),AA93,AND(AA93>=15500,AA93<$Z$1),15500,AA93>=$Z$1,AA93*$AB$2) -> 15500 | AC93: =round(IF($AA93<=$Z$1,($AA93-$AB93)*AC$1,$AA93*AC$2),-1) -> 1620 | AD93: =round(IF($AA93<=$Z$1,($AA93-$AB93)*AD$1,$AA93*AD$2),-1)+AA93-AB93-AC93-round(IF($AA93<=$Z$1,($AA93-$AB93)*AD$1,$AA93*AD$2),-1) -> 2421 | AE93: 0 | AF93: =IF(SUM(AB93:AE93)=AA93,"OK","NO") -> OK | AG93: =IF(U93="US",IF(AA93<9750,"Under","US OK"),IF(U93="S",IF(AA93<12000,"Under","S OK"),"Skill Missing")) -> US OK | AH93: =VLOOKUP(A93,'Advance Sheet'!$A$4:$A$165,1,FALSE) -> #REF! | AI93: =IF(ISERROR(VLOOKUP(A93,'SNP Sal Main'!$A$3:$A1592,1,false))=FALSE,"SNP SAL",IF(ISERROR(VLOOKUP(A93,'Rest Sal Main org'!$A$3:$A1592,1,false))=FALSE,"Rest Sal","Not Found")) -> Not Found | AM93: =if(J93="","",datedif(J93,$AM$2,"M")) -> 96
A94: SE1208 | B94: DEEPSHIKHA JAIN | C94: Salary | D94: Management | E94: Director | F94: DEL | G94: 0.375 | H94: 0.75 | I94: =IF(ISBLANK(H94),,H94-G94) -> 0.375 | J94: 44701 | K94: SE | L94: =Y94 -> 150000 | M94: Chq | N94: Employed | P94: 150000 | Q94: 20983 | T94: NO | V94: =P94 -> 150000 | W94: 0 | Y94: =if(W94="",V94,round(V94*(1+W94),-1)) -> 150000 | AA94: =L94 -> 150000 | AB94: 150000 | AC94: 0 | AD94: 0 | AE94: 0 | AF94: =IF(SUM(AB94:AE94)=AA94,"OK","NO") -> OK | AG94: =IF(U94="US",IF(AA94<9750,"Under","US OK"),IF(U94="S",IF(AA94<12000,"Under","S OK"),"Skill Missing")) -> Skill Missing | AH94: =VLOOKUP(A94,'Advance Sheet'!$A$4:$A$165,1,FALSE) -> #REF! | AI94: =IF(ISERROR(VLOOKUP(A94,'SNP Sal Main'!$A$3:$A1593,1,false))=FALSE,"SNP SAL",IF(ISERROR(VLOOKUP(A94,'Rest Sal Main org'!$A$3:$A1593,1,false))=FALSE,"Rest Sal","Not Found")) -> Not Found | AM94: =if(J94="","",datedif(J94,$AM$2,"M")) -> 52
A95: SE1209 | B95: GAURAV PALIWAL | C95: Salary | D95: MIS | E95: HOD | F95: SNP | G95: 0.375 | H95: 0.76041667 | I95: =IF(ISBLANK(H95),,H95-G95) -> 0.38541667 | J95: 44697 | K95: SE | L95: =Y95 -> 33720 | M95: Chq | N95: Employed | O95: 45901 | P95: 30650 | T95: NO | V95: =P95 -> 30650 | W95: 0.1 | Y95: =if(W95="",V95,round(V95*(1+W95),-1)) -> 33720 | AA95: =L95 -> 33720 | AB95: =IFS(AA95<=12000,AA95,AND(AA95>12000,AA95<=15200),15200,AND(AA95>15200,AA95<15500),AA95,AND(AA95>=15500,AA95<30000),15500,AA95>=30000,AA95*$AB$2) -> 16860 | AC95: =IF($AA95<=$Z$1,($AA95-$AB95)*AC$1,$AA95*AC$2) -> 6744 | AD95: =round(IF($AA95<=$Z$1,($AA95-$AB95)*AD$1,$AA95*AD$2),-1)+AA95-AB95-AC95-round(IF($AA95<=$Z$1,($AA95-$AB95)*AD$1,$AA95*AD$2),-1) -> 10116 | AE95: 0 | AF95: =IF(SUM(AB95:AE95)=AA95,"OK","NO") -> OK | AG95: =IF(U95="US",IF(AA95<9750,"Under","US OK"),IF(U95="S",IF(AA95<12000,"Under","S OK"),"Skill Missing")) -> Skill Missing | AH95: =VLOOKUP(A95,'Advance Sheet'!$A$4:$A$165,1,FALSE) -> #REF! | AI95: =IF(ISERROR(VLOOKUP(A95,'SNP Sal Main'!$A$3:$A1594,1,false))=FALSE,"SNP SAL",IF(ISERROR(VLOOKUP(A95,'Rest Sal Main org'!$A$3:$A1594,1,false))=FALSE,"Rest Sal","Not Found")) -> Not Found | AM95: =if(J95="","",datedif(J95,$AM$2,"M")) -> 52
A96: SE1212 | B96: HIMANSHU | C96: Salary | D96: Digital Marketing | E96: Designer | F96: DEL | G96: 0.39583333 | H96: 0.75 | I96: =IF(ISBLANK(H96),,H96-G96) -> 0.35416667 | J96: 44744 | K96: SE | L96: =Y96 -> 21620 | M96: Chq | N96: Employed | O96: 45901 | P96: 19480 | T96: NO | U96: S | V96: =P96 -> 19480 | W96: 0.11 | Y96: =if(W96="",V96,round(V96*(1+W96),-1)) -> 21620 | Z96: 13815 aug | AA96: 21620 | AB96: =IFS(AND(AA96<=15000),15300,AND(AA96>15000,AA96<15500),AA96,AND(AA96>=15500,AA96<$Z$1),15500,AA96>=$Z$1,AA96*$AB$2) -> 15500 | AC96: =round(IF($AA96<=$Z$1,($AA96-$AB96)*AC$1,$AA96*AC$2),-1) -> 2450 | AD96: =round(IF($AA96<=$Z$1,($AA96-$AB96)*AD$1,$AA96*AD$2),-1)+AA96-AB96-AC96-round(IF($AA96<=$Z$1,($AA96-$AB96)*AD$1,$AA96*AD$2),-1) -> 3670 | AE96: 0 | AF96: =IF(SUM(AB96:AE96)=AA96,"OK","NO") -> OK | AG96: =IF(U96="US",IF(AA96<9750,"Under","US OK"),IF(U96="S",IF(AA96<12000,"Under","S OK"),"Skill Missing")) -> S OK | AH96: =VLOOKUP(A96,'Advance Sheet'!$A$4:$A$165,1,FALSE) -> #REF! | AI96: =IF(ISERROR(VLOOKUP(A96,'SNP Sal Main'!$A$3:$A1595,1,false))=FALSE,"SNP SAL",IF(ISERROR(VLOOKUP(A96,'Rest Sal Main org'!$A$3:$A1595,1,false))=FALSE,"Rest Sal","Not Found")) -> Not Found | AM96: =if(J96="","",datedif(J96,$AM$2,"M")) -> 50
A97: SE1214 | B97: PAWAN MALIK | C97: Salary | D97: Machining | E97: Quality | F97: SNP | G97: 0.33333333 | H97: 0.75 | I97: =IF(ISBLANK(H97),,H97-G97) -> 0.41666667 | J97: 44767 | K97: SE | L97: 25620 | M97: Chq | N97: Employed | O97: 45901 | P97: 21980 | S97: YES | T97: NO | V97: =P97 -> 21980 | W97: 0.11 | Y97: =if(W97="",V97,round(V97*(1+W97),-1)) -> 24400 | AA97: =L97 -> 25620 | AB97: =IFS(AND(AA97<=15000),15300,AND(AA97>15000,AA97<15500),AA97,AND(AA97>=15500,AA97<$Z$1),15500,AA97>=$Z$1,AA97*$AB$2) -> 15500 | AC97: =round(IF($AA97<=$Z$1,($AA97-$AB97)*AC$1,$AA97*AC$2),-1) -> 4050 | AD97: =round(IF($AA97<=$Z$1,($AA97-$AB97)*AD$1,$AA97*AD$2),-1)+AA97-AB97-AC97-round(IF($AA97<=$Z$1,($AA97-$AB97)*AD$1,$AA97*AD$2),-1) -> 6070 | AE97: 0 | AF97: =IF(SUM(AB97:AE97)=AA97,"OK","NO") -> OK | AG97: =IF(U97="US",IF(AA97<9750,"Under","US OK"),IF(U97="S",IF(AA97<12000,"Under","S OK"),"Skill Missing")) -> Skill Missing | AH97: =VLOOKUP(A97,'Advance Sheet'!$A$4:$A$165,1,FALSE) -> #REF! | AI97: =IF(ISERROR(VLOOKUP(A97,'SNP Sal Main'!$A$3:$A1596,1,false))=FALSE,"SNP SAL",IF(ISERROR(VLOOKUP(A97,'Rest Sal Main org'!$A$3:$A1596,1,false))=FALSE,"Rest Sal","Not Found")) -> Not Found | AL97: =AM97/12 -> 4.1666667 | AM97: =if(J97="","",datedif(J97,$AM$2,"M")) -> 50
A98: SE1216 | B98: SUMIT RANA | C98: Salary | D98: Cutting | E98: Operator | F98: SNP | G98: 0.33333333 | H98: 0.75 | I98: =IF(ISBLANK(H98),,H98-G98) -> 0.41666667 | J98: 44440 | K98: SE | L98: 21500 | M98: Chq | N98: Employed | O98: 45901 | P98: 18858 | S98: YES | T98: YES | V98: =P98 -> 18858 | W98: 0.11 | Y98: =if(W98="",V98,round(V98*(1+W98),-1)) -> 20930 | Z98: july 500 | AA98: =L98 -> 21500 | AB98: =IFS(AND(AA98<=15000),15300,AND(AA98>15000,AA98<15500),AA98,AND(AA98>=15500,AA98<$Z$1),15500,AA98>=$Z$1,AA98*$AB$2) -> 15500 | AC98: =round(IF($AA98<=$Z$1,($AA98-$AB98)*AC$1,$AA98*AC$2),-1) -> 2400 | AD98: =round(IF($AA98<=$Z$1,($AA98-$AB98)*AD$1,$AA98*AD$2),-1)+AA98-AB98-AC98-round(IF($AA98<=$Z$1,($AA98-$AB98)*AD$1,$AA98*AD$2),-1) -> 3600 | AE98: 0 | AF98: =IF(SUM(AB98:AE98)=AA98,"OK","NO") -> OK | AG98: =IF(U98="US",IF(AA98<9750,"Under","US OK"),IF(U98="S",IF(AA98<12000,"Under","S OK"),"Skill Missing")) -> Skill Missing | AH98: =VLOOKUP(A98,'Advance Sheet'!$A$4:$A$165,1,FALSE) -> #REF! | AI98: =IF(ISERROR(VLOOKUP(A98,'SNP Sal Main'!$A$3:$A1597,1,false))=FALSE,"SNP SAL",IF(ISERROR(VLOOKUP(A98,'Rest Sal Main org'!$A$3:$A1597,1,false))=FALSE,"Rest Sal","Not Found")) -> Not Found | AM98: =if(J98="","",datedif(J98,$AM$2,"M")) -> 60
A99: SE1217 | B99: JAI DEEP | C99: Salary | D99: Cutting | E99: Helper | F99: SNP | G99: 0.33333333 | H99: 0.75 | I99: =IF(ISBLANK(H99),,H99-G99) -> 0.41666667 | J99: 44158 | K99: SE | L99: 15279 | M99: Chq | N99: Employed | O99: 45901 | P99: 12400 | S99: YES | T99: YES | U99: US | V99: =P99 -> 12400 | W99: 0.12 | Y99: =if(W99="",V99,round(V99*(1+W99),-1)) -> 13890 | AA99: =L99 -> 15279 | AB99: =IFS(AND(AA99<=15000),15300,AND(AA99>15000,AA99<15500),AA99,AND(AA99>=15500,AA99<$Z$1),15500,AA99>=$Z$1,AA99*$AB$2) -> 15279 | AC99: =round(IF($AA99<=$Z$1,($AA99-$AB99)*AC$1,$AA99*AC$2),-1) -> 0 | AD99: =round(IF($AA99<=$Z$1,($AA99-$AB99)*AD$1,$AA99*AD$2),-1)+AA99-AB99-AC99-round(IF($AA99<=$Z$1,($AA99-$AB99)*AD$1,$AA99*AD$2),-1) -> 0 | AE99: 0 | AF99: =IF(SUM(AB99:AE99)=AA99,"OK","NO") -> OK | AG99: =IF(U99="US",IF(AA99<9750,"Under","US OK"),IF(U99="S",IF(AA99<12000,"Under","S OK"),"Skill Missing")) -> US OK | AH99: =VLOOKUP(A99,'Advance Sheet'!$A$4:$A$165,1,FALSE) -> #REF! | AI99: =IF(ISERROR(VLOOKUP(A99,'SNP Sal Main'!$A$3:$A1598,1,false))=FALSE,"SNP SAL",IF(ISERROR(VLOOKUP(A99,'Rest Sal Main org'!$A$3:$A1598,1,false))=FALSE,"Rest Sal","Not Found")) -> Not Found | AM99: =if(J99="","",datedif(J99,$AM$2,"M")) -> 70
A100: SE1219 | B100: DINSHA JAIN | C100: Salary | D100: Management | E100: Director | F100: DEL | G100: 0.375 | H100: 0.75 | I100: =IF(ISBLANK(H100),,H100-G100) -> 0.375 | J100: 44805 | K100: SE | L100: =Y100 -> 175000 | M100: Chq | N100: Employed | P100: 175000 | Q100: 25783 | T100: NO | V100: =P100 -> 175000 | W100: 0 | Y100: =if(W100="",V100,round(V100*(1+W100),-1)) -> 175000 | AA100: =L100 -> 175000 | AB100: =150000+25000 -> 175000 | AC100: 0 | AD100: 0 | AE100: 0 | AF100: =IF(SUM(AB100:AE100)=AA100,"OK","NO") -> OK | AG100: =IF(U100="US",IF(AA100<9750,"Under","US OK"),IF(U100="S",IF(AA100<12000,"Under","S OK"),"Skill Missing")) -> Skill Missing | AH100: =VLOOKUP(A100,'Advance Sheet'!$A$4:$A$165,1,FALSE) -> #REF! | AI100: =IF(ISERROR(VLOOKUP(A100,'SNP Sal Main'!$A$3:$A1599,1,false))=FALSE,"SNP SAL",IF(ISERROR(VLOOKUP(A100,'Rest Sal Main org'!$A$3:$A1599,1,false))=FALSE,"Rest Sal","Not Found")) -> Not Found | AM100: =if(J100="","",datedif(J100,$AM$2,"M")) -> 48
...

Sheet Copy of Advance Sheet
B1: -2 | D1: =text(EOMONTH(today(),B1),"mmmyyyy")&"!A:A" -> Jul2026!A:A | E1: =text(EOMONTH(today(),B1),"mmmyyyy")&"!R:R" -> Jul2026!R:R | F1: =SUBTOTAL(9,F4:F2010) -> 82100 | G1: =SUBTOTAL(9,G4:G2010) -> 508300 | H1: =SUBTOTAL(9,H4:H2010) -> 82100 | I1: =SUBTOTAL(9,I4:I2010) -> 599200 | J1: =SUBTOTAL(9,J4:J2010) -> 98600 | K1: =SUBTOTAL(9,K4:K2010) -> 528600 | L1: =SUBTOTAL(9,L4:L2010) -> 81000 | M1: =SUBTOTAL(9,M4:M2010) -> 595600 | ... DV1: =SUBTOTAL(9,DV4:DV2010) -> 704076
F2: Deduction | G2: Outstanding | H2: Deduction | I2: Outstanding | J2: Deduction | K2: Outstanding | L2: Deduction | M2: Outstanding | N2: Deduction | O2: Outstanding | P2: Deduction | Q2: Outstanding | R2: Deduction | S2: Outstanding | T2: Deduction | U2: Outstanding | V2: Deduction | W2: Outstanding | X2: Deduction | Y2: Outstanding | Z2: Deduction | AA2: Outstanding | AB2: Deduction | AC2: Outstanding | AD2: Deduction | AE2: Outstanding | AF2: Deduction | AG2: Outstanding | AH2: Deduction | AI2: Outstanding | AJ2: Deduction | AK2: Outstanding | AL2: Deduction | AM2: Outstanding | AN2: Deduction | AO2: Outstanding | AP2: Deduction | AQ2: Outstanding | AR2: Deduction | AS2: Outstanding | AT2: Deduction | AU2: Outstanding | AV2: Deduction | AW2: Outstanding | AX2: Deduction | AY2: Outstanding | AZ2: Deduction | BA2: Outstanding | BB2: Deduction | BC2: Outstanding | BD2: Deduction | BE2: Outstanding | BF2: Deduction | BG2: Outstanding | BH2: Deduction | BI2: Outstanding | BJ2: Deduction | BK2: Outstanding | BL2: Deduction | BM2: Outstanding | BN2: Deduction | BO2: Outstanding | BP2: Deduction | BQ2: Outstanding | BR2: Deduction | BS2: Outstanding | BT2: Deduction | BU2: Outstanding | BV2: Deduction | BW2: Outstanding | BX2: Deduction | BY2: Outstanding | BZ2: Deduction | CA2: Outstanding | CB2: Deduction | CC2: Outstanding | CD2: Deduction | CE2: Outstanding | CF2: Deduction | CG2: Outstanding | CH2: Deduction | CI2: Outstanding | CJ2: Deduction | CK2: Outstanding | CL2: Deduction | CM2: Outstanding | CN2: Deduction | CO2: Outstanding | CP2: Deduction | CQ2: Outstanding | CR2: Deduction | CS2: Outstanding | CT2: Deduction | CU2: Outstanding | CV2: Deduction | CW2: Outstanding | CX2: Deduction | CY2: Deduction | CZ2: Outstanding | DA2: Deduction | DB2: Outstanding | DC2: Deduction | DD2: Outstanding | DE2: Deduction | DF2: Outstanding | DG2: Deduction | DH2: Outstanding | DI2: Deduction | DJ2: Outstanding | DK2: Deduction | DL2: Outstanding | DM2: Deduction | DN2: Outstanding | DO2: Deduction | DP2: Outstanding | DQ2: Deduction | DR2: Outstanding | DS2: Deduction | DT2: Outstanding | DU2: Deduction | DV2: Outstanding
A3: Employee Code | B3: NAME | C3: Location | D3: Department | E3: Bal Adv Today | F3: Oct2021-D | H3: 2021-D | I3: Nov2021-O | J3: Nov2021-D | K3: Dec2021-O | L3: Dec2021-D | M3: Jan2022-O | N3: Jan2022-D | O3: Feb2022-O | P3: Feb2022-D | Q3: Mar2022-O | R3: Mar2022-D | S3: Apr2022-O | T3: Apr2022-D | U3: May2022-O | V3: May2022-D | W3: Jun2022-O | X3: Jun2022-D | Y3: Jul2022-O | Z3: Jul2022-D | AA3: Aug2022-O | AB3: Aug2022-D | AC3: Sep2022-O | AD3: Sep2022-D | AE3: Oct2022-O | AF3: Oct2022-D | AG3: Nov2022-O | AH3: Nov2022-D | AI3: Dec2022-O | AJ3: Dec2022-D | AK3: Jan2023-O | AL3: Jan2023-D | AM3: Feb2023-O | AN3: Feb2023-D | AO3: Mar2023-O | AP3: Mar2023-D | AQ3: Apr2023-O | AR3: Apr2023-D | AS3: May2023-O | AT3: May2023-D | AU3: Jun2023-O | AV3: Jun2023-D | AW3: Jul2023-O | AX3: Jul2023-D | AY3: Aug2023-O | AZ3: Aug2023-D | BA3: Sep2023-O | BB3: Sep2023-D | BC3: Oct2023-O | BD3: Oct2023-D | BE3: Nov2023-O | BF3: Nov2023-D | BG3: Dec2023-O | BH3: Dec2023-D | BI3: Jan2024-O | BJ3: Jan2024-D | BK3: Feb2024-O | BL3: Feb2024-D | BM3: Mar2024-O | BN3: Mar2024-D | BO3: Apr2024-O | BP3: Apr2024-D | BQ3: May2024-O | BR3: May2024-D | BS3: Jun2024-O | BT3: Jun2024-D | BU3: Jul2024-O | BV3: Jul2024-D | BW3: Aug2024-O | BX3: Aug2024-D | BY3: Sep2024-O | BZ3: Sep2024-D | CA3: Oct2024-O | CB3: Oct2024-D | CC3: Nov2024-O | CD3: Nov2024-D | CE3: Dec2024-O | CF3: Dec2024-D | CG3: Jan2025-O | CH3: Jan2025-D | CI3: Feb2025-O | CJ3: Feb2025-D | CK3: Mar2025-O | CL3: Mar2025-D | CM3: Apr2025-O | CN3: Apr2025-D | CO3: May2025-O | CP3: May2025-D | CQ3: Jun2025-O | CR3: Jun2025-D | CS3: Jul2025-O | CT3: Jul2025-D | CU3: Aug2025-O | CV3: Aug2025-D | CW3: Sep2025-O | CX3: Sep2025-D | CY3: Bonus | CZ3: Oct2025-O | DA3: Oct2025-D | DB3: Nov2025-O | DC3: Nov2025-D | DD3: Dec2025-O | DE3: Dec2025-D | DF3: Jan2026-O | DG3: Jan2026-D | DH3: Feb2026-O | DI3: Feb2026-D | DJ3: Mar2026-O | DK3: Mar2026-D | DL3: Apr2026-O | DM3: Apr2026-D | DN3: May2026-O | DO3: May2026-D | DP3: Jun2026-O | DQ3: Jun2026-D | DR3: Jul2026-O | DS3: Jul2026-D | DT3: Aug2026-O | DU3: Aug2026-D | DV3: Sep2026-O
A4: CO1001 | B4: HARESH | C4: {=_xlfn.XLOOKUP(A4,'Emp Master'!A:A,'Emp Master'!F:F)} -> BENG | D4: {=_xlfn.XLOOKUP(A4,'Emp Master'!A:A,'Emp Master'!D:D)} -> Sales & Marketing | E4: =_xlfn.XLOOKUP(A4,INDIRECT($D$1),INDIRECT($E$1),0) -> #REF! | I4: =G4-H4 -> 0 | K4: =I4-J4 -> 0 | M4: =K4-L4 -> 0 | O4: =M4-N4 -> 0 | Q4: =O4-P4 -> 0 | S4: =Q4-R4 -> 0 | U4: =S4-T4 -> 0 | W4: =U4-V4 -> 0 | Y4: =W4-X4 -> 0 | AA4: =Y4-Z4 -> 0 | AC4: =AA4-AB4 -> 0 | AE4: =AC4-AD4 -> 0 | AG4: =AE4-AF4 -> 0 | AI4: =AG4-AH4 -> 0 | AK4: =AI4-AJ4 -> 0 | AM4: =AK4-AL4 -> 0 | AO4: =AM4-AN4 -> 0 | AQ4: =AO4-AP4 -> 0 | AS4: =AQ4-AR4 -> 0 | AU4: =AS4-AT4 -> 0 | AW4: =AU4-AV4 -> 0 | AY4: =AW4-AX4 -> 0 | BA4: =AY4-AZ4 -> 0 | BC4: =BA4-BB4 -> 0 | BE4: =BC4-BD4 -> 0 | BG4: =BE4-BF4 -> 0 | BI4: =BG4-BH4 -> 0 | BK4: =BI4-BJ4 -> 0 | BM4: =BK4-BL4 -> 0 | BO4: =BM4-BN4 -> 0 | BQ4: =BO4-BP4 -> 0 | BS4: =BQ4-BR4 -> 0 | BU4: =BS4-BT4 -> 0 | BW4: =BU4-BV4 -> 0 | BY4: =BW4-BX4 -> 0 | CA4: =BY4-BZ4 -> 0 | CC4: =CA4-CB4 -> 0 | CE4: =CC4-CD4 -> 0 | CG4: =CE4-CF4 -> 0 | CI4: =CG4-CH4 -> 0 | CK4: =CI4-CJ4 -> 0 | CM4: =CK4-CL4 -> 0 | CO4: =CM4-CN4 -> 0 | CQ4: =CO4-CP4 -> 0 | CS4: =CQ4-CR4 -> 0 | CU4: =CS4-CT4 -> 0 | CW4: =CU4-CV4 -> 0 | CZ4: =CW4-CX4 -> 0 | DB4: =CZ4-DA4 -> 0 | DD4: =DB4-DC4 -> 0 | DF4: =DD4-DE4 -> 0 | DH4: =DF4-DG4 -> 0 | DJ4: =DH4-DI4 -> 0 | DL4: =DJ4-DK4 -> 0 | DM4: 0 | DN4: =DL4-DM4 -> 0 | DO4: 0 | DP4: =DN4-DO4 -> 0 | DQ4: 0 | DR4: =DP4-DQ4 -> 0 | DS4: 0 | DT4: =DR4-DS4 -> 0 | DU4: 0 | DV4: =DT4-DU4 -> 0
A5: CO1002 | B5: V UDAI SHANKAR | C5: {=_xlfn.XLOOKUP(A5,'Emp Master'!A:A,'Emp Master'!F:F)} -> MUM | D5: {=_xlfn.XLOOKUP(A5,'Emp Master'!A:A,'Emp Master'!D:D)} -> Agent | E5: =_xlfn.XLOOKUP(A5,INDIRECT($D$1),INDIRECT($E$1),0) -> #REF! | I5: =G5-H5 -> 0 | K5: =I5-J5 -> 0 | M5: =K5-L5 -> 0 | O5: =M5-N5 -> 0 | Q5: =O5-P5 -> 0 | S5: =Q5-R5 -> 0 | U5: =S5-T5 -> 0 | W5: =U5-V5 -> 0 | Y5: =W5-X5 -> 0 | AA5: =Y5-Z5 -> 0 | AC5: =AA5-AB5 -> 0 | AE5: =AC5-AD5 -> 0 | AG5: =AE5-AF5 -> 0 | AI5: =AG5-AH5 -> 0 | AK5: =AI5-AJ5 -> 0 | AM5: =AK5-AL5 -> 0 | AO5: =AM5-AN5 -> 0 | AQ5: =AO5-AP5 -> 0 | AS5: =AQ5-AR5 -> 0 | AU5: =AS5-AT5 -> 0 | AW5: =AU5-AV5 -> 0 | AY5: =AW5-AX5 -> 0 | BA5: =AY5-AZ5 -> 0 | BC5: =BA5-BB5 -> 0 | BE5: =BC5-BD5 -> 0 | BG5: =BE5-BF5 -> 0 | BI5: =BG5-BH5 -> 0 | BK5: =BI5-BJ5 -> 0 | BM5: =BK5-BL5 -> 0 | BO5: =BM5-BN5 -> 0 | BQ5: =BO5-BP5 -> 0 | BS5: =BQ5-BR5 -> 0 | BU5: =BS5-BT5 -> 0 | BW5: =BU5-BV5 -> 0 | BY5: =BW5-BX5 -> 0 | CA5: =BY5-BZ5 -> 0 | CC5: =CA5-CB5 -> 0 | CE5: =CC5-CD5 -> 0 | CG5: =CE5-CF5 -> 0 | CI5: =CG5-CH5 -> 0 | CK5: =CI5-CJ5 -> 0 | CM5: =CK5-CL5 -> 0 | CO5: =CM5-CN5 -> 0 | CQ5: =CO5-CP5 -> 0 | CS5: =CQ5-CR5 -> 0 | CU5: =CS5-CT5 -> 0 | CW5: =CU5-CV5 -> 0 | CZ5: =CW5-CX5 -> 0 | DB5: =CZ5-DA5 -> 0 | DD5: =DB5-DC5 -> 0 | DF5: =DD5-DE5 -> 0 | DH5: =DF5-DG5 -> 0 | DJ5: =DH5-DI5 -> 0 | DL5: =DJ5-DK5 -> 0 | DM5: 0 | DN5: =DL5-DM5 -> 0 | DO5: 0 | DP5: =DN5-DO5 -> 0 | DQ5: 0 | DR5: =DP5-DQ5 -> 0 | DS5: 0 | DT5: =DR5-DS5 -> 0 | DU5: 0 | DV5: =DT5-DU5 -> 0
A6: CO1003 | B6: VARUN KAUSHAL | C6: {=_xlfn.XLOOKUP(A6,'Emp Master'!A:A,'Emp Master'!F:F)} -> DEL | D6: {=_xlfn.XLOOKUP(A6,'Emp Master'!A:A,'Emp Master'!D:D)} -> Sales & Marketing | E6: =_xlfn.XLOOKUP(A6,INDIRECT($D$1),INDIRECT($E$1),0) -> #REF! | I6: 0 | K6: =I6-J6 -> 0 | M6: =K6-L6 -> 0 | O6: =M6-N6 -> 0 | Q6: =O6-P6 -> 0 | S6: =Q6-R6 -> 0 | U6: =S6-T6 -> 0 | W6: =U6-V6 -> 0 | Y6: =W6-X6 -> 0 | AA6: =Y6-Z6 -> 0 | AC6: =AA6-AB6 -> 0 | AE6: =AC6-AD6 -> 0 | AG6: =AE6-AF6 -> 0 | AI6: =AG6-AH6 -> 0 | AK6: =AI6-AJ6 -> 0 | AM6: =AK6-AL6 -> 0 | AO6: =AM6-AN6 -> 0 | AQ6: =AO6-AP6 -> 0 | AS6: =AQ6-AR6 -> 0 | AU6: =AS6-AT6 -> 0 | AW6: =AU6-AV6 -> 0 | AY6: =AW6-AX6 -> 0 | BA6: =AY6-AZ6 -> 0 | BC6: =BA6-BB6 -> 0 | BE6: =BC6-BD6 -> 0 | BG6: =BE6-BF6 -> 0 | BI6: =BG6-BH6 -> 0 | BK6: =BI6-BJ6 -> 0 | BM6: =BK6-BL6 -> 0 | BO6: =BM6-BN6 -> 0 | BQ6: =BO6-BP6 -> 0 | BS6: =BQ6-BR6 -> 0 | BU6: =BS6-BT6 -> 0 | BW6: =BU6-BV6 -> 0 | BY6: =BW6-BX6 -> 0 | CA6: =BY6-BZ6 -> 0 | CC6: =CA6-CB6 -> 0 | CE6: =CC6-CD6 -> 0 | CG6: =CE6-CF6 -> 0 | CI6: =CG6-CH6 -> 0 | CK6: =CI6-CJ6 -> 0 | CM6: =CK6-CL6 -> 0 | CO6: =CM6-CN6 -> 0 | CQ6: =CO6-CP6 -> 0 | CS6: =CQ6-CR6 -> 0 | CU6: =CS6-CT6 -> 0 | CW6: =CU6-CV6 -> 0 | CZ6: =CW6-CX6 -> 0 | DB6: =CZ6-DA6 -> 0 | DD6: =DB6-DC6 -> 0 | DF6: =DD6-DE6 -> 0 | DH6: =DF6-DG6 -> 0 | DJ6: =DH6-DI6 -> 0 | DL6: =DJ6-DK6 -> 0 | DM6: 0 | DN6: =DL6-DM6 -> 0 | DO6: 0 | DP6: =DN6-DO6 -> 0 | DQ6: 0 | DR6: =DP6-DQ6 -> 0 | DS6: 0 | DT6: =DR6-DS6 -> 0 | DU6: 0 | DV6: =DT6-DU6 -> 0
A7: CS1003 | B7: BABLI | C7: {=_xlfn.XLOOKUP(A7,'Emp Master'!A:A,'Emp Master'!F:F)} -> #N/A | D7: {=_xlfn.XLOOKUP(A7,'Emp Master'!A:A,'Emp Master'!D:D)} -> #N/A | E7: =_xlfn.XLOOKUP(A7,INDIRECT($D$1),INDIRECT($E$1),0) -> #REF! | I7: =G7-H7 -> 0 | K7: =I7-J7 -> 0 | M7: =K7-L7 -> 0 | O7: =M7-N7 -> 0 | Q7: =O7-P7 -> 0 | S7: =Q7-R7 -> 0 | U7: =S7-T7 -> 0 | W7: =U7-V7 -> 0 | Y7: =W7-X7 -> 0 | AA7: =Y7-Z7 -> 0 | AC7: =AA7-AB7 -> 0 | AE7: =AC7-AD7 -> 0 | AG7: =AE7-AF7 -> 0 | AI7: =AG7-AH7 -> 0 | AK7: =AI7-AJ7 -> 0 | AM7: =AK7-AL7 -> 0 | AO7: =AM7-AN7 -> 0 | AQ7: =AO7-AP7 -> 0 | AS7: =AQ7-AR7 -> 0 | AU7: =AS7-AT7 -> 0 | AW7: =AU7-AV7 -> 0 | AY7: =AW7-AX7 -> 0 | BA7: =AY7-AZ7 -> 0 | BC7: =BA7-BB7 -> 0 | BE7: =BC7-BD7 -> 0 | BG7: =BE7-BF7 -> 0 | BI7: =BG7-BH7 -> 0 | BK7: =BI7-BJ7 -> 0 | BM7: =BK7-BL7 -> 0 | BO7: =BM7-BN7 -> 0 | BQ7: =BO7-BP7 -> 0 | BS7: =BQ7-BR7 -> 0 | BU7: =BS7-BT7 -> 0 | BW7: =BU7-BV7 -> 0 | BY7: =BW7-BX7 -> 0 | CA7: =BY7-BZ7 -> 0 | CC7: =CA7-CB7 -> 0 | CE7: =CC7-CD7 -> 0 | CG7: =CE7-CF7 -> 0 | CI7: =CG7-CH7 -> 0 | CK7: =CI7-CJ7 -> 0 | CM7: =CK7-CL7 -> 0 | CO7: =CM7-CN7 -> 0 | CQ7: =CO7-CP7 -> 0 | CS7: =CQ7-CR7 -> 0 | CU7: =CS7-CT7 -> 0 | CW7: =CU7-CV7 -> 0 | CZ7: =CW7-CX7 -> 0 | DB7: =CZ7-DA7 -> 0 | DD7: =DB7-DC7 -> 0 | DF7: =DD7-DE7 -> 0 | DH7: =DF7-DG7 -> 0 | DJ7: =DH7-DI7 -> 0 | DL7: =DJ7-DK7 -> 0 | DM7: 0 | DN7: =DL7-DM7 -> 0 | DO7: 0 | DP7: =DN7-DO7 -> 0 | DQ7: 0 | DR7: =DP7-DQ7 -> 0 | DS7: 0 | DT7: =DR7-DS7 -> 0 | DU7: 0 | DV7: =DT7-DU7 -> 0
A8: CS1004 | B8: CHINKI | C8: {=_xlfn.XLOOKUP(A8,'Emp Master'!A:A,'Emp Master'!F:F)} -> #N/A | D8: {=_xlfn.XLOOKUP(A8,'Emp Master'!A:A,'Emp Master'!D:D)} -> #N/A | E8: =_xlfn.XLOOKUP(A8,INDIRECT($D$1),INDIRECT($E$1),0) -> #REF! | I8: =G8-H8 -> 0 | K8: =I8-J8 -> 0 | M8: =K8-L8 -> 0 | O8: =M8-N8 -> 0 | Q8: =O8-P8 -> 0 | S8: =Q8-R8 -> 0 | U8: =S8-T8 -> 0 | W8: =U8-V8 -> 0 | Y8: =W8-X8 -> 0 | AA8: =Y8-Z8 -> 0 | AC8: =AA8-AB8 -> 0 | AE8: =AC8-AD8 -> 0 | AG8: =AE8-AF8 -> 0 | AI8: =AG8-AH8 -> 0 | AK8: =AI8-AJ8 -> 0 | AM8: =AK8-AL8 -> 0 | AO8: =AM8-AN8 -> 0 | AQ8: =AO8-AP8 -> 0 | AS8: =AQ8-AR8 -> 0 | AU8: =AS8-AT8 -> 0 | AW8: =AU8-AV8 -> 0 | AY8: =AW8-AX8 -> 0 | BA8: =AY8-AZ8 -> 0 | BC8: =BA8-BB8 -> 0 | BE8: =BC8-BD8 -> 0 | BG8: =BE8-BF8 -> 0 | BI8: =BG8-BH8 -> 0 | BK8: =BI8-BJ8 -> 0 | BM8: =BK8-BL8 -> 0 | BO8: =BM8-BN8 -> 0 | BQ8: =BO8-BP8 -> 0 | BS8: =BQ8-BR8 -> 0 | BU8: =BS8-BT8 -> 0 | BW8: =BU8-BV8 -> 0 | BY8: =BW8-BX8 -> 0 | CA8: =BY8-BZ8 -> 0 | CC8: =CA8-CB8 -> 0 | CE8: =CC8-CD8 -> 0 | CG8: =CE8-CF8 -> 0 | CI8: =CG8-CH8 -> 0 | CK8: =CI8-CJ8 -> 0 | CM8: =CK8-CL8 -> 0 | CO8: =CM8-CN8 -> 0 | CQ8: =CO8-CP8 -> 0 | CS8: =CQ8-CR8 -> 0 | CU8: =CS8-CT8 -> 0 | CW8: =CU8-CV8 -> 0 | CZ8: =CW8-CX8 -> 0 | DB8: =CZ8-DA8 -> 0 | DD8: =DB8-DC8 -> 0 | DF8: =DD8-DE8 -> 0 | DH8: =DF8-DG8 -> 0 | DJ8: =DH8-DI8 -> 0 | DL8: =DJ8-DK8 -> 0 | DM8: 0 | DN8: =DL8-DM8 -> 0 | DO8: 0 | DP8: =DN8-DO8 -> 0 | DQ8: 0 | DR8: =DP8-DQ8 -> 0 | DS8: 0 | DT8: =DR8-DS8 -> 0 | DU8: 0 | DV8: =DT8-DU8 -> 0
A9: CS1010 | B9: Vinod | C9: {=_xlfn.XLOOKUP(A9,'Emp Master'!A:A,'Emp Master'!F:F)} -> #N/A | D9: {=_xlfn.XLOOKUP(A9,'Emp Master'!A:A,'Emp Master'!D:D)} -> #N/A | E9: =_xlfn.XLOOKUP(A9,INDIRECT($D$1),INDIRECT($E$1),0) -> #REF! | I9: =G9-H9 -> 0 | K9: =I9-J9 -> 0 | M9: =K9-L9 -> 0 | O9: =M9-N9 -> 0 | Q9: =O9-P9 -> 0 | S9: =Q9-R9 -> 0 | U9: =S9-T9 -> 0 | W9: =U9-V9 -> 0 | Y9: =W9-X9 -> 0 | AA9: =Y9-Z9 -> 0 | AC9: =AA9-AB9 -> 0 | AE9: =AC9-AD9 -> 0 | AG9: =AE9-AF9 -> 0 | AI9: =AG9-AH9 -> 0 | AK9: =AI9-AJ9 -> 0 | AM9: =AK9-AL9 -> 0 | AO9: =AM9-AN9 -> 0 | AQ9: =AO9-AP9 -> 0 | AS9: =AQ9-AR9 -> 0 | AU9: =AS9-AT9 -> 0 | AW9: =AU9-AV9 -> 0 | AY9: =AW9-AX9 -> 0 | BA9: =AY9-AZ9 -> 0 | BC9: =BA9-BB9 -> 0 | BE9: =BC9-BD9 -> 0 | BG9: =BE9-BF9 -> 0 | BI9: =BG9-BH9 -> 0 | BK9: =BI9-BJ9 -> 0 | BM9: =BK9-BL9 -> 0 | BO9: =BM9-BN9 -> 0 | BQ9: =BO9-BP9 -> 0 | BS9: =BQ9-BR9 -> 0 | BU9: =BS9-BT9 -> 0 | BW9: =BU9-BV9 -> 0 | BY9: =BW9-BX9 -> 0 | CA9: =BY9-BZ9 -> 0 | CC9: =CA9-CB9 -> 0 | CE9: =CC9-CD9 -> 0 | CG9: =CE9-CF9 -> 0 | CI9: =CG9-CH9 -> 0 | CK9: =CI9-CJ9 -> 0 | CM9: =CK9-CL9 -> 0 | CO9: =CM9-CN9 -> 0 | CQ9: =CO9-CP9 -> 0 | CS9: =CQ9-CR9 -> 0 | CU9: =CS9-CT9 -> 0 | CW9: =CU9-CV9 -> 0 | CZ9: =CW9-CX9 -> 0 | DB9: =CZ9-DA9 -> 0 | DD9: =DB9-DC9 -> 0 | DF9: =DD9-DE9 -> 0 | DH9: =DF9-DG9 -> 0 | DJ9: =DH9-DI9 -> 0 | DL9: =DJ9-DK9 -> 0 | DM9: 0 | DN9: =DL9-DM9 -> 0 | DO9: 0 | DP9: =DN9-DO9 -> 0 | DQ9: 0 | DR9: =DP9-DQ9 -> 0 | DS9: 0 | DT9: =DR9-DS9 -> 0 | DU9: 0 | DV9: =DT9-DU9 -> 0
A10: CS1011 | B10: JAIDEEP | C10: {=_xlfn.XLOOKUP(A10,'Emp Master'!A:A,'Emp Master'!F:F)} -> #N/A | D10: {=_xlfn.XLOOKUP(A10,'Emp Master'!A:A,'Emp Master'!D:D)} -> #N/A | E10: =_xlfn.XLOOKUP(A10,INDIRECT($D$1),INDIRECT($E$1),0) -> #REF! | I10: =G10-H10 -> 0 | K10: =I10-J10 -> 0 | M10: =K10-L10 -> 0 | O10: =M10-N10 -> 0 | Q10: =O10-P10 -> 0 | S10: =Q10-R10 -> 0 | U10: =S10-T10 -> 0 | W10: =U10-V10 -> 0 | Y10: =W10-X10 -> 0 | AA10: =Y10-Z10 -> 0 | AC10: =AA10-AB10 -> 0 | AE10: =AC10-AD10 -> 0 | AG10: =AE10-AF10 -> 0 | AI10: =AG10-AH10 -> 0 | AK10: =AI10-AJ10 -> 0 | AM10: =AK10-AL10 -> 0 | AO10: =AM10-AN10 -> 0 | AQ10: =AO10-AP10 -> 0 | AS10: =AQ10-AR10 -> 0 | AU10: =AS10-AT10 -> 0 | AW10: =AU10-AV10 -> 0 | AY10: =AW10-AX10 -> 0 | BA10: =AY10-AZ10 -> 0 | BC10: =BA10-BB10 -> 0 | BE10: =BC10-BD10 -> 0 | BG10: =BE10-BF10 -> 0 | BI10: =BG10-BH10 -> 0 | BK10: =BI10-BJ10 -> 0 | BM10: =BK10-BL10 -> 0 | BO10: =BM10-BN10 -> 0 | BQ10: =BO10-BP10 -> 0 | BS10: =BQ10-BR10 -> 0 | BU10: =BS10-BT10 -> 0 | BW10: =BU10-BV10 -> 0 | BY10: =BW10-BX10 -> 0 | CA10: =BY10-BZ10 -> 0 | CC10: =CA10-CB10 -> 0 | CE10: =CC10-CD10 -> 0 | CG10: =CE10-CF10 -> 0 | CI10: =CG10-CH10 -> 0 | CK10: =CI10-CJ10 -> 0 | CM10: =CK10-CL10 -> 0 | CO10: =CM10-CN10 -> 0 | CQ10: =CO10-CP10 -> 0 | CS10: =CQ10-CR10 -> 0 | CU10: =CS10-CT10 -> 0 | CW10: =CU10-CV10 -> 0 | CZ10: =CW10-CX10 -> 0 | DB10: =CZ10-DA10 -> 0 | DD10: =DB10-DC10 -> 0 | DF10: =DD10-DE10 -> 0 | DH10: =DF10-DG10 -> 0 | DJ10: =DH10-DI10 -> 0 | DL10: =DJ10-DK10 -> 0 | DM10: 0 | DN10: =DL10-DM10 -> 0 | DO10: 0 | DP10: =DN10-DO10 -> 0 | DQ10: 0 | DR10: =DP10-DQ10 -> 0 | DS10: 0 | DT10: =DR10-DS10 -> 0 | DU10: 0 | DV10: =DT10-DU10 -> 0
A11: CS1013 | B11: MOHAN | C11: {=_xlfn.XLOOKUP(A11,'Emp Master'!A:A,'Emp Master'!F:F)} -> #N/A | D11: {=_xlfn.XLOOKUP(A11,'Emp Master'!A:A,'Emp Master'!D:D)} -> #N/A | E11: =_xlfn.XLOOKUP(A11,INDIRECT($D$1),INDIRECT($E$1),0) -> #REF! | I11: =G11-H11 -> 0 | K11: =I11-J11 -> 0 | M11: =K11-L11 -> 0 | O11: =M11-N11 -> 0 | Q11: =O11-P11 -> 0 | S11: =Q11-R11 -> 0 | U11: =S11-T11 -> 0 | W11: =U11-V11 -> 0 | Y11: =W11-X11 -> 0 | AA11: =Y11-Z11 -> 0 | AC11: =AA11-AB11 -> 0 | AE11: =AC11-AD11 -> 0 | AG11: =AE11-AF11 -> 0 | AI11: =AG11-AH11 -> 0 | AK11: =AI11-AJ11 -> 0 | AM11: =AK11-AL11 -> 0 | AO11: =AM11-AN11 -> 0 | AQ11: =AO11-AP11 -> 0 | AS11: =AQ11-AR11 -> 0 | AU11: =AS11-AT11 -> 0 | AW11: =AU11-AV11 -> 0 | AY11: =AW11-AX11 -> 0 | BA11: =AY11-AZ11 -> 0 | BC11: =BA11-BB11 -> 0 | BE11: =BC11-BD11 -> 0 | BG11: =BE11-BF11 -> 0 | BI11: =BG11-BH11 -> 0 | BK11: =BI11-BJ11 -> 0 | BM11: =BK11-BL11 -> 0 | BO11: =BM11-BN11 -> 0 | BQ11: =BO11-BP11 -> 0 | BS11: =BQ11-BR11 -> 0 | BU11: =BS11-BT11 -> 0 | BW11: =BU11-BV11 -> 0 | BY11: =BW11-BX11 -> 0 | CA11: =BY11-BZ11 -> 0 | CC11: =CA11-CB11 -> 0 | CE11: =CC11-CD11 -> 0 | CG11: =CE11-CF11 -> 0 | CI11: =CG11-CH11 -> 0 | CK11: =CI11-CJ11 -> 0 | CM11: =CK11-CL11 -> 0 | CO11: =CM11-CN11 -> 0 | CQ11: =CO11-CP11 -> 0 | CS11: =CQ11-CR11 -> 0 | CU11: =CS11-CT11 -> 0 | CW11: =CU11-CV11 -> 0 | CZ11: =CW11-CX11 -> 0 | DB11: =CZ11-DA11 -> 0 | DD11: =DB11-DC11 -> 0 | DF11: =DD11-DE11 -> 0 | DH11: =DF11-DG11 -> 0 | DJ11: =DH11-DI11 -> 0 | DL11: =DJ11-DK11 -> 0 | DM11: 0 | DN11: =DL11-DM11 -> 0 | DO11: 0 | DP11: =DN11-DO11 -> 0 | DQ11: 0 | DR11: =DP11-DQ11 -> 0 | DS11: 0 | DT11: =DR11-DS11 -> 0 | DU11: 0 | DV11: =DT11-DU11 -> 0
A12: CS1014 | B12: PARDEEP SINGH | C12: {=_xlfn.XLOOKUP(A12,'Emp Master'!A:A,'Emp Master'!F:F)} -> #N/A | D12: {=_xlfn.XLOOKUP(A12,'Emp Master'!A:A,'Emp Master'!D:D)} -> #N/A | E12: =_xlfn.XLOOKUP(A12,INDIRECT($D$1),INDIRECT($E$1),0) -> #REF! | I12: =G12-H12 -> 0 | K12: =I12-J12 -> 0 | M12: =K12-L12 -> 0 | O12: =M12-N12 -> 0 | Q12: =O12-P12 -> 0 | S12: =Q12-R12 -> 0 | U12: =S12-T12 -> 0 | W12: =U12-V12 -> 0 | Y12: =W12-X12 -> 0 | AA12: =Y12-Z12 -> 0 | AC12: =AA12-AB12 -> 0 | AE12: =AC12-AD12 -> 0 | AG12: =AE12-AF12 -> 0 | AI12: =AG12-AH12 -> 0 | AK12: =AI12-AJ12 -> 0 | AM12: =AK12-AL12 -> 0 | AO12: =AM12-AN12 -> 0 | AQ12: =AO12-AP12 -> 0 | AS12: =AQ12-AR12 -> 0 | AU12: =AS12-AT12 -> 0 | AW12: =AU12-AV12 -> 0 | AY12: =AW12-AX12 -> 0 | BA12: =AY12-AZ12 -> 0 | BC12: =BA12-BB12 -> 0 | BE12: =BC12-BD12 -> 0 | BG12: =BE12-BF12 -> 0 | BI12: =BG12-BH12 -> 0 | BK12: =BI12-BJ12 -> 0 | BM12: =BK12-BL12 -> 0 | BO12: =BM12-BN12 -> 0 | BQ12: =BO12-BP12 -> 0 | BS12: =BQ12-BR12 -> 0 | BU12: =BS12-BT12 -> 0 | BW12: =BU12-BV12 -> 0 | BY12: =BW12-BX12 -> 0 | CA12: =BY12-BZ12 -> 0 | CC12: =CA12-CB12 -> 0 | CE12: =CC12-CD12 -> 0 | CG12: =CE12-CF12 -> 0 | CI12: =CG12-CH12 -> 0 | CK12: =CI12-CJ12 -> 0 | CM12: =CK12-CL12 -> 0 | CO12: =CM12-CN12 -> 0 | CQ12: =CO12-CP12 -> 0 | CS12: =CQ12-CR12 -> 0 | CU12: =CS12-CT12 -> 0 | CW12: =CU12-CV12 -> 0 | CZ12: =CW12-CX12 -> 0 | DB12: =CZ12-DA12 -> 0 | DD12: =DB12-DC12 -> 0 | DF12: =DD12-DE12 -> 0 | DH12: =DF12-DG12 -> 0 | DJ12: =DH12-DI12 -> 0 | DL12: =DJ12-DK12 -> 0 | DM12: 0 | DN12: =DL12-DM12 -> 0 | DO12: 0 | DP12: =DN12-DO12 -> 0 | DQ12: 0 | DR12: =DP12-DQ12 -> 0 | DS12: 0 | DT12: =DR12-DS12 -> 0 | DU12: 0 | DV12: =DT12-DU12 -> 0
A13: CS1017 | B13: RAHUL | C13: {=_xlfn.XLOOKUP(A13,'Emp Master'!A:A,'Emp Master'!F:F)} -> #N/A | D13: {=_xlfn.XLOOKUP(A13,'Emp Master'!A:A,'Emp Master'!D:D)} -> #N/A | E13: =_xlfn.XLOOKUP(A13,INDIRECT($D$1),INDIRECT($E$1),0) -> #REF! | I13: =G13-H13 -> 0 | K13: =I13-J13 -> 0 | M13: =K13-L13 -> 0 | O13: =M13-N13 -> 0 | Q13: =O13-P13 -> 0 | S13: =Q13-R13 -> 0 | U13: =S13-T13 -> 0 | W13: =U13-V13 -> 0 | Y13: =W13-X13 -> 0 | AA13: =Y13-Z13 -> 0 | AC13: =AA13-AB13 -> 0 | AE13: =AC13-AD13 -> 0 | AG13: =AE13-AF13 -> 0 | AI13: =AG13-AH13 -> 0 | AK13: =AI13-AJ13 -> 0 | AM13: =AK13-AL13 -> 0 | AO13: =AM13-AN13 -> 0 | AQ13: =AO13-AP13 -> 0 | AS13: =AQ13-AR13 -> 0 | AU13: =AS13-AT13 -> 0 | AW13: =AU13-AV13 -> 0 | AY13: =AW13-AX13 -> 0 | BA13: =AY13-AZ13 -> 0 | BC13: =BA13-BB13 -> 0 | BE13: =BC13-BD13 -> 0 | BG13: =BE13-BF13 -> 0 | BI13: =BG13-BH13 -> 0 | BK13: =BI13-BJ13 -> 0 | BM13: =BK13-BL13 -> 0 | BO13: =BM13-BN13 -> 0 | BQ13: =BO13-BP13 -> 0 | BS13: =BQ13-BR13 -> 0 | BU13: =BS13-BT13 -> 0 | BW13: =BU13-BV13 -> 0 | BY13: =BW13-BX13 -> 0 | CA13: =BY13-BZ13 -> 0 | CC13: =CA13-CB13 -> 0 | CE13: =CC13-CD13 -> 0 | CG13: =CE13-CF13 -> 0 | CI13: =CG13-CH13 -> 0 | CK13: =CI13-CJ13 -> 0 | CM13: =CK13-CL13 -> 0 | CO13: =CM13-CN13 -> 0 | CQ13: =CO13-CP13 -> 0 | CS13: =CQ13-CR13 -> 0 | CU13: =CS13-CT13 -> 0 | CW13: =CU13-CV13 -> 0 | CZ13: =CW13-CX13 -> 0 | DB13: =CZ13-DA13 -> 0 | DD13: =DB13-DC13 -> 0 | DF13: =DD13-DE13 -> 0 | DH13: =DF13-DG13 -> 0 | DJ13: =DH13-DI13 -> 0 | DL13: =DJ13-DK13 -> 0 | DM13: 0 | DN13: =DL13-DM13 -> 0 | DO13: 0 | DP13: =DN13-DO13 -> 0 | DQ13: 0 | DR13: =DP13-DQ13 -> 0 | DS13: 0 | DT13: =DR13-DS13 -> 0 | DU13: 0 | DV13: =DT13-DU13 -> 0
A14: CS1021 | B14: VISHAL | C14: {=_xlfn.XLOOKUP(A14,'Emp Master'!A:A,'Emp Master'!F:F)} -> #N/A | D14: {=_xlfn.XLOOKUP(A14,'Emp Master'!A:A,'Emp Master'!D:D)} -> #N/A | E14: =_xlfn.XLOOKUP(A14,INDIRECT($D$1),INDIRECT($E$1),0) -> #REF! | I14: =G14-H14 -> 0 | K14: =I14-J14 -> 0 | M14: =K14-L14 -> 0 | O14: =M14-N14 -> 0 | Q14: =O14-P14 -> 0 | S14: =Q14-R14 -> 0 | U14: =S14-T14 -> 0 | W14: =U14-V14 -> 0 | Y14: =W14-X14 -> 0 | AA14: =Y14-Z14 -> 0 | AC14: =AA14-AB14 -> 0 | AE14: =AC14-AD14 -> 0 | AG14: =AE14-AF14 -> 0 | AI14: =AG14-AH14 -> 0 | AK14: =AI14-AJ14 -> 0 | AM14: =AK14-AL14 -> 0 | AO14: =AM14-AN14 -> 0 | AQ14: =AO14-AP14 -> 0 | AS14: =AQ14-AR14 -> 0 | AU14: =AS14-AT14 -> 0 | AW14: =AU14-AV14 -> 0 | AY14: =AW14-AX14 -> 0 | BA14: =AY14-AZ14 -> 0 | BC14: =BA14-BB14 -> 0 | BE14: =BC14-BD14 -> 0 | BG14: =BE14-BF14 -> 0 | BI14: =BG14-BH14 -> 0 | BK14: =BI14-BJ14 -> 0 | BM14: =BK14-BL14 -> 0 | BO14: =BM14-BN14 -> 0 | BQ14: =BO14-BP14 -> 0 | BS14: =BQ14-BR14 -> 0 | BU14: =BS14-BT14 -> 0 | BW14: =BU14-BV14 -> 0 | BY14: =BW14-BX14 -> 0 | CA14: =BY14-BZ14 -> 0 | CC14: =CA14-CB14 -> 0 | CE14: =CC14-CD14 -> 0 | CG14: =CE14-CF14 -> 0 | CI14: =CG14-CH14 -> 0 | CK14: =CI14-CJ14 -> 0 | CM14: =CK14-CL14 -> 0 | CO14: =CM14-CN14 -> 0 | CQ14: =CO14-CP14 -> 0 | CS14: =CQ14-CR14 -> 0 | CU14: =CS14-CT14 -> 0 | CW14: =CU14-CV14 -> 0 | CZ14: =CW14-CX14 -> 0 | DB14: =CZ14-DA14 -> 0 | DD14: =DB14-DC14 -> 0 | DF14: =DD14-DE14 -> 0 | DH14: =DF14-DG14 -> 0 | DJ14: =DH14-DI14 -> 0 | DL14: =DJ14-DK14 -> 0 | DM14: 0 | DN14: =DL14-DM14 -> 0 | DO14: 0 | DP14: =DN14-DO14 -> 0 | DQ14: 0 | DR14: =DP14-DQ14 -> 0 | DS14: 0 | DT14: =DR14-DS14 -> 0 | DU14: 0 | DV14: =DT14-DU14 -> 0
A15: CS1022 | B15: RAJU MUM | C15: {=_xlfn.XLOOKUP(A15,'Emp Master'!A:A,'Emp Master'!F:F)} -> #N/A | D15: {=_xlfn.XLOOKUP(A15,'Emp Master'!A:A,'Emp Master'!D:D)} -> #N/A | E15: =_xlfn.XLOOKUP(A15,INDIRECT($D$1),INDIRECT($E$1),0) -> #REF! | I15: =G15-H15 -> 0 | K15: =I15-J15 -> 0 | M15: =K15-L15 -> 0 | O15: =M15-N15 -> 0 | Q15: =O15-P15 -> 0 | S15: =Q15-R15 -> 0 | U15: =S15-T15 -> 0 | W15: =U15-V15 -> 0 | Y15: =W15-X15 -> 0 | AA15: =Y15-Z15 -> 0 | AC15: =AA15-AB15 -> 0 | AE15: =AC15-AD15 -> 0 | AG15: =AE15-AF15 -> 0 | AI15: =AG15-AH15 -> 0 | AK15: =AI15-AJ15 -> 0 | AM15: =AK15-AL15 -> 0 | AO15: =AM15-AN15 -> 0 | AQ15: =AO15-AP15 -> 0 | AS15: =AQ15-AR15 -> 0 | AU15: =AS15-AT15 -> 0 | AW15: =AU15-AV15 -> 0 | AY15: =AW15-AX15 -> 0 | BA15: =AY15-AZ15 -> 0 | BC15: =BA15-BB15 -> 0 | BE15: =BC15-BD15 -> 0 | BG15: =BE15-BF15 -> 0 | BI15: =BG15-BH15 -> 0 | BK15: =BI15-BJ15 -> 0 | BM15: =BK15-BL15 -> 0 | BO15: =BM15-BN15 -> 0 | BQ15: =BO15-BP15 -> 0 | BS15: =BQ15-BR15 -> 0 | BU15: =BS15-BT15 -> 0 | BW15: =BU15-BV15 -> 0 | BY15: =BW15-BX15 -> 0 | CA15: =BY15-BZ15 -> 0 | CC15: =CA15-CB15 -> 0 | CE15: =CC15-CD15 -> 0 | CG15: =CE15-CF15 -> 0 | CI15: =CG15-CH15 -> 0 | CK15: =CI15-CJ15 -> 0 | CM15: =CK15-CL15 -> 0 | CO15: =CM15-CN15 -> 0 | CQ15: =CO15-CP15 -> 0 | CS15: =CQ15-CR15 -> 0 | CU15: =CS15-CT15 -> 0 | CW15: =CU15-CV15 -> 0 | CZ15: =CW15-CX15 -> 0 | DB15: =CZ15-DA15 -> 0 | DD15: =DB15-DC15 -> 0 | DF15: =DD15-DE15 -> 0 | DH15: =DF15-DG15 -> 0 | DJ15: =DH15-DI15 -> 0 | DL15: =DJ15-DK15 -> 0 | DM15: 0 | DN15: =DL15-DM15 -> 0 | DO15: 0 | DP15: =DN15-DO15 -> 0 | DQ15: 0 | DR15: =DP15-DQ15 -> 0 | DS15: 0 | DT15: =DR15-DS15 -> 0 | DU15: 0 | DV15: =DT15-DU15 -> 0
A16: CS1023 | B16: RAM NARYAN SINGH | C16: {=_xlfn.XLOOKUP(A16,'Emp Master'!A:A,'Emp Master'!F:F)} -> #N/A | D16: {=_xlfn.XLOOKUP(A16,'Emp Master'!A:A,'Emp Master'!D:D)} -> #N/A | E16: =_xlfn.XLOOKUP(A16,INDIRECT($D$1),INDIRECT($E$1),0) -> #REF! | I16: =G16-H16 -> 0 | K16: =I16-J16 -> 0 | M16: =K16-L16 -> 0 | O16: =M16-N16 -> 0 | Q16: =O16-P16 -> 0 | S16: =Q16-R16 -> 0 | U16: =S16-T16 -> 0 | W16: =U16-V16 -> 0 | Y16: =W16-X16 -> 0 | AA16: =Y16-Z16 -> 0 | AC16: =AA16-AB16 -> 0 | AE16: =AC16-AD16 -> 0 | AG16: =AE16-AF16 -> 0 | AI16: =AG16-AH16 -> 0 | AK16: =AI16-AJ16 -> 0 | AM16: =AK16-AL16 -> 0 | AO16: =AM16-AN16 -> 0 | AQ16: =AO16-AP16 -> 0 | AS16: =AQ16-AR16 -> 0 | AU16: =AS16-AT16 -> 0 | AW16: =AU16-AV16 -> 0 | AY16: =AW16-AX16 -> 0 | BA16: =AY16-AZ16 -> 0 | BC16: =BA16-BB16 -> 0 | BE16: =BC16-BD16 -> 0 | BG16: =BE16-BF16 -> 0 | BI16: =BG16-BH16 -> 0 | BK16: =BI16-BJ16 -> 0 | BM16: =BK16-BL16 -> 0 | BO16: =BM16-BN16 -> 0 | BQ16: =BO16-BP16 -> 0 | BS16: =BQ16-BR16 -> 0 | BU16: =BS16-BT16 -> 0 | BW16: =BU16-BV16 -> 0 | BY16: =BW16-BX16 -> 0 | CA16: =BY16-BZ16 -> 0 | CC16: =CA16-CB16 -> 0 | CE16: =CC16-CD16 -> 0 | CG16: =CE16-CF16 -> 0 | CI16: =CG16-CH16 -> 0 | CK16: =CI16-CJ16 -> 0 | CM16: =CK16-CL16 -> 0 | CO16: =CM16-CN16 -> 0 | CQ16: =CO16-CP16 -> 0 | CS16: =CQ16-CR16 -> 0 | CU16: =CS16-CT16 -> 0 | CW16: =CU16-CV16 -> 0 | CZ16: =CW16-CX16 -> 0 | DB16: =CZ16-DA16 -> 0 | DD16: =DB16-DC16 -> 0 | DF16: =DD16-DE16 -> 0 | DH16: =DF16-DG16 -> 0 | DJ16: =DH16-DI16 -> 0 | DL16: =DJ16-DK16 -> 0 | DM16: 0 | DN16: =DL16-DM16 -> 0 | DO16: 0 | DP16: =DN16-DO16 -> 0 | DQ16: 0 | DR16: =DP16-DQ16 -> 0 | DS16: 0 | DT16: =DR16-DS16 -> 0 | DU16: 0 | DV16: =DT16-DU16 -> 0
A17: CS1024 | B17: RAVINDER RAM | C17: {=_xlfn.XLOOKUP(A17,'Emp Master'!A:A,'Emp Master'!F:F)} -> #N/A | D17: {=_xlfn.XLOOKUP(A17,'Emp Master'!A:A,'Emp Master'!D:D)} -> #N/A | E17: =_xlfn.XLOOKUP(A17,INDIRECT($D$1),INDIRECT($E$1),0) -> #REF! | I17: =G17-H17 -> 0 | K17: =I17-J17 -> 0 | M17: =K17-L17 -> 0 | O17: =M17-N17 -> 0 | Q17: =O17-P17 -> 0 | S17: =Q17-R17 -> 0 | U17: =S17-T17 -> 0 | W17: =U17-V17 -> 0 | Y17: =W17-X17 -> 0 | AA17: =Y17-Z17 -> 0 | AC17: =AA17-AB17 -> 0 | AE17: =AC17-AD17 -> 0 | AG17: =AE17-AF17 -> 0 | AI17: =AG17-AH17 -> 0 | AK17: =AI17-AJ17 -> 0 | AM17: =AK17-AL17 -> 0 | AO17: =AM17-AN17 -> 0 | AQ17: =AO17-AP17 -> 0 | AS17: =AQ17-AR17 -> 0 | AU17: =AS17-AT17 -> 0 | AW17: =AU17-AV17 -> 0 | AY17: =AW17-AX17 -> 0 | BA17: =AY17-AZ17 -> 0 | BC17: =BA17-BB17 -> 0 | BE17: =BC17-BD17 -> 0 | BG17: =BE17-BF17 -> 0 | BI17: =BG17-BH17 -> 0 | BK17: =BI17-BJ17 -> 0 | BM17: =BK17-BL17 -> 0 | BO17: =BM17-BN17 -> 0 | BQ17: =BO17-BP17 -> 0 | BS17: =BQ17-BR17 -> 0 | BU17: =BS17-BT17 -> 0 | BW17: =BU17-BV17 -> 0 | BY17: =BW17-BX17 -> 0 | CA17: =BY17-BZ17 -> 0 | CC17: =CA17-CB17 -> 0 | CE17: =CC17-CD17 -> 0 | CG17: =CE17-CF17 -> 0 | CI17: =CG17-CH17 -> 0 | CK17: =CI17-CJ17 -> 0 | CM17: =CK17-CL17 -> 0 | CO17: =CM17-CN17 -> 0 | CQ17: =CO17-CP17 -> 0 | CS17: =CQ17-CR17 -> 0 | CU17: =CS17-CT17 -> 0 | CW17: =CU17-CV17 -> 0 | CZ17: =CW17-CX17 -> 0 | DB17: =CZ17-DA17 -> 0 | DD17: =DB17-DC17 -> 0 | DF17: =DD17-DE17 -> 0 | DH17: =DF17-DG17 -> 0 | DJ17: =DH17-DI17 -> 0 | DL17: =DJ17-DK17 -> 0 | DM17: 0 | DN17: =DL17-DM17 -> 0 | DO17: 0 | DP17: =DN17-DO17 -> 0 | DQ17: 0 | DR17: =DP17-DQ17 -> 0 | DS17: 0 | DT17: =DR17-DS17 -> 0 | DU17: 0 | DV17: =DT17-DU17 -> 0
A18: CS1025 | B18: REKHA | C18: {=_xlfn.XLOOKUP(A18,'Emp Master'!A:A,'Emp Master'!F:F)} -> #N/A | D18: {=_xlfn.XLOOKUP(A18,'Emp Master'!A:A,'Emp Master'!D:D)} -> #N/A | E18: =_xlfn.XLOOKUP(A18,INDIRECT($D$1),INDIRECT($E$1),0) -> #REF! | I18: =G18-H18 -> 0 | K18: =I18-J18 -> 0 | M18: =K18-L18 -> 0 | O18: =M18-N18 -> 0 | Q18: =O18-P18 -> 0 | S18: =Q18-R18 -> 0 | U18: =S18-T18 -> 0 | W18: =U18-V18 -> 0 | Y18: =W18-X18 -> 0 | AA18: =Y18-Z18 -> 0 | AC18: =AA18-AB18 -> 0 | AE18: =AC18-AD18 -> 0 | AG18: =AE18-AF18 -> 0 | AI18: =AG18-AH18 -> 0 | AK18: =AI18-AJ18 -> 0 | AM18: =AK18-AL18 -> 0 | AO18: =AM18-AN18 -> 0 | AQ18: =AO18-AP18 -> 0 | AS18: =AQ18-AR18 -> 0 | AU18: =AS18-AT18 -> 0 | AW18: =AU18-AV18 -> 0 | AY18: =AW18-AX18 -> 0 | BA18: =AY18-AZ18 -> 0 | BC18: =BA18-BB18 -> 0 | BE18: =BC18-BD18 -> 0 | BG18: =BE18-BF18 -> 0 | BI18: =BG18-BH18 -> 0 | BK18: =BI18-BJ18 -> 0 | BM18: =BK18-BL18 -> 0 | BO18: =BM18-BN18 -> 0 | BQ18: =BO18-BP18 -> 0 | BS18: =BQ18-BR18 -> 0 | BU18: =BS18-BT18 -> 0 | BW18: =BU18-BV18 -> 0 | BY18: =BW18-BX18 -> 0 | CA18: =BY18-BZ18 -> 0 | CC18: =CA18-CB18 -> 0 | CE18: =CC18-CD18 -> 0 | CG18: =CE18-CF18 -> 0 | CI18: =CG18-CH18 -> 0 | CK18: =CI18-CJ18 -> 0 | CM18: =CK18-CL18 -> 0 | CO18: =CM18-CN18 -> 0 | CQ18: =CO18-CP18 -> 0 | CS18: =CQ18-CR18 -> 0 | CU18: =CS18-CT18 -> 0 | CW18: =CU18-CV18 -> 0 | CZ18: =CW18-CX18 -> 0 | DB18: =CZ18-DA18 -> 0 | DD18: =DB18-DC18 -> 0 | DF18: =DD18-DE18 -> 0 | DH18: =DF18-DG18 -> 0 | DJ18: =DH18-DI18 -> 0 | DL18: =DJ18-DK18 -> 0 | DM18: 0 | DN18: =DL18-DM18 -> 0 | DO18: 0 | DP18: =DN18-DO18 -> 0 | DQ18: 0 | DR18: =DP18-DQ18 -> 0 | DS18: 0 | DT18: =DR18-DS18 -> 0 | DU18: 0 | DV18: =DT18-DU18 -> 0
... A21: CS1029 | B21: SONU KUMAR | C21: {=_xlfn.XLOOKUP(A21,'Emp Master'!A:A,'Emp Master'!F:F)} -> #N/A | D21: {=_xlfn.XLOOKUP(A21,'Emp Master'!A:A,'Emp Master'!D:D)} -> #N/A | E21: =_xlfn.XLOOKUP(A21,INDIRECT($D$1),INDIRECT($E$1),0) -> #REF! | I21: =G21-H21 -> 0 | K21: =I21-J21 -> 0 | M21: =K21-L21 -> 0 | O21: =M21-N21 -> 0 | Q21: =O21-P21 -> 0 | S21: =Q21-R21 -> 0 | U21: =S21-T21 -> 0 | W21: =U21-V21 -> 0 | Y21: =W21-X21 -> 0 | AA21: =Y21-Z21 -> 0 | AC21: =AA21-AB21 -> 0 | AE21: =AC21-AD21 -> 0 | AG21: =AE21-AF21 -> 0 | AI21: =AG21-AH21 -> 0 | AK21: =AI21-AJ21 -> 0 | AM21: =AK21-AL21 -> 0 | AO21: =AM21-AN21 -> 0 | AQ21: =AO21-AP21 -> 0 | AS21: =AQ21-AR21 -> 0 | AU21: =AS21-AT21 -> 0 | AW21: =AU21-AV21 -> 0 | AY21: =AW21-AX21 -> 0 | BA21: =AY21-AZ21 -> 0 | BC21: =BA21-BB21 -> 0 | BE21: =BC21-BD21 -> 0 | BG21: =BE21-BF21 -> 0 | BI21: =BG21-BH21 -> 0 | BK21: =BI21-BJ21 -> 0 | BM21: =BK21-BL21 -> 0 | BO21: =BM21-BN21 -> 0 | BQ21: =BO21-BP21 -> 0 | BS21: =BQ21-BR21 -> 0 | BU21: =BS21-BT21 -> 0 | BW21: =BU21-BV21 -> 0 | BY21: =BW21-BX21 -> 0 | CA21: =BY21-BZ21 -> 0 | CC21: =CA21-CB21 -> 0 | CE21: =CC21-CD21 -> 0 | CG21: =CE21-CF21 -> 0 | CI21: =CG21-CH21 -> 0 | CK21: =CI21-CJ21 -> 0 | CM21: =CK21-CL21 -> 0 | CO21: =CM21-CN21 -> 0 | CQ21: =CO21-CP21 -> 0 | CS21: =CQ21-CR21 -> 0 | CU21: =CS21-CT21 -> 0 | CW21: =CU21-CV21 -> 0 | CZ21: =CW21-CX21 -> 0 | DB21: =CZ21-DA21 -> 0 | DD21: =DB21-DC21 -> 0 | DF21: =DD21-DE21 -> 0 | DH21: =DF21-DG21 -> 0 | DJ21: =DH21-DI21 -> 0 | DL21: =DJ21-DK21 -> 0 | DM21: 0 | DN21: =DL21-DM21 -> 0 | DO21: 0 | DP21: =DN21-DO21 -> 0 | DQ21: 0 | DR21: =DP21-DQ21 -> 0 | DS21: 0 | DT21: =DR21-DS21 -> 0 | DU21: 0 | DV21: =DT21-DU21 -> 0
A22: CS1030 | B22: SUBHASH CHAND | C22: {=_xlfn.XLOOKUP(A22,'Emp Master'!A:A,'Emp Master'!F:F)} -> DEL | D22: {=_xlfn.XLOOKUP(A22,'Emp Master'!A:A,'Emp Master'!D:D)} -> Backend Ops | E22: =_xlfn.XLOOKUP(A22,INDIRECT($D$1),INDIRECT($E$1),0) -> #REF! | F22: 5000 | G22: 80000 | H22: 5000 | I22: =G22-H22 -> 75000 | J22: 5000 | K22: =I22-J22 -> 70000 | L22: 0 | M22: =K22-L22 -> 70000 | N22: 5000 | O22: =M22-N22 -> 65000 | P22: 5000 | Q22: =O22-P22 -> 60000 | R22: 5000 | S22: =Q22-R22 -> 55000 | T22: 5000 | U22: =S22-T22 -> 50000 | V22: 0 | W22: =U22-V22 -> 50000 | X22: 0 | Y22: =W22-X22 -> 50000 | Z22: 0 | AA22: =Y22-Z22 -> 50000 | AB22: 0 | AC22: =AA22-AB22 -> 50000 | AD22: 5000 | AE22: =AC22-AD22 -> 45000 | AF22: 5000 | AG22: =AE22-AF22 -> 40000 | AH22: 5000 | AI22: =AG22-AH22+100000 -> 135000 | AJ22: 5000 | AK22: =AI22-AJ22 -> 130000 | AL22: 5000 | AM22: =AK22-AL22 -> 125000 | AN22: 5000 | AO22: =AM22-AN22 -> 120000 | AP22: 5000 | AQ22: =AO22-AP22 -> 115000 | AR22: 5000 | AS22: =AQ22-AR22 -> 110000 | AT22: 5000 | AU22: =AS22-AT22 -> 105000 | AV22: 5000 | AW22: =AU22-AV22 -> 100000 | AX22: 5000 | AY22: =AW22-AX22 -> 95000 | AZ22: 5000 | BA22: =AY22-AZ22 -> 90000 | BB22: 5000 | BC22: =BA22-BB22 -> 85000 | BD22: 5000 | BE22: =BC22-BD22 -> 80000 | BF22: 5000 | BG22: =BE22-BF22 -> 75000 | BH22: 5000 | BI22: =BG22-BH22 -> 70000 | BJ22: 5000 | BK22: =BI22-BJ22 -> 65000 | BL22: 5000 | BM22: =BK22-BL22 -> 60000 | BN22: 5000 | BO22: =BM22-BN22 -> 55000 | BP22: 5000 | BQ22: =BO22-BP22 -> 50000 | BR22: 5000 | BS22: =BQ22-BR22 -> 45000 | BT22: 5000 | BU22: =BS22-BT22 -> 40000 | BV22: 5000 | BW22: =BU22-BV22 -> 35000 | BX22: 5000 | BY22: =BW22-BX22 -> 30000 | BZ22: 5000 | CA22: =BY22-BZ22 -> 25000 | CB22: 5000 | CC22: =CA22-CB22 -> 20000 | CD22: 5000 | CE22: =CC22-CD22 -> 15000 | CF22: 5000 | CG22: =CE22-CF22 -> 10000 | CH22: 5000 | CI22: =CG22-CH22 -> 5000 | CJ22: 5000 | CK22: =CI22-CJ22 -> 0 | CM22: =CK22-CL22 -> 0 | CO22: =CM22-CN22 -> 0 | CQ22: =CO22-CP22 -> 0 | CS22: =CQ22-CR22 -> 0 | CU22: =CS22-CT22 -> 0 | CW22: =CU22-CV22 -> 0 | CZ22: =CW22-CX22 -> 0 | DB22: =CZ22-DA22 -> 0 | DD22: =DB22-DC22 -> 0 | DF22: =DD22-DE22 -> 0 | DH22: =DF22-DG22 -> 0 | DJ22: =DH22-DI22 -> 0 | DL22: =DJ22-DK22 -> 0 | DM22: 0 | DN22: =DL22-DM22 -> 0 | DO22: 0 | DP22: =DN22-DO22 -> 0 | DQ22: 0 | DR22: =DP22-DQ22 -> 0 | DS22: 0 | DT22: =DR22-DS22 -> 0 | DU22: 0 | DV22: =DT22-DU22 -> 0
A23: CS1034 | B23: VICKY | C23: {=_xlfn.XLOOKUP(A23,'Emp Master'!A:A,'Emp Master'!F:F)} -> #N/A | D23: {=_xlfn.XLOOKUP(A23,'Emp Master'!A:A,'Emp Master'!D:D)} -> #N/A | E23: =_xlfn.XLOOKUP(A23,INDIRECT($D$1),INDIRECT($E$1),0) -> #REF! | I23: =G23-H23 -> 0 | K23: =I23-J23 -> 0 | M23: =K23-L23 -> 0 | O23: =M23-N23 -> 0 | Q23: =O23-P23 -> 0 | S23: =Q23-R23 -> 0 | U23: =S23-T23 -> 0 | W23: =U23-V23 -> 0 | Y23: =W23-X23 -> 0 | AA23: =Y23-Z23 -> 0 | AC23: =AA23-AB23 -> 0 | AE23: =AC23-AD23 -> 0 | AG23: =AE23-AF23 -> 0 | AI23: =AG23-AH23 -> 0 | AK23: =AI23-AJ23 -> 0 | AM23: =AK23-AL23 -> 0 | AO23: =AM23-AN23 -> 0 | AQ23: =AO23-AP23 -> 0 | AS23: =AQ23-AR23 -> 0 | AU23: =AS23-AT23 -> 0 | AW23: =AU23-AV23 -> 0 | AY23: =AW23-AX23 -> 0 | BA23: =AY23-AZ23 -> 0 | BC23: =BA23-BB23 -> 0 | BE23: =BC23-BD23 -> 0 | BG23: =BE23-BF23 -> 0 | BI23: =BG23-BH23 -> 0 | BK23: =BI23-BJ23 -> 0 | BM23: =BK23-BL23 -> 0 | BO23: =BM23-BN23 -> 0 | BQ23: =BO23-BP23 -> 0 | BS23: =BQ23-BR23 -> 0 | BU23: =BS23-BT23 -> 0 | BW23: =BU23-BV23 -> 0 | BY23: =BW23-BX23 -> 0 | CA23: =BY23-BZ23 -> 0 | CC23: =CA23-CB23 -> 0 | CE23: =CC23-CD23 -> 0 | CG23: =CE23-CF23 -> 0 | CI23: =CG23-CH23 -> 0 | CK23: =CI23-CJ23 -> 0 | CM23: =CK23-CL23 -> 0 | CO23: =CM23-CN23 -> 0 | CQ23: =CO23-CP23 -> 0 | CS23: =CQ23-CR23 -> 0 | CU23: =CS23-CT23 -> 0 | CW23: =CU23-CV23 -> 0 | CZ23: =CW23-CX23 -> 0 | DB23: =CZ23-DA23 -> 0 | DD23: =DB23-DC23 -> 0 | DF23: =DD23-DE23 -> 0 | DH23: =DF23-DG23 -> 0 | DJ23: =DH23-DI23 -> 0 | DL23: =DJ23-DK23 -> 0 | DM23: 0 | DN23: =DL23-DM23 -> 0 | DO23: 0 | DP23: =DN23-DO23 -> 0 | DQ23: 0 | DR23: =DP23-DQ23 -> 0 | DS23: 0 | DT23: =DR23-DS23 -> 0 | DU23: 0 | DV23: =DT23-DU23 -> 0
A24: CS1036 | B24: RAMJIT | C24: {=_xlfn.XLOOKUP(A24,'Emp Master'!A:A,'Emp Master'!F:F)} -> #N/A | D24: {=_xlfn.XLOOKUP(A24,'Emp Master'!A:A,'Emp Master'!D:D)} -> #N/A | E24: =_xlfn.XLOOKUP(A24,INDIRECT($D$1),INDIRECT($E$1),0) -> #REF! | I24: =G24-H24 -> 0 | K24: =I24-J24 -> 0 | M24: =K24-L24 -> 0 | O24: =M24-N24 -> 0 | Q24: =O24-P24 -> 0 | S24: =Q24-R24 -> 0 | U24: =S24-T24 -> 0 | W24: =U24-V24 -> 0 | Y24: =W24-X24 -> 0 | AA24: =Y24-Z24 -> 0 | AC24: =AA24-AB24 -> 0 | AE24: =AC24-AD24 -> 0 | AG24: =AE24-AF24 -> 0 | AI24: =AG24-AH24 -> 0 | AK24: =AI24-AJ24 -> 0 | AM24: =AK24-AL24 -> 0 | AO24: =AM24-AN24 -> 0 | AQ24: =AO24-AP24 -> 0 | AS24: =AQ24-AR24 -> 0 | AU24: =AS24-AT24 -> 0 | AW24: =AU24-AV24 -> 0 | AY24: =AW24-AX24 -> 0 | BA24: =AY24-AZ24 -> 0 | BC24: =BA24-BB24 -> 0 | BE24: =BC24-BD24 -> 0 | BG24: =BE24-BF24 -> 0 | BI24: =BG24-BH24 -> 0 | BK24: =BI24-BJ24 -> 0 | BM24: =BK24-BL24 -> 0 | BO24: =BM24-BN24 -> 0 | BQ24: =BO24-BP24 -> 0 | BS24: =BQ24-BR24 -> 0 | BU24: =BS24-BT24 -> 0 | BW24: =BU24-BV24 -> 0 | BY24: =BW24-BX24 -> 0 | CA24: =BY24-BZ24 -> 0 | CC24: =CA24-CB24 -> 0 | CE24: =CC24-CD24 -> 0 | CG24: =CE24-CF24 -> 0 | CI24: =CG24-CH24 -> 0 | CK24: =CI24-CJ24 -> 0 | CM24: =CK24-CL24 -> 0 | CO24: =CM24-CN24 -> 0 | CQ24: =CO24-CP24 -> 0 | CS24: =CQ24-CR24 -> 0 | CU24: =CS24-CT24 -> 0 | CW24: =CU24-CV24 -> 0 | CZ24: =CW24-CX24 -> 0 | DB24: =CZ24-DA24 -> 0 | DD24: =DB24-DC24 -> 0 | DF24: =DD24-DE24 -> 0 | DH24: =DF24-DG24 -> 0 | DJ24: =DH24-DI24 -> 0 | DL24: =DJ24-DK24 -> 0 | DM24: 0 | DN24: =DL24-DM24 -> 0 | DO24: 0 | DP24: =DN24-DO24 -> 0 | DQ24: 0 | DR24: =DP24-DQ24 -> 0 | DS24: 0 | DT24: =DR24-DS24 -> 0 | DU24: 0 | DV24: =DT24-DU24 -> 0
A25: CS1038 | B25: ROHIT | C25: {=_xlfn.XLOOKUP(A25,'Emp Master'!A:A,'Emp Master'!F:F)} -> #N/A | D25: {=_xlfn.XLOOKUP(A25,'Emp Master'!A:A,'Emp Master'!D:D)} -> #N/A | E25: =_xlfn.XLOOKUP(A25,INDIRECT($D$1),INDIRECT($E$1),0) -> #REF! | I25: =G25-H25 -> 0 | K25: =I25-J25 -> 0 | M25: =K25-L25 -> 0 | O25: =M25-N25 -> 0 | Q25: =O25-P25 -> 0 | S25: =Q25-R25 -> 0 | U25: =S25-T25 -> 0 | W25: =U25-V25 -> 0 | Y25: =W25-X25 -> 0 | AA25: =Y25-Z25 -> 0 | AC25: =AA25-AB25 -> 0 | AE25: =AC25-AD25 -> 0 | AG25: =AE25-AF25 -> 0 | AI25: =AG25-AH25 -> 0 | AK25: =AI25-AJ25 -> 0 | AM25: =AK25-AL25 -> 0 | AO25: =AM25-AN25 -> 0 | AQ25: =AO25-AP25 -> 0 | AS25: =AQ25-AR25 -> 0 | AU25: =AS25-AT25 -> 0 | AW25: =AU25-AV25 -> 0 | AY25: =AW25-AX25 -> 0 | BA25: =AY25-AZ25 -> 0 | BC25: =BA25-BB25 -> 0 | BE25: =BC25-BD25 -> 0 | BG25: =BE25-BF25 -> 0 | BI25: =BG25-BH25 -> 0 | BK25: =BI25-BJ25 -> 0 | BM25: =BK25-BL25 -> 0 | BO25: =BM25-BN25 -> 0 | BQ25: =BO25-BP25 -> 0 | BS25: =BQ25-BR25 -> 0 | BU25: =BS25-BT25 -> 0 | BW25: =BU25-BV25 -> 0 | BY25: =BW25-BX25 -> 0 | CA25: =BY25-BZ25 -> 0 | CC25: =CA25-CB25 -> 0 | CE25: =CC25-CD25 -> 0 | CG25: =CE25-CF25 -> 0 | CI25: =CG25-CH25 -> 0 | CK25: =CI25-CJ25 -> 0 | CM25: =CK25-CL25 -> 0 | CO25: =CM25-CN25 -> 0 | CQ25: =CO25-CP25 -> 0 | CS25: =CQ25-CR25 -> 0 | CU25: =CS25-CT25 -> 0 | CW25: =CU25-CV25 -> 0 | CZ25: =CW25-CX25 -> 0 | DB25: =CZ25-DA25 -> 0 | DD25: =DB25-DC25 -> 0 | DF25: =DD25-DE25 -> 0 | DH25: =DF25-DG25 -> 0 | DJ25: =DH25-DI25 -> 0 | DL25: =DJ25-DK25 -> 0 | DM25: 0 | DN25: =DL25-DM25 -> 0 | DO25: 0 | DP25: =DN25-DO25 -> 0 | DQ25: 0 | DR25: =DP25-DQ25 -> 0 | DS25: 0 | DT25: =DR25-DS25 -> 0 | DU25: 0 | DV25: =DT25-DU25 -> 0
A26: CS1039 | B26: BALI RAM | C26: {=_xlfn.XLOOKUP(A26,'Emp Master'!A:A,'Emp Master'!F:F)} -> #N/A | D26: {=_xlfn.XLOOKUP(A26,'Emp Master'!A:A,'Emp Master'!D:D)} -> #N/A | E26: =_xlfn.XLOOKUP(A26,INDIRECT($D$1),INDIRECT($E$1),0) -> #REF! | I26: =G26-H26 -> 0 | K26: =I26-J26 -> 0 | M26: =K26-L26 -> 0 | O26: =M26-N26 -> 0 | Q26: =O26-P26 -> 0 | S26: =Q26-R26 -> 0 | U26: =S26-T26 -> 0 | W26: =U26-V26 -> 0 | Y26: =W26-X26 -> 0 | AA26: =Y26-Z26 -> 0 | AC26: =AA26-AB26 -> 0 | AE26: =AC26-AD26 -> 0 | AG26: =AE26-AF26 -> 0 | AI26: =AG26-AH26 -> 0 | AK26: =AI26-AJ26 -> 0 | AM26: =AK26-AL26 -> 0 | AO26: =AM26-AN26 -> 0 | AQ26: =AO26-AP26 -> 0 | AS26: =AQ26-AR26 -> 0 | AU26: =AS26-AT26 -> 0 | AW26: =AU26-AV26 -> 0 | AY26: =AW26-AX26 -> 0 | BA26: =AY26-AZ26 -> 0 | BC26: =BA26-BB26 -> 0 | BE26: =BC26-BD26 -> 0 | BG26: =BE26-BF26 -> 0 | BI26: =BG26-BH26 -> 0 | BK26: =BI26-BJ26 -> 0 | BM26: =BK26-BL26 -> 0 | BO26: =BM26-BN26 -> 0 | BQ26: =BO26-BP26 -> 0 | BS26: =BQ26-BR26 -> 0 | BU26: =BS26-BT26 -> 0 | BW26: =BU26-BV26 -> 0 | BY26: =BW26-BX26 -> 0 | CA26: =BY26-BZ26 -> 0 | CC26: =CA26-CB26 -> 0 | CE26: =CC26-CD26 -> 0 | CG26: =CE26-CF26 -> 0 | CI26: =CG26-CH26 -> 0 | CK26: =CI26-CJ26 -> 0 | CM26: =CK26-CL26 -> 0 | CO26: =CM26-CN26 -> 0 | CQ26: =CO26-CP26 -> 0 | CS26: =CQ26-CR26 -> 0 | CU26: =CS26-CT26 -> 0 | CW26: =CU26-CV26 -> 0 | CZ26: =CW26-CX26 -> 0 | DB26: =CZ26-DA26 -> 0 | DD26: =DB26-DC26 -> 0 | DF26: =DD26-DE26 -> 0 | DH26: =DF26-DG26 -> 0 | DJ26: =DH26-DI26 -> 0 | DL26: =DJ26-DK26 -> 0 | DM26: 0 | DN26: =DL26-DM26 -> 0 | DO26: 0 | DP26: =DN26-DO26 -> 0 | DQ26: 0 | DR26: =DP26-DQ26 -> 0 | DS26: 0 | DT26: =DR26-DS26 -> 0 | DU26: 0 | DV26: =DT26-DU26 -> 0
A27: CS1040 | B27: AJAY | C27: {=_xlfn.XLOOKUP(A27,'Emp Master'!A:A,'Emp Master'!F:F)} -> #N/A | D27: {=_xlfn.XLOOKUP(A27,'Emp Master'!A:A,'Emp Master'!D:D)} -> #N/A | E27: =_xlfn.XLOOKUP(A27,INDIRECT($D$1),INDIRECT($E$1),0) -> #REF! | I27: =G27-H27 -> 0 | K27: =I27-J27 -> 0 | M27: =K27-L27 -> 0 | O27: =M27-N27 -> 0 | Q27: =O27-P27 -> 0 | S27: =Q27-R27 -> 0 | U27: =S27-T27 -> 0 | W27: =U27-V27 -> 0 | Y27: =W27-X27 -> 0 | AA27: =Y27-Z27 -> 0 | AC27: =AA27-AB27 -> 0 | AE27: =AC27-AD27 -> 0 | AG27: =AE27-AF27 -> 0 | AI27: =AG27-AH27 -> 0 | AK27: =AI27-AJ27 -> 0 | AM27: =AK27-AL27 -> 0 | AO27: =AM27-AN27 -> 0 | AQ27: =AO27-AP27 -> 0 | AS27: =AQ27-AR27 -> 0 | AU27: =AS27-AT27 -> 0 | AW27: =AU27-AV27 -> 0 | AY27: =AW27-AX27 -> 0 | BA27: =AY27-AZ27 -> 0 | BC27: =BA27-BB27 -> 0 | BE27: =BC27-BD27 -> 0 | BG27: =BE27-BF27 -> 0 | BI27: =BG27-BH27 -> 0 | BK27: =BI27-BJ27 -> 0 | BM27: =BK27-BL27 -> 0 | BO27: =BM27-BN27 -> 0 | BQ27: =BO27-BP27 -> 0 | BS27: =BQ27-BR27 -> 0 | BU27: =BS27-BT27 -> 0 | BW27: =BU27-BV27 -> 0 | BY27: =BW27-BX27 -> 0 | CA27: =BY27-BZ27 -> 0 | CC27: =CA27-CB27 -> 0 | CE27: =CC27-CD27 -> 0 | CG27: =CE27-CF27 -> 0 | CI27: =CG27-CH27 -> 0 | CK27: =CI27-CJ27 -> 0 | CM27: =CK27-CL27 -> 0 | CO27: =CM27-CN27 -> 0 | CQ27: =CO27-CP27 -> 0 | CS27: =CQ27-CR27 -> 0 | CU27: =CS27-CT27 -> 0 | CW27: =CU27-CV27 -> 0 | CZ27: =CW27-CX27 -> 0 | DB27: =CZ27-DA27 -> 0 | DD27: =DB27-DC27 -> 0 | DF27: =DD27-DE27 -> 0 | DH27: =DF27-DG27 -> 0 | DJ27: =DH27-DI27 -> 0 | DL27: =DJ27-DK27 -> 0 | DM27: 0 | DN27: =DL27-DM27 -> 0 | DO27: 0 | DP27: =DN27-DO27 -> 0 | DQ27: 0 | DR27: =DP27-DQ27 -> 0 | DS27: 0 | DT27: =DR27-DS27 -> 0 | DU27: 0 | DV27: =DT27-DU27 -> 0
A28: CS1041 | B28: JATIN | C28: {=_xlfn.XLOOKUP(A28,'Emp Master'!A:A,'Emp Master'!F:F)} -> #N/A | D28: {=_xlfn.XLOOKUP(A28,'Emp Master'!A:A,'Emp Master'!D:D)} -> #N/A | E28: =_xlfn.XLOOKUP(A28,INDIRECT($D$1),INDIRECT($E$1),0) -> #REF! | I28: =G28-H28 -> 0 | K28: =I28-J28 -> 0 | M28: =K28-L28 -> 0 | O28: =M28-N28 -> 0 | Q28: =O28-P28 -> 0 | S28: =Q28-R28 -> 0 | U28: =S28-T28 -> 0 | W28: =U28-V28 -> 0 | Y28: =W28-X28 -> 0 | AA28: =Y28-Z28 -> 0 | AC28: =AA28-AB28 -> 0 | AE28: =AC28-AD28 -> 0 | AG28: =AE28-AF28 -> 0 | AI28: =AG28-AH28 -> 0 | AK28: =AI28-AJ28 -> 0 | AM28: =AK28-AL28 -> 0 | AO28: =AM28-AN28 -> 0 | AQ28: =AO28-AP28 -> 0 | AS28: =AQ28-AR28 -> 0 | AU28: =AS28-AT28 -> 0 | AW28: =AU28-AV28 -> 0 | AY28: =AW28-AX28 -> 0 | BA28: =AY28-AZ28 -> 0 | BC28: =BA28-BB28 -> 0 | BE28: =BC28-BD28 -> 0 | BG28: =BE28-BF28 -> 0 | BI28: =BG28-BH28 -> 0 | BK28: =BI28-BJ28 -> 0 | BM28: =BK28-BL28 -> 0 | BO28: =BM28-BN28 -> 0 | BQ28: =BO28-BP28 -> 0 | BS28: =BQ28-BR28 -> 0 | BU28: =BS28-BT28 -> 0 | BW28: =BU28-BV28 -> 0 | BY28: =BW28-BX28 -> 0 | CA28: =BY28-BZ28 -> 0 | CC28: =CA28-CB28 -> 0 | CE28: =CC28-CD28 -> 0 | CG28: =CE28-CF28 -> 0 | CI28: =CG28-CH28 -> 0 | CK28: =CI28-CJ28 -> 0 | CM28: =CK28-CL28 -> 0 | CO28: =CM28-CN28 -> 0 | CQ28: =CO28-CP28 -> 0 | CS28: =CQ28-CR28 -> 0 | CU28: =CS28-CT28 -> 0 | CW28: =CU28-CV28 -> 0 | CZ28: =CW28-CX28 -> 0 | DB28: =CZ28-DA28 -> 0 | DD28: =DB28-DC28 -> 0 | DF28: =DD28-DE28 -> 0 | DH28: =DF28-DG28 -> 0 | DJ28: =DH28-DI28 -> 0 | DL28: =DJ28-DK28 -> 0 | DM28: 0 | DN28: =DL28-DM28 -> 0 | DO28: 0 | DP28: =DN28-DO28 -> 0 | DQ28: 0 | DR28: =DP28-DQ28 -> 0 | DS28: 0 | DT28: =DR28-DS28 -> 0 | DU28: 0 | DV28: =DT28-DU28 -> 0
A29: CS1042 | B29: PRINCE | C29: {=_xlfn.XLOOKUP(A29,'Emp Master'!A:A,'Emp Master'!F:F)} -> #N/A | D29: {=_xlfn.XLOOKUP(A29,'Emp Master'!A:A,'Emp Master'!D:D)} -> #N/A | E29: =_xlfn.XLOOKUP(A29,INDIRECT($D$1),INDIRECT($E$1),0) -> #REF! | I29: =G29-H29 -> 0 | K29: =I29-J29 -> 0 | M29: =K29-L29 -> 0 | O29: =M29-N29 -> 0 | Q29: =O29-P29 -> 0 | S29: =Q29-R29 -> 0 | U29: =S29-T29 -> 0 | W29: =U29-V29 -> 0 | Y29: =W29-X29 -> 0 | AA29: =Y29-Z29 -> 0 | AC29: =AA29-AB29 -> 0 | AE29: =AC29-AD29 -> 0 | AG29: =AE29-AF29 -> 0 | AI29: =AG29-AH29 -> 0 | AK29: =AI29-AJ29 -> 0 | AM29: =AK29-AL29 -> 0 | AO29: =AM29-AN29 -> 0 | AQ29: =AO29-AP29 -> 0 | AS29: =AQ29-AR29 -> 0 | AU29: =AS29-AT29 -> 0 | AW29: =AU29-AV29 -> 0 | AY29: =AW29-AX29 -> 0 | BA29: =AY29-AZ29 -> 0 | BC29: =BA29-BB29 -> 0 | BE29: =BC29-BD29 -> 0 | BG29: =BE29-BF29 -> 0 | BI29: =BG29-BH29 -> 0 | BK29: =BI29-BJ29 -> 0 | BM29: =BK29-BL29 -> 0 | BO29: =BM29-BN29 -> 0 | BQ29: =BO29-BP29 -> 0 | BS29: =BQ29-BR29 -> 0 | BU29: =BS29-BT29 -> 0 | BW29: =BU29-BV29 -> 0 | BY29: =BW29-BX29 -> 0 | CA29: =BY29-BZ29 -> 0 | CC29: =CA29-CB29 -> 0 | CE29: =CC29-CD29 -> 0 | CG29: =CE29-CF29 -> 0 | CI29: =CG29-CH29 -> 0 | CK29: =CI29-CJ29 -> 0 | CM29: =CK29-CL29 -> 0 | CO29: =CM29-CN29 -> 0 | CQ29: =CO29-CP29 -> 0 | CS29: =CQ29-CR29 -> 0 | CU29: =CS29-CT29 -> 0 | CW29: =CU29-CV29 -> 0 | CZ29: =CW29-CX29 -> 0 | DB29: =CZ29-DA29 -> 0 | DD29: =DB29-DC29 -> 0 | DF29: =DD29-DE29 -> 0 | DH29: =DF29-DG29 -> 0 | DJ29: =DH29-DI29 -> 0 | DL29: =DJ29-DK29 -> 0 | DM29: 0 | DN29: =DL29-DM29 -> 0 | DO29: 0 | DP29: =DN29-DO29 -> 0 | DQ29: 0 | DR29: =DP29-DQ29 -> 0 | DS29: 0 | DT29: =DR29-DS29 -> 0 | DU29: 0 | DV29: =DT29-DU29 -> 0
A30: CS1047 | B30: LEKHPAL SINGH | C30: {=_xlfn.XLOOKUP(A30,'Emp Master'!A:A,'Emp Master'!F:F)} -> #N/A | D30: {=_xlfn.XLOOKUP(A30,'Emp Master'!A:A,'Emp Master'!D:D)} -> #N/A | E30: =_xlfn.XLOOKUP(A30,INDIRECT($D$1),INDIRECT($E$1),0) -> #REF! | I30: =G30-H30 -> 0 | K30: =I30-J30 -> 0 | M30: =K30-L30 -> 0 | O30: =M30-N30 -> 0 | Q30: =O30-P30 -> 0 | S30: =Q30-R30 -> 0 | U30: =S30-T30 -> 0 | W30: =U30-V30 -> 0 | Y30: =W30-X30 -> 0 | AA30: =Y30-Z30 -> 0 | AC30: =AA30-AB30 -> 0 | AE30: =AC30-AD30 -> 0 | AG30: =AE30-AF30 -> 0 | AI30: =AG30-AH30 -> 0 | AK30: =AI30-AJ30 -> 0 | AM30: =AK30-AL30 -> 0 | AO30: =AM30-AN30 -> 0 | AQ30: =AO30-AP30 -> 0 | AS30: =AQ30-AR30 -> 0 | AU30: =AS30-AT30 -> 0 | AW30: =AU30-AV30 -> 0 | AY30: =AW30-AX30 -> 0 | BA30: =AY30-AZ30 -> 0 | BC30: =BA30-BB30 -> 0 | BE30: =BC30-BD30 -> 0 | BG30: =BE30-BF30 -> 0 | BI30: =BG30-BH30 -> 0 | BK30: =BI30-BJ30 -> 0 | BM30: =BK30-BL30 -> 0 | BO30: =BM30-BN30 -> 0 | BQ30: =BO30-BP30 -> 0 | BS30: =BQ30-BR30 -> 0 | BU30: =BS30-BT30 -> 0 | BW30: =BU30-BV30 -> 0 | BY30: =BW30-BX30 -> 0 | CA30: =BY30-BZ30 -> 0 | CC30: =CA30-CB30 -> 0 | CE30: =CC30-CD30 -> 0 | CG30: =CE30-CF30 -> 0 | CI30: =CG30-CH30 -> 0 | CK30: =CI30-CJ30 -> 0 | CM30: =CK30-CL30 -> 0 | CO30: =CM30-CN30 -> 0 | CQ30: =CO30-CP30 -> 0 | CS30: =CQ30-CR30 -> 0 | CU30: =CS30-CT30 -> 0 | CW30: =CU30-CV30 -> 0 | CZ30: =CW30-CX30 -> 0 | DB30: =CZ30-DA30 -> 0 | DD30: =DB30-DC30 -> 0 | DF30: =DD30-DE30 -> 0 | DH30: =DF30-DG30 -> 0 | DJ30: =DH30-DI30 -> 0 | DL30: =DJ30-DK30 -> 0 | DM30: 0 | DN30: =DL30-DM30 -> 0 | DO30: 0 | DP30: =DN30-DO30 -> 0 | DQ30: 0 | DR30: =DP30-DQ30 -> 0 | DS30: 0 | DT30: =DR30-DS30 -> 0 | DU30: 0 | DV30: =DT30-DU30 -> 0
A31: CS1048 | B31: VIKAS | C31: {=_xlfn.XLOOKUP(A31,'Emp Master'!A:A,'Emp Master'!F:F)} -> #N/A | D31: {=_xlfn.XLOOKUP(A31,'Emp Master'!A:A,'Emp Master'!D:D)} -> #N/A | E31: =_xlfn.XLOOKUP(A31,INDIRECT($D$1),INDIRECT($E$1),0) -> #REF! | I31: =G31-H31 -> 0 | K31: =I31-J31 -> 0 | M31: =K31-L31 -> 0 | O31: =M31-N31 -> 0 | Q31: =O31-P31 -> 0 | S31: =Q31-R31 -> 0 | U31: =S31-T31 -> 0 | W31: =U31-V31 -> 0 | Y31: =W31-X31 -> 0 | AA31: =Y31-Z31 -> 0 | AC31: =AA31-AB31 -> 0 | AE31: =AC31-AD31 -> 0 | AG31: =AE31-AF31 -> 0 | AI31: =AG31-AH31 -> 0 | AK31: =AI31-AJ31 -> 0 | AM31: =AK31-AL31 -> 0 | AO31: =AM31-AN31 -> 0 | AQ31: =AO31-AP31 -> 0 | AS31: =AQ31-AR31 -> 0 | AU31: =AS31-AT31 -> 0 | AW31: =AU31-AV31 -> 0 | AY31: =AW31-AX31 -> 0 | BA31: =AY31-AZ31 -> 0 | BC31: =BA31-BB31 -> 0 | BE31: =BC31-BD31 -> 0 | BG31: =BE31-BF31 -> 0 | BI31: =BG31-BH31 -> 0 | BK31: =BI31-BJ31 -> 0 | BM31: =BK31-BL31 -> 0 | BO31: =BM31-BN31 -> 0 | BQ31: =BO31-BP31 -> 0 | BS31: =BQ31-BR31 -> 0 | BU31: =BS31-BT31 -> 0 | BW31: =BU31-BV31 -> 0 | BY31: =BW31-BX31 -> 0 | CA31: =BY31-BZ31 -> 0 | CC31: =CA31-CB31 -> 0 | CE31: =CC31-CD31 -> 0 | CG31: =CE31-CF31 -> 0 | CI31: =CG31-CH31 -> 0 | CK31: =CI31-CJ31 -> 0 | CM31: =CK31-CL31 -> 0 | CO31: =CM31-CN31 -> 0 | CQ31: =CO31-CP31 -> 0 | CS31: =CQ31-CR31 -> 0 | CU31: =CS31-CT31 -> 0 | CW31: =CU31-CV31 -> 0 | CZ31: =CW31-CX31 -> 0 | DB31: =CZ31-DA31 -> 0 | DD31: =DB31-DC31 -> 0 | DF31: =DD31-DE31 -> 0 | DH31: =DF31-DG31 -> 0 | DJ31: =DH31-DI31 -> 0 | DL31: =DJ31-DK31 -> 0 | DM31: 0 | DN31: =DL31-DM31 -> 0 | DO31: 0 | DP31: =DN31-DO31 -> 0 | DQ31: 0 | DR31: =DP31-DQ31 -> 0 | DS31: 0 | DT31: =DR31-DS31 -> 0 | DU31: 0 | DV31: =DT31-DU31 -> 0
A32: CS1049 | B32: DEEPAK KUMAR | C32: {=_xlfn.XLOOKUP(A32,'Emp Master'!A:A,'Emp Master'!F:F)} -> #N/A | D32: {=_xlfn.XLOOKUP(A32,'Emp Master'!A:A,'Emp Master'!D:D)} -> #N/A | E32: =_xlfn.XLOOKUP(A32,INDIRECT($D$1),INDIRECT($E$1),0) -> #REF! | I32: =G32-H32 -> 0 | K32: =I32-J32 -> 0 | M32: =K32-L32 -> 0 | O32: =M32-N32 -> 0 | Q32: =O32-P32 -> 0 | S32: =Q32-R32 -> 0 | U32: =S32-T32 -> 0 | W32: =U32-V32 -> 0 | Y32: =W32-X32 -> 0 | AA32: =Y32-Z32 -> 0 | AC32: =AA32-AB32 -> 0 | AE32: =AC32-AD32 -> 0 | AG32: =AE32-AF32 -> 0 | AI32: =AG32-AH32 -> 0 | AK32: =AI32-AJ32 -> 0 | AM32: =AK32-AL32 -> 0 | AO32: =AM32-AN32 -> 0 | AQ32: =AO32-AP32 -> 0 | AS32: =AQ32-AR32 -> 0 | AU32: =AS32-AT32 -> 0 | AW32: =AU32-AV32 -> 0 | AY32: =AW32-AX32 -> 0 | BA32: =AY32-AZ32 -> 0 | BC32: =BA32-BB32 -> 0 | BE32: =BC32-BD32 -> 0 | BG32: =BE32-BF32 -> 0 | BI32: =BG32-BH32 -> 0 | BK32: =BI32-BJ32 -> 0 | BM32: =BK32-BL32 -> 0 | BO32: =BM32-BN32 -> 0 | BQ32: =BO32-BP32 -> 0 | BS32: =BQ32-BR32 -> 0 | BU32: =BS32-BT32 -> 0 | BW32: =BU32-BV32 -> 0 | BY32: =BW32-BX32 -> 0 | CA32: =BY32-BZ32 -> 0 | CC32: =CA32-CB32 -> 0 | CE32: =CC32-CD32 -> 0 | CG32: =CE32-CF32 -> 0 | CI32: =CG32-CH32 -> 0 | CK32: =CI32-CJ32 -> 0 | CM32: =CK32-CL32 -> 0 | CO32: =CM32-CN32 -> 0 | CQ32: =CO32-CP32 -> 0 | CS32: =CQ32-CR32 -> 0 | CU32: =CS32-CT32 -> 0 | CW32: =CU32-CV32 -> 0 | CZ32: =CW32-CX32 -> 0 | DB32: =CZ32-DA32 -> 0 | DD32: =DB32-DC32 -> 0 | DF32: =DD32-DE32 -> 0 | DH32: =DF32-DG32 -> 0 | DJ32: =DH32-DI32 -> 0 | DL32: =DJ32-DK32 -> 0 | DM32: 0 | DN32: =DL32-DM32 -> 0 | DO32: 0 | DP32: =DN32-DO32 -> 0 | DQ32: 0 | DR32: =DP32-DQ32 -> 0 | DS32: 0 | DT32: =DR32-DS32 -> 0 | DU32: 0 | DV32: =DT32-DU32 -> 0
A33: CS1050 | B33: BOBI KUMAR | C33: {=_xlfn.XLOOKUP(A33,'Emp Master'!A:A,'Emp Master'!F:F)} -> #N/A | D33: {=_xlfn.XLOOKUP(A33,'Emp Master'!A:A,'Emp Master'!D:D)} -> #N/A | E33: =_xlfn.XLOOKUP(A33,INDIRECT($D$1),INDIRECT($E$1),0) -> #REF! | I33: =G33-H33 -> 0 | K33: =I33-J33 -> 0 | M33: =K33-L33 -> 0 | O33: =M33-N33 -> 0 | Q33: =O33-P33 -> 0 | S33: =Q33-R33 -> 0 | U33: =S33-T33 -> 0 | W33: =U33-V33 -> 0 | Y33: =W33-X33 -> 0 | AA33: =Y33-Z33 -> 0 | AC33: =AA33-AB33 -> 0 | AE33: =AC33-AD33 -> 0 | AG33: =AE33-AF33 -> 0 | AI33: =AG33-AH33 -> 0 | AK33: =AI33-AJ33 -> 0 | AM33: =AK33-AL33 -> 0 | AO33: =AM33-AN33 -> 0 | AQ33: =AO33-AP33 -> 0 | AS33: =AQ33-AR33 -> 0 | AU33: =AS33-AT33 -> 0 | AW33: =AU33-AV33 -> 0 | AY33: =AW33-AX33 -> 0 | BA33: =AY33-AZ33 -> 0 | BC33: =BA33-BB33 -> 0 | BE33: =BC33-BD33 -> 0 | BG33: =BE33-BF33 -> 0 | BI33: =BG33-BH33 -> 0 | BK33: =BI33-BJ33 -> 0 | BM33: =BK33-BL33 -> 0 | BO33: =BM33-BN33 -> 0 | BQ33: =BO33-BP33 -> 0 | BS33: =BQ33-BR33 -> 0 | BU33: =BS33-BT33 -> 0 | BW33: =BU33-BV33 -> 0 | BY33: =BW33-BX33 -> 0 | CA33: =BY33-BZ33 -> 0 | CC33: =CA33-CB33 -> 0 | CE33: =CC33-CD33 -> 0 | CG33: =CE33-CF33 -> 0 | CI33: =CG33-CH33 -> 0 | CK33: =CI33-CJ33 -> 0 | CM33: =CK33-CL33 -> 0 | CO33: =CM33-CN33 -> 0 | CQ33: =CO33-CP33 -> 0 | CS33: =CQ33-CR33 -> 0 | CU33: =CS33-CT33 -> 0 | CW33: =CU33-CV33 -> 0 | CZ33: =CW33-CX33 -> 0 | DB33: =CZ33-DA33 -> 0 | DD33: =DB33-DC33 -> 0 | DF33: =DD33-DE33 -> 0 | DH33: =DF33-DG33 -> 0 | DJ33: =DH33-DI33 -> 0 | DL33: =DJ33-DK33 -> 0 | DM33: 0 | DN33: =DL33-DM33 -> 0 | DO33: 0 | DP33: =DN33-DO33 -> 0 | DQ33: 0 | DR33: =DP33-DQ33 -> 0 | DS33: 0 | DT33: =DR33-DS33 -> 0 | DU33: 0 | DV33: =DT33-DU33 -> 0
A34: CS1051 | B34: GAURAV DAHIYA | C34: {=_xlfn.XLOOKUP(A34,'Emp Master'!A:A,'Emp Master'!F:F)} -> #N/A | D34: {=_xlfn.XLOOKUP(A34,'Emp Master'!A:A,'Emp Master'!D:D)} -> #N/A | E34: =_xlfn.XLOOKUP(A34,INDIRECT($D$1),INDIRECT($E$1),0) -> #REF! | I34: =G34-H34 -> 0 | K34: =I34-J34 -> 0 | M34: =K34-L34 -> 0 | O34: =M34-N34 -> 0 | Q34: =O34-P34 -> 0 | S34: =Q34-R34 -> 0 | U34: =S34-T34 -> 0 | W34: =U34-V34 -> 0 | Y34: =W34-X34 -> 0 | AA34: =Y34-Z34 -> 0 | AC34: =AA34-AB34 -> 0 | AE34: =AC34-AD34 -> 0 | AG34: =AE34-AF34 -> 0 | AI34: =AG34-AH34 -> 0 | AK34: =AI34-AJ34 -> 0 | AM34: =AK34-AL34 -> 0 | AO34: =AM34-AN34 -> 0 | AQ34: =AO34-AP34 -> 0 | AS34: =AQ34-AR34 -> 0 | AU34: =AS34-AT34 -> 0 | AW34: =AU34-AV34 -> 0 | AY34: =AW34-AX34 -> 0 | BA34: =AY34-AZ34 -> 0 | BC34: =BA34-BB34 -> 0 | BE34: =BC34-BD34 -> 0 | BG34: =BE34-BF34 -> 0 | BI34: =BG34-BH34 -> 0 | BK34: =BI34-BJ34 -> 0 | BM34: =BK34-BL34 -> 0 | BO34: =BM34-BN34 -> 0 | BQ34: =BO34-BP34 -> 0 | BS34: =BQ34-BR34 -> 0 | BU34: =BS34-BT34 -> 0 | BW34: =BU34-BV34 -> 0 | BY34: =BW34-BX34 -> 0 | CA34: =BY34-BZ34 -> 0 | CC34: =CA34-CB34 -> 0 | CE34: =CC34-CD34 -> 0 | CG34: =CE34-CF34 -> 0 | CI34: =CG34-CH34 -> 0 | CK34: =CI34-CJ34 -> 0 | CM34: =CK34-CL34 -> 0 | CO34: =CM34-CN34 -> 0 | CQ34: =CO34-CP34 -> 0 | CS34: =CQ34-CR34 -> 0 | CU34: =CS34-CT34 -> 0 | CW34: =CU34-CV34 -> 0 | CZ34: =CW34-CX34 -> 0 | DB34: =CZ34-DA34 -> 0 | DD34: =DB34-DC34 -> 0 | DF34: =DD34-DE34 -> 0 | DH34: =DF34-DG34 -> 0 | DJ34: =DH34-DI34 -> 0 | DL34: =DJ34-DK34 -> 0 | DM34: 0 | DN34: =DL34-DM34 -> 0 | DO34: 0 | DP34: =DN34-DO34 -> 0 | DQ34: 0 | DR34: =DP34-DQ34 -> 0 | DS34: 0 | DT34: =DR34-DS34 -> 0 | DU34: 0 | DV34: =DT34-DU34 -> 0
... A44: CS1062 | B44: SHRIPAL | C44: {=_xlfn.XLOOKUP(A44,'Emp Master'!A:A,'Emp Master'!F:F)} -> #N/A | D44: {=_xlfn.XLOOKUP(A44,'Emp Master'!A:A,'Emp Master'!D:D)} -> #N/A | E44: =_xlfn.XLOOKUP(A44,INDIRECT($D$1),INDIRECT($E$1),0) -> #REF! | I44: =G44-H44 -> 0 | K44: =I44-J44 -> 0 | M44: =K44-L44 -> 0 | O44: =M44-N44 -> 0 | Q44: =O44-P44 -> 0 | S44: =Q44-R44 -> 0 | U44: =S44-T44 -> 0 | W44: =U44-V44 -> 0 | Y44: =W44-X44 -> 0 | AA44: =Y44-Z44 -> 0 | AC44: =AA44-AB44 -> 0 | AE44: =AC44-AD44 -> 0 | AG44: =AE44-AF44 -> 0 | AI44: =AG44-AH44 -> 0 | AK44: =AI44-AJ44 -> 0 | AM44: =AK44-AL44 -> 0 | AO44: =AM44-AN44 -> 0 | AQ44: =AO44-AP44 -> 0 | AS44: =AQ44-AR44 -> 0 | AU44: =AS44-AT44 -> 0 | AW44: =AU44-AV44 -> 0 | AY44: =AW44-AX44 -> 0 | BA44: =AY44-AZ44 -> 0 | BC44: =BA44-BB44 -> 0 | BE44: =BC44-BD44 -> 0 | BG44: =BE44-BF44 -> 0 | BI44: =BG44-BH44 -> 0 | BK44: =BI44-BJ44 -> 0 | BM44: =BK44-BL44 -> 0 | BO44: =BM44-BN44 -> 0 | BQ44: =BO44-BP44 -> 0 | BS44: =BQ44-BR44 -> 0 | BU44: =BS44-BT44 -> 0 | BW44: =BU44-BV44 -> 0 | BY44: =BW44-BX44 -> 0 | CA44: =BY44-BZ44 -> 0 | CC44: =CA44-CB44 -> 0 | CE44: =CC44-CD44 -> 0 | CG44: =CE44-CF44 -> 0 | CI44: =CG44-CH44 -> 0 | CK44: =CI44-CJ44 -> 0 | CM44: =CK44-CL44 -> 0 | CO44: =CM44-CN44 -> 0 | CQ44: =CO44-CP44 -> 0 | CS44: =CQ44-CR44 -> 0 | CU44: =CS44-CT44 -> 0 | CW44: =CU44-CV44 -> 0 | CZ44: =CW44-CX44 -> 0 | DB44: =CZ44-DA44 -> 0 | DD44: =DB44-DC44 -> 0 | DF44: =DD44-DE44 -> 0 | DH44: =DF44-DG44 -> 0 | DJ44: =DH44-DI44 -> 0 | DL44: =DJ44-DK44 -> 0 | DM44: 0 | DN44: =DL44-DM44 -> 0 | DO44: 0 | DP44: =DN44-DO44 -> 0 | DQ44: 0 | DR44: =DP44-DQ44 -> 0 | DS44: 0 | DT44: =DR44-DS44 -> 0 | DU44: 0 | DV44: =DT44-DU44 -> 0
A45: CS1102 | B45: SANJAY | C45: {=_xlfn.XLOOKUP(A45,'Emp Master'!A:A,'Emp Master'!F:F)} -> #N/A | D45: {=_xlfn.XLOOKUP(A45,'Emp Master'!A:A,'Emp Master'!D:D)} -> #N/A | E45: =_xlfn.XLOOKUP(A45,INDIRECT($D$1),INDIRECT($E$1),0) -> #REF! | BI45: =BG45-BH45 -> 0 | BS45: =BQ45-BR45 -> 0 | BU45: =BS45-BT45 -> 0 | BW45: =BU45-BV45 -> 0 | BY45: =BW45-BX45 -> 0 | CA45: =BY45-BZ45 -> 0 | CC45: =CA45-CB45 -> 0 | CE45: =CC45-CD45 -> 0 | CG45: =CE45-CF45 -> 0 | CI45: =CG45-CH45 -> 0 | CK45: =CI45-CJ45 -> 0 | CM45: =CK45-CL45 -> 0 | CO45: =CM45-CN45 -> 0 | CQ45: =CO45-CP45 -> 0 | CS45: =CQ45-CR45 -> 0 | CU45: =CS45-CT45 -> 0 | CW45: =CU45-CV45 -> 0 | CZ45: =CW45-CX45 -> 0 | DB45: =CZ45-DA45 -> 0 | DD45: =DB45-DC45 -> 0 | DF45: =DD45-DE45 -> 0 | DH45: =DF45-DG45 -> 0 | DJ45: =DH45-DI45 -> 0 | DL45: =DJ45-DK45 -> 0 | DM45: 0 | DN45: =DL45-DM45 -> 0 | DO45: 0 | DP45: =DN45-DO45 -> 0 | DQ45: 0 | DR45: =DP45-DQ45 -> 0 | DS45: 0 | DT45: =DR45-DS45 -> 0 | DU45: 0 | DV45: =DT45-DU45 -> 0
A46: CS1112 | B46: CHIRAG | C46: {=_xlfn.XLOOKUP(A46,'Emp Master'!A:A,'Emp Master'!F:F)} -> #N/A | D46: {=_xlfn.XLOOKUP(A46,'Emp Master'!A:A,'Emp Master'!D:D)} -> #N/A | E46: =_xlfn.XLOOKUP(A46,INDIRECT($D$1),INDIRECT($E$1),0) -> #REF! | BG46: =BE46-BF46+12500 -> 12500 | BH46: 6000 | BI46: =BG46-BH46 -> 6500 | BJ46: 2000 | BK46: =BI46-BJ46 -> 4500 | BM46: =BK46-BL46 -> 4500 | BN46: 2000 | BO46: =BM46-BN46 -> 2500 | BP46: 2500 | BQ46: =BO46-BP46 -> 0 | BS46: =BQ46-BR46 -> 0 | BU46: =BS46-BT46 -> 0 | BW46: =BU46-BV46 -> 0 | BY46: =BW46-BX46 -> 0 | CA46: =BY46-BZ46 -> 0 | CC46: =CA46-CB46 -> 0 | CE46: =CC46-CD46 -> 0 | CG46: =CE46-CF46 -> 0 | CI46: =CG46-CH46 -> 0 | CK46: =CI46-CJ46 -> 0 | CM46: =CK46-CL46 -> 0 | CO46: =CM46-CN46 -> 0 | CQ46: =CO46-CP46 -> 0 | CS46: =CQ46-CR46 -> 0 | CU46: =CS46-CT46 -> 0 | CW46: =CU46-CV46 -> 0 | CZ46: =CW46-CX46 -> 0 | DB46: =CZ46-DA46 -> 0 | DD46: =DB46-DC46 -> 0 | DF46: =DD46-DE46 -> 0 | DH46: =DF46-DG46 -> 0 | DJ46: =DH46-DI46 -> 0 | DL46: =DJ46-DK46 -> 0 | DM46: 0 | DN46: =DL46-DM46 -> 0 | DO46: 0 | DP46: =DN46-DO46 -> 0 | DQ46: 0 | DR46: =DP46-DQ46 -> 0 | DS46: 0 | DT46: =DR46-DS46 -> 0 | DU46: 0 | DV46: =DT46-DU46 -> 0
A47: CS1132 | B47: RAJU MAHTO | C47: {=_xlfn.XLOOKUP(A47,'Emp Master'!A:A,'Emp Master'!F:F)} -> #N/A | D47: {=_xlfn.XLOOKUP(A47,'Emp Master'!A:A,'Emp Master'!D:D)} -> #N/A | E47: =_xlfn.XLOOKUP(A47,INDIRECT($D$1),INDIRECT($E$1),0) -> #REF! | BI47: =BG47-BH47 -> 0 | BQ47: 500 | BR47: 500 | BS47: =BQ47-BR47 -> 0 | BU47: =BS47-BT47 -> 0 | BW47: =BU47-BV47 -> 0 | BY47: =BW47-BX47 -> 0 | CA47: =BY47-BZ47 -> 0 | CC47: =CA47-CB47 -> 0 | CE47: =CC47-CD47 -> 0 | CG47: =CE47-CF47 -> 0 | CI47: =CG47-CH47 -> 0 | CK47: =CI47-CJ47 -> 0 | CM47: =CK47-CL47 -> 0 | CO47: =CM47-CN47 -> 0 | CQ47: =CO47-CP47 -> 0 | CS47: =CQ47-CR47 -> 0 | CU47: =CS47-CT47 -> 0 | CW47: =CU47-CV47 -> 0 | CZ47: =CW47-CX47 -> 0 | DB47: =CZ47-DA47 -> 0 | DD47: =DB47-DC47 -> 0 | DF47: =DD47-DE47 -> 0 | DH47: =DF47-DG47 -> 0 | DJ47: =DH47-DI47 -> 0 | DL47: =DJ47-DK47 -> 0 | DM47: 0 | DN47: =DL47-DM47 -> 0 | DO47: 0 | DP47: =DN47-DO47 -> 0 | DQ47: 0 | DR47: =DP47-DQ47 -> 0 | DS47: 0 | DT47: =DR47-DS47 -> 0 | DU47: 0 | DV47: =DT47-DU47 -> 0
A48: CS1138 | B48: KARAN SINGH | C48: {=_xlfn.XLOOKUP(A48,'Emp Master'!A:A,'Emp Master'!F:F)} -> #N/A | D48: {=_xlfn.XLOOKUP(A48,'Emp Master'!A:A,'Emp Master'!D:D)} -> #N/A | E48: =_xlfn.XLOOKUP(A48,INDIRECT($D$1),INDIRECT($E$1),0) -> #REF! | BI48: =BG48-BH48 -> 0 | BS48: =BQ48-BR48 -> 0 | BU48: =BS48-BT48 -> 0 | BW48: =BU48-BV48 -> 0 | BY48: =BW48-BX48 -> 0 | CA48: =BY48-BZ48 -> 0 | CC48: =CA48-CB48 -> 0 | CE48: =CC48-CD48 -> 0 | CG48: =CE48-CF48 -> 0 | CI48: =CG48-CH48 -> 0 | CK48: =CI48-CJ48 -> 0 | CM48: =CK48-CL48 -> 0 | CO48: =CM48-CN48 -> 0 | CQ48: =CO48-CP48 -> 0 | CS48: =CQ48-CR48 -> 0 | CU48: =CS48-CT48 -> 0 | CW48: =CU48-CV48 -> 0 | CZ48: =CW48-CX48 -> 0 | DB48: =CZ48-DA48 -> 0 | DD48: =DB48-DC48 -> 0 | DF48: =DD48-DE48 -> 0 | DH48: =DF48-DG48 -> 0 | DJ48: =DH48-DI48 -> 0 | DL48: =DJ48-DK48 -> 0 | DM48: 0 | DN48: =DL48-DM48 -> 0 | DO48: 0 | DP48: =DN48-DO48 -> 0 | DQ48: 0 | DR48: =DP48-DQ48 -> 0 | DS48: 0 | DT48: =DR48-DS48 -> 0 | DU48: 0 | DV48: =DT48-DU48 -> 0
A49: CS1139 | B49: RAJESH | C49: {=_xlfn.XLOOKUP(A49,'Emp Master'!A:A,'Emp Master'!F:F)} -> #N/A | D49: {=_xlfn.XLOOKUP(A49,'Emp Master'!A:A,'Emp Master'!D:D)} -> #N/A | E49: =_xlfn.XLOOKUP(A49,INDIRECT($D$1),INDIRECT($E$1),0) -> #REF! | BI49: =BG49-BH49 -> 0 | BS49: =BQ49-BR49 -> 0 | BU49: =BS49-BT49 -> 0 | BW49: =BU49-BV49 -> 0 | BY49: =BW49-BX49 -> 0 | CA49: =BY49-BZ49 -> 0 | CC49: =CA49-CB49 -> 0 | CE49: =CC49-CD49 -> 0 | CG49: =CE49-CF49 -> 0 | CI49: =CG49-CH49 -> 0 | CK49: =CI49-CJ49 -> 0 | CM49: =CK49-CL49 -> 0 | CO49: =CM49-CN49 -> 0 | CQ49: =CO49-CP49 -> 0 | CS49: =CQ49-CR49 -> 0 | CU49: =CS49-CT49 -> 0 | CW49: =CU49-CV49 -> 0 | CZ49: =CW49-CX49 -> 0 | DB49: =CZ49-DA49 -> 0 | DD49: =DB49-DC49 -> 0 | DF49: =DD49-DE49 -> 0 | DH49: =DF49-DG49 -> 0 | DJ49: =DH49-DI49 -> 0 | DL49: =DJ49-DK49 -> 0 | DM49: 0 | DN49: =DL49-DM49 -> 0 | DO49: 0 | DP49: =DN49-DO49 -> 0 | DQ49: 0 | DR49: =DP49-DQ49 -> 0 | DS49: 0 | DT49: =DR49-DS49 -> 0 | DU49: 0 | DV49: =DT49-DU49 -> 0
A50: MA1001 | B50: JAGDISH RAI BAHL | C50: {=_xlfn.XLOOKUP(A50,'Emp Master'!A:A,'Emp Master'!F:F)} -> #N/A | D50: {=_xlfn.XLOOKUP(A50,'Emp Master'!A:A,'Emp Master'!D:D)} -> #N/A | E50: =_xlfn.XLOOKUP(A50,INDIRECT($D$1),INDIRECT($E$1),0) -> #REF! | I50: =G50-H50 -> 0 | K50: =I50-J50 -> 0 | M50: =K50-L50 -> 0 | O50: =M50-N50 -> 0 | Q50: =O50-P50 -> 0 | S50: =Q50-R50 -> 0 | U50: =S50-T50 -> 0 | W50: =U50-V50 -> 0 | Y50: =W50-X50 -> 0 | AA50: =Y50-Z50 -> 0 | AC50: =AA50-AB50 -> 0 | AE50: =AC50-AD50 -> 0 | AG50: =AE50-AF50 -> 0 | AI50: =AG50-AH50 -> 0 | AK50: =AI50-AJ50 -> 0 | AM50: =AK50-AL50 -> 0 | AO50: =AM50-AN50 -> 0 | AQ50: =AO50-AP50 -> 0 | AS50: =AQ50-AR50 -> 0 | AU50: =AS50-AT50 -> 0 | AW50: =AU50-AV50 -> 0 | AY50: =AW50-AX50 -> 0 | BA50: =AY50-AZ50 -> 0 | BC50: =BA50-BB50 -> 0 | BE50: =BC50-BD50 -> 0 | BG50: =BE50-BF50 -> 0 | BI50: =BG50-BH50 -> 0 | BK50: =BI50-BJ50 -> 0 | BM50: =BK50-BL50 -> 0 | BO50: =BM50-BN50 -> 0 | BQ50: =BO50-BP50 -> 0 | BS50: =BQ50-BR50 -> 0 | BU50: =BS50-BT50 -> 0 | BW50: =BU50-BV50 -> 0 | BY50: =BW50-BX50 -> 0 | CA50: =BY50-BZ50 -> 0 | CC50: =CA50-CB50 -> 0 | CE50: =CC50-CD50 -> 0 | CG50: =CE50-CF50 -> 0 | CI50: =CG50-CH50 -> 0 | CK50: =CI50-CJ50 -> 0 | CM50: =CK50-CL50 -> 0 | CO50: =CM50-CN50 -> 0 | CQ50: =CO50-CP50 -> 0 | CS50: =CQ50-CR50 -> 0 | CU50: =CS50-CT50 -> 0 | CW50: =CU50-CV50 -> 0 | CZ50: =CW50-CX50 -> 0 | DB50: =CZ50-DA50 -> 0 | DD50: =DB50-DC50 -> 0 | DF50: =DD50-DE50 -> 0 | DH50: =DF50-DG50 -> 0 | DJ50: =DH50-DI50 -> 0 | DL50: =DJ50-DK50 -> 0 | DM50: 0 | DN50: =DL50-DM50 -> 0 | DO50: 0 | DP50: =DN50-DO50 -> 0 | DQ50: 0 | DR50: =DP50-DQ50 -> 0 | DS50: 0 | DT50: =DR50-DS50 -> 0 | DU50: 0 | DV50: =DT50-DU50 -> 0
A51: MA1002 | B51: RAJESH PURI | C51: {=_xlfn.XLOOKUP(A51,'Emp Master'!A:A,'Emp Master'!F:F)} -> #N/A | D51: {=_xlfn.XLOOKUP(A51,'Emp Master'!A:A,'Emp Master'!D:D)} -> #N/A | E51: =_xlfn.XLOOKUP(A51,INDIRECT($D$1),INDIRECT($E$1),0) -> #REF! | I51: =G51-H51 -> 0 | K51: =I51-J51 -> 0 | M51: =K51-L51 -> 0 | O51: =M51-N51 -> 0 | Q51: =O51-P51 -> 0 | S51: =Q51-R51 -> 0 | U51: =S51-T51 -> 0 | W51: =U51-V51 -> 0 | Y51: =W51-X51 -> 0 | AA51: =Y51-Z51 -> 0 | AC51: =AA51-AB51 -> 0 | AE51: =AC51-AD51 -> 0 | AG51: =AE51-AF51 -> 0 | AI51: =AG51-AH51 -> 0 | AK51: =AI51-AJ51 -> 0 | AM51: =AK51-AL51 -> 0 | AO51: =AM51-AN51 -> 0 | AQ51: =AO51-AP51 -> 0 | AS51: =AQ51-AR51 -> 0 | AU51: =AS51-AT51 -> 0 | AW51: =AU51-AV51 -> 0 | AY51: =AW51-AX51 -> 0 | BA51: =AY51-AZ51 -> 0 | BC51: =BA51-BB51 -> 0 | BE51: =BC51-BD51 -> 0 | BG51: =BE51-BF51 -> 0 | BI51: =BG51-BH51 -> 0 | BK51: =BI51-BJ51 -> 0 | BM51: =BK51-BL51 -> 0 | BO51: =BM51-BN51 -> 0 | BQ51: =BO51-BP51 -> 0 | BS51: =BQ51-BR51 -> 0 | BU51: =BS51-BT51 -> 0 | BW51: =BU51-BV51 -> 0 | BY51: =BW51-BX51 -> 0 | CA51: =BY51-BZ51 -> 0 | CC51: =CA51-CB51 -> 0 | CE51: =CC51-CD51 -> 0 | CG51: =CE51-CF51 -> 0 | CI51: =CG51-CH51 -> 0 | CK51: =CI51-CJ51 -> 0 | CM51: =CK51-CL51 -> 0 | CO51: =CM51-CN51 -> 0 | CQ51: =CO51-CP51 -> 0 | CS51: =CQ51-CR51 -> 0 | CU51: =CS51-CT51 -> 0 | CW51: =CU51-CV51 -> 0 | CZ51: =CW51-CX51 -> 0 | DB51: =CZ51-DA51 -> 0 | DD51: =DB51-DC51 -> 0 | DF51: =DD51-DE51 -> 0 | DH51: =DF51-DG51 -> 0 | DJ51: =DH51-DI51 -> 0 | DL51: =DJ51-DK51 -> 0 | DM51: 0 | DN51: =DL51-DM51 -> 0 | DO51: 0 | DP51: =DN51-DO51 -> 0 | DQ51: 0 | DR51: =DP51-DQ51 -> 0 | DS51: 0 | DT51: =DR51-DS51 -> 0 | DU51: 0 | DV51: =DT51-DU51 -> 0
A52: MP1001 | B52: JASWANT SINGH MALI | C52: {=_xlfn.XLOOKUP(A52,'Emp Master'!A:A,'Emp Master'!F:F)} -> SNP | D52: {=_xlfn.XLOOKUP(A52,'Emp Master'!A:A,'Emp Master'!D:D)} -> Garden | E52: =_xlfn.XLOOKUP(A52,INDIRECT($D$1),INDIRECT($E$1),0) -> #REF! | I52: =G52-H52 -> 0 | K52: =I52-J52 -> 0 | M52: =K52-L52 -> 0 | O52: =M52-N52 -> 0 | Q52: =O52-P52 -> 0 | S52: =Q52-R52 -> 0 | U52: =S52-T52 -> 0 | W52: =U52-V52 -> 0 | Y52: =W52-X52 -> 0 | AA52: =Y52-Z52 -> 0 | AC52: =AA52-AB52 -> 0 | AE52: =AC52-AD52 -> 0 | AG52: =AE52-AF52 -> 0 | AI52: =AG52-AH52 -> 0 | AK52: =AI52-AJ52 -> 0 | AM52: =AK52-AL52 -> 0 | AO52: =AM52-AN52 -> 0 | AQ52: =AO52-AP52 -> 0 | AS52: =AQ52-AR52 -> 0 | AU52: =AS52-AT52 -> 0 | AW52: =AU52-AV52 -> 0 | AY52: =AW52-AX52 -> 0 | BA52: =AY52-AZ52 -> 0 | BC52: =BA52-BB52 -> 0 | BE52: =BC52-BD52 -> 0 | BG52: =BE52-BF52 -> 0 | BI52: =BG52-BH52 -> 0 | BK52: =BI52-BJ52 -> 0 | BM52: =BK52-BL52 -> 0 | BO52: =BM52-BN52 -> 0 | BQ52: =BO52-BP52 -> 0 | BS52: =BQ52-BR52 -> 0 | BU52: =BS52-BT52 -> 0 | BW52: =BU52-BV52 -> 0 | BY52: =BW52-BX52 -> 0 | CA52: =BY52-BZ52 -> 0 | CC52: =CA52-CB52 -> 0 | CE52: =CC52-CD52 -> 0 | CG52: =CE52-CF52 -> 0 | CI52: =CG52-CH52 -> 0 | CK52: =CI52-CJ52 -> 0 | CM52: =CK52-CL52 -> 0 | CO52: =CM52-CN52 -> 0 | CQ52: =CO52-CP52 -> 0 | CS52: =CQ52-CR52 -> 0 | CU52: =CS52-CT52 -> 0 | CW52: =CU52-CV52 -> 0 | CZ52: =CW52-CX52 -> 0 | DB52: =CZ52-DA52 -> 0 | DD52: =DB52-DC52 -> 0 | DF52: =DD52-DE52 -> 0 | DH52: =DF52-DG52 -> 0 | DJ52: =DH52-DI52 -> 0 | DL52: =DJ52-DK52 -> 0 | DM52: 0 | DN52: =DL52-DM52+1790 -> 1790 | DO52: 500 | DP52: =DN52-DO52 -> 1290 | DQ52: 500 | DR52: =DP52-DQ52 -> 790 | DS52: 790 | DT52: =DR52-DS52 -> 0 | DU52: 0 | DV52: =DT52-DU52 -> 0
A53: MP1004 | B53: RAM KIRPAL | C53: {=_xlfn.XLOOKUP(A53,'Emp Master'!A:A,'Emp Master'!F:F)} -> #N/A | D53: {=_xlfn.XLOOKUP(A53,'Emp Master'!A:A,'Emp Master'!D:D)} -> #N/A | E53: =_xlfn.XLOOKUP(A53,INDIRECT($D$1),INDIRECT($E$1),0) -> #REF! | I53: =G53-H53 -> 0 | K53: =I53-J53 -> 0 | M53: =K53-L53 -> 0 | O53: =M53-N53 -> 0 | Q53: =O53-P53 -> 0 | S53: =Q53-R53 -> 0 | U53: =S53-T53 -> 0 | W53: =U53-V53 -> 0 | Y53: =W53-X53 -> 0 | AA53: =Y53-Z53 -> 0 | AC53: =AA53-AB53 -> 0 | AE53: =AC53-AD53 -> 0 | AG53: =AE53-AF53 -> 0 | AI53: =AG53-AH53 -> 0 | AK53: =AI53-AJ53 -> 0 | AM53: =AK53-AL53 -> 0 | AO53: =AM53-AN53 -> 0 | AQ53: =AO53-AP53 -> 0 | AS53: =AQ53-AR53 -> 0 | AT53: 0 | AU53: =AS53-AT53 -> 0 | AV53: 0 | AW53: =AU53-AV53 -> 0 | AX53: 0 | AY53: =AW53-AX53 -> 0 | AZ53: 0 | BA53: =AY53-AZ53 -> 0 | BB53: 0 | BC53: =BA53-BB53 -> 0 | BE53: =BC53-BD53 -> 0 | BG53: =BE53-BF53 -> 0 | BI53: =BG53-BH53 -> 0 | BK53: =BI53-BJ53 -> 0 | BM53: =BK53-BL53 -> 0 | BO53: =BM53-BN53 -> 0 | BQ53: =BO53-BP53 -> 0 | BS53: =BQ53-BR53 -> 0 | BU53: =BS53-BT53 -> 0 | BW53: =BU53-BV53 -> 0 | BY53: =BW53-BX53 -> 0 | CA53: =BY53-BZ53 -> 0 | CC53: =CA53-CB53 -> 0 | CE53: =CC53-CD53 -> 0 | CG53: =CE53-CF53 -> 0 | CI53: =CG53-CH53 -> 0 | CK53: =CI53-CJ53 -> 0 | CM53: =CK53-CL53 -> 0 | CO53: =CM53-CN53 -> 0 | CQ53: =CO53-CP53 -> 0 | CS53: =CQ53-CR53 -> 0 | CU53: =CS53-CT53 -> 0 | CW53: =CU53-CV53 -> 0 | CZ53: =CW53-CX53 -> 0 | DB53: =CZ53-DA53 -> 0 | DD53: =DB53-DC53 -> 0 | DF53: =DD53-DE53 -> 0 | DH53: =DF53-DG53 -> 0 | DJ53: =DH53-DI53 -> 0 | DL53: =DJ53-DK53 -> 0 | DM53: 0 | DN53: =DL53-DM53 -> 0 | DO53: 0 | DP53: =DN53-DO53 -> 0 | DQ53: 0 | DR53: =DP53-DQ53 -> 0 | DS53: 0 | DT53: =DR53-DS53 -> 0 | DU53: 0 | DV53: =DT53-DU53 -> 0
A54: MP1005 | B54: VEER BHAN | C54: {=_xlfn.XLOOKUP(A54,'Emp Master'!A:A,'Emp Master'!F:F)} -> #N/A | D54: {=_xlfn.XLOOKUP(A54,'Emp Master'!A:A,'Emp Master'!D:D)} -> #N/A | E54: =_xlfn.XLOOKUP(A54,INDIRECT($D$1),INDIRECT($E$1),0) -> #REF! | F54: 2000 | G54: 4000 | H54: 2000 | I54: =G54-H54 -> 2000 | J54: 2000 | K54: =I54-J54 -> 0 | M54: =K54-L54 -> 0 | O54: =M54-N54 -> 0 | Q54: =O54-P54 -> 0 | S54: =Q54-R54 -> 0 | U54: =S54-T54 -> 0 | W54: =U54-V54 -> 0 | Y54: =W54-X54 -> 0 | AA54: =Y54-Z54 -> 0 | AC54: =AA54-AB54 -> 0 | AE54: =AC54-AD54 -> 0 | AG54: =AE54-AF54 -> 0 | AI54: =AG54-AH54 -> 0 | AK54: =AI54-AJ54 -> 0 | AM54: =AK54-AL54 -> 0 | AO54: =AM54-AN54 -> 0 | AQ54: =AO54-AP54 -> 0 | AS54: =AQ54-AR54 -> 0 | AU54: =AS54-AT54 -> 0 | AW54: =AU54-AV54 -> 0 | AY54: =AW54-AX54 -> 0 | BA54: =AY54-AZ54 -> 0 | BC54: =BA54-BB54 -> 0 | BE54: =BC54-BD54 -> 0 | BG54: =BE54-BF54 -> 0 | BI54: =BG54-BH54 -> 0 | BK54: =BI54-BJ54 -> 0 | BM54: =BK54-BL54 -> 0 | BO54: =BM54-BN54 -> 0 | BQ54: =BO54-BP54 -> 0 | BS54: =BQ54-BR54 -> 0 | BU54: =BS54-BT54 -> 0 | BW54: =BU54-BV54 -> 0 | BY54: =BW54-BX54 -> 0 | CA54: =BY54-BZ54 -> 0 | CC54: =CA54-CB54 -> 0 | CE54: =CC54-CD54 -> 0 | CG54: =CE54-CF54 -> 0 | CI54: =CG54-CH54 -> 0 | CK54: =CI54-CJ54 -> 0 | CM54: =CK54-CL54 -> 0 | CO54: =CM54-CN54 -> 0 | CQ54: =CO54-CP54 -> 0 | CS54: =CQ54-CR54 -> 0 | CU54: =CS54-CT54 -> 0 | CW54: =CU54-CV54 -> 0 | CZ54: =CW54-CX54 -> 0 | DB54: =CZ54-DA54 -> 0 | DD54: =DB54-DC54 -> 0 | DF54: =DD54-DE54 -> 0 | DH54: =DF54-DG54 -> 0 | DJ54: =DH54-DI54 -> 0 | DL54: =DJ54-DK54 -> 0 | DM54: 0 | DN54: =DL54-DM54 -> 0 | DO54: 0 | DP54: =DN54-DO54 -> 0 | DQ54: 0 | DR54: =DP54-DQ54 -> 0 | DS54: 0 | DT54: =DR54-DS54 -> 0 | DU54: 0 | DV54: =DT54-DU54 -> 0
A55: SA1001 | B55: RAJESH PURI | C55: {=_xlfn.XLOOKUP(A55,'Emp Master'!A:A,'Emp Master'!F:F)} -> DEL | D55: {=_xlfn.XLOOKUP(A55,'Emp Master'!A:A,'Emp Master'!D:D)} -> Accounts & Finance | E55: =_xlfn.XLOOKUP(A55,INDIRECT($D$1),INDIRECT($E$1),0) -> #REF! | I55: =G55-H55 -> 0 | K55: =I55-J55 -> 0 | M55: =K55-L55 -> 0 | O55: =M55-N55 -> 0 | Q55: =O55-P55 -> 0 | S55: =Q55-R55 -> 0 | U55: =S55-T55 -> 0 | W55: =U55-V55 -> 0 | Y55: =W55-X55 -> 0 | AA55: =Y55-Z55 -> 0 | AC55: =AA55-AB55 -> 0 | AE55: =AC55-AD55 -> 0 | AG55: =AE55-AF55 -> 0 | AI55: =AG55-AH55 -> 0 | AK55: =AI55-AJ55 -> 0 | AM55: =AK55-AL55 -> 0 | AO55: =AM55-AN55 -> 0 | AQ55: =AO55-AP55 -> 0 | AS55: =AQ55-AR55 -> 0 | AU55: =AS55-AT55 -> 0 | AW55: =AU55-AV55 -> 0 | AY55: =AW55-AX55 -> 0 | BA55: =AY55-AZ55 -> 0 | BC55: =BA55-BB55 -> 0 | BE55: =BC55-BD55 -> 0 | BG55: =BE55-BF55 -> 0 | BI55: =BG55-BH55 -> 0 | BK55: =BI55-BJ55 -> 0 | BM55: =BK55-BL55 -> 0 | BO55: =BM55-BN55 -> 0 | BQ55: =BO55-BP55 -> 0 | BS55: =BQ55-BR55 -> 0 | BU55: =BS55-BT55 -> 0 | BW55: =BU55-BV55 -> 0 | BY55: =BW55-BX55 -> 0 | CA55: =BY55-BZ55 -> 0 | CC55: =CA55-CB55 -> 0 | CE55: =CC55-CD55 -> 0 | CG55: =CE55-CF55 -> 0 | CI55: =CG55-CH55 -> 0 | CK55: =CI55-CJ55 -> 0 | CM55: =CK55-CL55 -> 0 | CO55: =CM55-CN55 -> 0 | CQ55: =CO55-CP55 -> 0 | CS55: =CQ55-CR55 -> 0 | CU55: =CS55-CT55 -> 0 | CW55: =CU55-CV55 -> 0 | CZ55: =CW55-CX55 -> 0 | DB55: =CZ55-DA55 -> 0 | DD55: =DB55-DC55 -> 0 | DF55: =DD55-DE55 -> 0 | DH55: =DF55-DG55 -> 0 | DJ55: =DH55-DI55 -> 0 | DL55: =DJ55-DK55 -> 0 | DM55: 0 | DN55: =DL55-DM55 -> 0 | DO55: 0 | DP55: =DN55-DO55 -> 0 | DQ55: 0 | DR55: =DP55-DQ55 -> 0 | DS55: 0 | DT55: =DR55-DS55 -> 0 | DU55: 0 | DV55: =DT55-DU55 -> 0
A56: SE1001 | B56: NAVEEN CHANDRA | C56: {=_xlfn.XLOOKUP(A56,'Emp Master'!A:A,'Emp Master'!F:F)} -> SNP | D56: {=_xlfn.XLOOKUP(A56,'Emp Master'!A:A,'Emp Master'!D:D)} -> Cutting | E56: =_xlfn.XLOOKUP(A56,INDIRECT($D$1),INDIRECT($E$1),0) -> #REF! | I56: =G56-H56 -> 0 | K56: =I56-J56 -> 0 | M56: =K56-L56 -> 0 | O56: =M56-N56 -> 0 | Q56: =O56-P56 -> 0 | S56: =Q56-R56 -> 0 | U56: =S56-T56 -> 0 | W56: =U56-V56 -> 0 | Y56: =W56-X56 -> 0 | AA56: =Y56-Z56 -> 0 | AC56: =AA56-AB56 -> 0 | AE56: =AC56-AD56 -> 0 | AG56: =AE56-AF56 -> 0 | AI56: =AG56-AH56 -> 0 | AK56: =AI56-AJ56 -> 0 | AM56: =AK56-AL56 -> 0 | AO56: =AM56-AN56 -> 0 | AQ56: =AO56-AP56 -> 0 | AS56: =AQ56-AR56 -> 0 | AU56: =AS56-AT56 -> 0 | AW56: =AU56-AV56 -> 0 | AY56: =AW56-AX56 -> 0 | BA56: =AY56-AZ56 -> 0 | BC56: =BA56-BB56 -> 0 | BE56: =BC56-BD56 -> 0 | BG56: =BE56-BF56 -> 0 | BI56: =BG56-BH56 -> 0 | BK56: =BI56-BJ56 -> 0 | BM56: =BK56-BL56 -> 0 | BO56: =BM56-BN56 -> 0 | BQ56: =BO56-BP56 -> 0 | BS56: =BQ56-BR56 -> 0 | BU56: =BS56-BT56 -> 0 | BW56: =BU56-BV56 -> 0 | BY56: =BW56-BX56 -> 0 | CA56: =BY56-BZ56 -> 0 | CC56: =CA56-CB56 -> 0 | CE56: =CC56-CD56 -> 0 | CG56: =CE56-CF56 -> 0 | CI56: =CG56-CH56 -> 0 | CK56: =CI56-CJ56 -> 0 | CM56: =CK56-CL56 -> 0 | CO56: =CM56-CN56 -> 0 | CQ56: =CO56-CP56 -> 0 | CS56: =CQ56-CR56 -> 0 | CU56: =CS56-CT56 -> 0 | CW56: =CU56-CV56 -> 0 | CZ56: =CW56-CX56 -> 0 | DB56: =CZ56-DA56 -> 0 | DD56: =DB56-DC56 -> 0 | DF56: =DD56-DE56 -> 0 | DH56: =DF56-DG56 -> 0 | DJ56: =DH56-DI56 -> 0 | DL56: 1572 | DM56: 200 | DN56: =DL56-DM56+1790 -> 3162 | DO56: 1000 | DP56: =DN56-DO56 -> 2162 | DQ56: 1000 | DR56: =DP56-DQ56 -> 1162 | DS56: 1162 | DT56: =DR56-DS56 -> 0 | DU56: 0 | DV56: =DT56-DU56 -> 0
A57: SE1002 | B57: KHAJAN SINGH RAWAT | C57: {=_xlfn.XLOOKUP(A57,'Emp Master'!A:A,'Emp Master'!F:F)} -> SNP | D57: {=_xlfn.XLOOKUP(A57,'Emp Master'!A:A,'Emp Master'!D:D)} -> Cutting | E57: =_xlfn.XLOOKUP(A57,INDIRECT($D$1),INDIRECT($E$1),0) -> #REF! | F57: 2000 | G57: 8000 | H57: 2000 | I57: =G57-H57 -> 6000 | J57: 3000 | K57: =I57-J57 -> 3000 | L57: 3000 | M57: =K57-L57 -> 0 | O57: =M57-N57 -> 0 | Q57: =O57-P57 -> 0 | S57: =Q57-R57+25000 -> 25000 | T57: 5000 | U57: =S57-T57 -> 20000 | V57: 3000 | W57: =U57-V57 -> 17000 | X57: 0 | Y57: =W57-X57 -> 17000 | Z57: 3000 | AA57: =Y57-Z57 -> 14000 | AB57: 3000 | AC57: =AA57-AB57 -> 11000 | AD57: 3000 | AE57: =AC57-AD57 -> 8000 | AF57: 4000 | AG57: =AE57-AF57 -> 4000 | AH57: 4000 | AI57: =AG57-AH57 -> 0 | AK57: =AI57-AJ57 -> 0 | AM57: =AK57-AL57 -> 0 | AO57: =AM57-AN57 -> 0 | AQ57: =AO57-AP57+20000 -> 20000 | AR57: 4000 | AS57: =AQ57-AR57 -> 16000 | AT57: 4000 | AU57: =AS57-AT57 -> 12000 | AV57: 4000 | AW57: =AU57-AV57 -> 8000 | AX57: 4000 | AY57: =AW57-AX57 -> 4000 | AZ57: 4000 | BA57: =AY57-AZ57 -> 0 | BC57: =BA57-BB57 -> 0 | BE57: =BC57-BD57 -> 0 | BG57: =BE57-BF57 -> 0 | BI57: =BG57-BH57 -> 0 | BK57: =BI57-BJ57 -> 0 | BM57: =BK57-BL57 -> 0 | BO57: =BM57-BN57+20000 -> 20000 | BP57: 5000 | BQ57: =BO57-BP57 -> 15000 | BR57: 5000 | BS57: =BQ57-BR57 -> 10000 | BT57: 5000 | BU57: =BS57-BT57 -> 5000 | BV57: 5000 | BW57: =BU57-BV57 -> 0 | BY57: =BW57-BX57 -> 0 | CA57: =BY57-BZ57 -> 0 | CC57: 10000 | CD57: 5000 | CE57: =CC57-CD57 -> 5000 | CF57: 5000 | CG57: =CE57-CF57 -> 0 | CI57: =CG57-CH57 -> 0 | CK57: =CI57-CJ57 -> 0 | CM57: =25000+CK57-CL57 -> 25000 | CN57: 6250 | CO57: =CM57-CN57 -> 18750 | CP57: 6250 | CQ57: =CO57-CP57 -> 12500 | CR57: 6250 | CS57: =CQ57-CR57 -> 6250 | CT57: 6250 | CU57: =CS57-CT57 -> 0 | CW57: =CU57-CV57 -> 0 | CZ57: =CW57-CX57 -> 0 | DB57: =CZ57-DA57 -> 0 | DD57: =DB57-DC57+20000 -> 20000 | DE57: 10000 | DF57: =DD57-DE57 -> 10000 | DG57: 10000 | DH57: =DF57-DG57 -> 0 | DJ57: =DH57-DI57 -> 0 | DL57: 25000 | DM57: 10000 | DN57: =DL57-DM57 -> 15000 | DO57: 10000 | DP57: =DN57-DO57 -> 5000 | DQ57: 5000 | DR57: =DP57-DQ57 -> 0 | DS57: 0 | DT57: =DR57-DS57 -> 0 | DU57: 0 | DV57: =DT57-DU57 -> 0
A58: SE1003 | B58: SANJAY SINGH | C58: {=_xlfn.XLOOKUP(A58,'Emp Master'!A:A,'Emp Master'!F:F)} -> #N/A | D58: {=_xlfn.XLOOKUP(A58,'Emp Master'!A:A,'Emp Master'!D:D)} -> #N/A | E58: =_xlfn.XLOOKUP(A58,INDIRECT($D$1),INDIRECT($E$1),0) -> #REF! | I58: =G58-H58 -> 0 | K58: =I58-J58 -> 0 | M58: =K58-L58 -> 0 | O58: =M58-N58 -> 0 | Q58: =O58-P58 -> 0 | S58: =Q58-R58 -> 0 | U58: =S58-T58 -> 0 | W58: =U58-V58 -> 0 | Y58: =W58-X58 -> 0 | AA58: =Y58-Z58 -> 0 | AC58: =AA58-AB58 -> 0 | AE58: =AC58-AD58 -> 0 | AG58: =AE58-AF58 -> 0 | AI58: =AG58-AH58 -> 0 | AK58: =AI58-AJ58 -> 0 | AM58: =AK58-AL58 -> 0 | AO58: =AM58-AN58 -> 0 | AQ58: =AO58-AP58 -> 0 | AS58: =AQ58-AR58 -> 0 | AU58: =AS58-AT58 -> 0 | AW58: =AU58-AV58 -> 0 | AY58: =AW58-AX58 -> 0 | BA58: =AY58-AZ58 -> 0 | BC58: =BA58-BB58 -> 0 | BE58: =BC58-BD58 -> 0 | BG58: =BE58-BF58 -> 0 | BI58: =BG58-BH58 -> 0 | BK58: =BI58-BJ58 -> 0 | BM58: =BK58-BL58 -> 0 | BO58: =BM58-BN58 -> 0 | BQ58: =BO58-BP58 -> 0 | BS58: =BQ58-BR58 -> 0 | BU58: =BS58-BT58 -> 0 | BW58: =BU58-BV58 -> 0 | BY58: =BW58-BX58 -> 0 | CA58: =BY58-BZ58 -> 0 | CC58: =CA58-CB58 -> 0 | CE58: =CC58-CD58 -> 0 | CG58: =CE58-CF58 -> 0 | CI58: =CG58-CH58 -> 0 | CK58: =CI58-CJ58 -> 0 | CM58: =CK58-CL58 -> 0 | CO58: =CM58-CN58 -> 0 | CQ58: =CO58-CP58 -> 0 | CS58: =CQ58-CR58 -> 0 | CU58: =CS58-CT58 -> 0 | CW58: =CU58-CV58 -> 0 | CZ58: =CW58-CX58 -> 0 | DB58: =CZ58-DA58 -> 0 | DD58: =DB58-DC58 -> 0 | DF58: =DD58-DE58 -> 0 | DH58: =DF58-DG58 -> 0 | DJ58: =DH58-DI58 -> 0 | DL58: =DJ58-DK58 -> 0 | DM58: 0 | DN58: =DL58-DM58 -> 0 | DO58: 0 | DP58: =DN58-DO58 -> 0 | DQ58: 0 | DR58: =DP58-DQ58 -> 0 | DS58: 0 | DT58: =DR58-DS58 -> 0 | DU58: 0 | DV58: =DT58-DU58 -> 0
A59: SE1004 | B59: BIRENDRA PRASAD SAH | C59: {=_xlfn.XLOOKUP(A59,'Emp Master'!A:A,'Emp Master'!F:F)} -> #N/A | D59: {=_xlfn.XLOOKUP(A59,'Emp Master'!A:A,'Emp Master'!D:D)} -> #N/A | E59: =_xlfn.XLOOKUP(A59,INDIRECT($D$1),INDIRECT($E$1),0) -> #REF! | F59: 2000 | G59: 12000 | H59: 2000 | I59: =G59-H59 -> 10000 | J59: 2000 | K59: =I59-J59 -> 8000 | L59: 2000 | M59: =K59-L59 -> 6000 | N59: 2000 | O59: =M59-N59+6000 -> 10000 | P59: 2000 | Q59: =O59-P59 -> 8000 | R59: 8000 | S59: =Q59-R59 -> 0 | U59: =S59-T59 -> 0 | W59: =U59-V59 -> 0 | Y59: =W59-X59 -> 0 | AA59: =Y59-Z59 -> 0 | AC59: =AA59-AB59 -> 0 | AE59: =AC59-AD59 -> 0 | AG59: =AE59-AF59 -> 0 | AI59: =AG59-AH59 -> 0 | AK59: =AI59-AJ59 -> 0 | AM59: =AK59-AL59 -> 0 | AO59: =AM59-AN59 -> 0 | AQ59: =AO59-AP59 -> 0 | AS59: =AQ59-AR59 -> 0 | AU59: =AS59-AT59 -> 0 | AW59: =AU59-AV59 -> 0 | AY59: =AW59-AX59 -> 0 | BA59: =AY59-AZ59 -> 0 | BC59: =BA59-BB59 -> 0 | BE59: =BC59-BD59 -> 0 | BG59: =BE59-BF59 -> 0 | BI59: =BG59-BH59 -> 0 | BK59: =BI59-BJ59 -> 0 | BM59: =BK59-BL59 -> 0 | BO59: =BM59-BN59 -> 0 | BQ59: =BO59-BP59 -> 0 | BS59: =BQ59-BR59 -> 0 | BU59: =BS59-BT59 -> 0 | BW59: =BU59-BV59 -> 0 | BY59: =BW59-BX59 -> 0 | CA59: =BY59-BZ59 -> 0 | CC59: =CA59-CB59 -> 0 | CE59: =CC59-CD59 -> 0 | CG59: =CE59-CF59 -> 0 | CI59: =CG59-CH59 -> 0 | CK59: =CI59-CJ59 -> 0 | CM59: =CK59-CL59 -> 0 | CO59: =CM59-CN59 -> 0 | CQ59: =CO59-CP59 -> 0 | CS59: =CQ59-CR59 -> 0 | CU59: =CS59-CT59 -> 0 | CW59: =CU59-CV59 -> 0 | CZ59: =CW59-CX59 -> 0 | DB59: =CZ59-DA59 -> 0 | DD59: =DB59-DC59 -> 0 | DF59: =DD59-DE59 -> 0 | DH59: =DF59-DG59 -> 0 | DJ59: =DH59-DI59 -> 0 | DL59: =DJ59-DK59 -> 0 | DM59: 0 | DN59: =DL59-DM59 -> 0 | DO59: 0 | DP59: =DN59-DO59 -> 0 | DQ59: 0 | DR59: =DP59-DQ59 -> 0 | DS59: 0 | DT59: =DR59-DS59 -> 0 | DU59: 0 | DV59: =DT59-DU59 -> 0
A60: SE1005 | B60: DEEPAK JOSHI | C60: {=_xlfn.XLOOKUP(A60,'Emp Master'!A:A,'Emp Master'!F:F)} -> SNP | D60: {=_xlfn.XLOOKUP(A60,'Emp Master'!A:A,'Emp Master'!D:D)} -> Cutting | E60: =_xlfn.XLOOKUP(A60,INDIRECT($D$1),INDIRECT($E$1),0) -> #REF! | F60: 2000 | G60: 10000 | H60: 2000 | I60: =G60-H60 -> 8000 | J60: 2000 | K60: =I60-J60 -> 6000 | L60: 2000 | M60: =K60-L60 -> 4000 | N60: 2000 | O60: =M60-N60 -> 2000 | P60: 2000 | Q60: =O60-P60 -> 0 | S60: =Q60-R60 -> 0 | U60: =S60-T60 -> 0 | W60: =U60-V60 -> 0 | Y60: =W60-X60 -> 0 | AA60: =Y60-Z60 -> 0 | AC60: =AA60-AB60 -> 0 | AE60: =AC60-AD60 -> 0 | AG60: =AE60-AF60+20000 -> 20000 | AI60: =AG60-AH60 -> 20000 | AJ60: 2000 | AK60: =AI60-AJ60 -> 18000 | AL60: 2000 | AM60: =AK60-AL60 -> 16000 | AN60: 2000 | AO60: =AM60-AN60 -> 14000 | AP60: 2000 | AQ60: =AO60-AP60 -> 12000 | AR60: 2000 | AS60: =AQ60-AR60 -> 10000 | AT60: 2000 | AU60: =AS60-AT60 -> 8000 | AV60: 2000 | AW60: =AU60-AV60 -> 6000 | AX60: 2000 | AY60: =AW60-AX60 -> 4000 | AZ60: 2000 | BA60: =AY60-AZ60 -> 2000 | BB60: 2000 | BC60: =BA60-BB60 -> 0 | BE60: =BC60-BD60 -> 0 | BG60: =BE60-BF60 -> 0 | BI60: =BG60-BH60 -> 0 | BK60: =BI60-BJ60 -> 0 | BM60: =BK60-BL60 -> 0 | BO60: =BM60-BN60 -> 0 | BQ60: =BO60-BP60 -> 0 | BS60: =BQ60-BR60 -> 0 | BU60: =BS60-BT60 -> 0 | BW60: =BU60-BV60 -> 0 | BY60: =BW60-BX60 -> 0 | CA60: =BY60-BZ60 -> 0 | CC60: =CA60-CB60 -> 0 | CE60: =CC60-CD60 -> 0 | CG60: =CE60-CF60 -> 0 | CI60: =CG60-CH60 -> 0 | CK60: =CI60-CJ60 -> 0 | CM60: =CK60-CL60 -> 0 | CO60: =25000+CM60-CN60 -> 25000 | CP60: 6250 | CQ60: =CO60-CP60 -> 18750 | CR60: 0 | CS60: =CQ60-CR60 -> 18750 | CU60: =CS60-CT60 -> 18750 | CV60: 6250 | CW60: =CU60-CV60 -> 12500 | CX60: 6250 | CY60: 6250 | CZ60: =CW60-CX60-CY60 -> 0 | DB60: =CZ60-DA60 -> 0 | DD60: =DB60-DC60 -> 0 | DF60: =DD60-DE60 -> 0 | DH60: =DF60-DG60 -> 0 | DJ60: =DH60-DI60 -> 0 | DL60: =DJ60-DK60 -> 0 | DM60: 0 | DN60: =DL60-DM60 -> 0 | DO60: 0 | DP60: =DN60-DO60 -> 0 | DQ60: 0 | DR60: =DP60-DQ60+496 -> 496 | DS60: 496 | DT60: =DR60-DS60 -> 0 | DU60: 0 | DV60: =DT60-DU60 -> 0
A61: SE1007 | B61: AMBICA YADAV | C61: {=_xlfn.XLOOKUP(A61,'Emp Master'!A:A,'Emp Master'!F:F)} -> SNP | D61: {=_xlfn.XLOOKUP(A61,'Emp Master'!A:A,'Emp Master'!D:D)} -> Cutting | E61: =_xlfn.XLOOKUP(A61,INDIRECT($D$1),INDIRECT($E$1),0) -> #REF! | F61: 1000 | G61: 5000 | H61: 1000 | I61: =G61-H61 -> 4000 | J61: 1000 | K61: =I61-J61 -> 3000 | L61: 1000 | M61: =K61-L61 -> 2000 | N61: 1000 | O61: =M61-N61 -> 1000 | P61: 1000 | Q61: =O61-P61 -> 0 | S61: =Q61-R61 -> 0 | U61: =S61-T61 -> 0 | W61: =U61-V61 -> 0 | Y61: =W61-X61 -> 0 | AA61: =Y61-Z61+20000 -> 20000 | AB61: 2000 | AC61: =AA61-AB61 -> 18000 | AD61: 2000 | AE61: =AC61-AD61 -> 16000 | AF61: 2000 | AG61: =AE61-AF61 -> 14000 | AH61: 2000 | AI61: =AG61-AH61 -> 12000 | AJ61: 2000 | AK61: =AI61-AJ61 -> 10000 | AL61: 2000 | AM61: =AK61-AL61 -> 8000 | AN61: 2000 | AO61: =AM61-AN61 -> 6000 | AP61: 2000 | AQ61: =AO61-AP61 -> 4000 | AR61: 2000 | AS61: =AQ61-AR61 -> 2000 | AT61: 2000 | AU61: =AS61-AT61 -> 0 | AW61: =AU61-AV61 -> 0 | AY61: =AW61-AX61 -> 0 | BA61: =AY61-AZ61 -> 0 | BC61: =BA61-BB61 -> 0 | BE61: =BC61-BD61 -> 0 | BG61: =BE61-BF61 -> 0 | BI61: =BG61-BH61 -> 0 | BK61: =BI61-BJ61 -> 0 | BM61: =BK61-BL61 -> 0 | BO61: =BM61-BN61 -> 0 | BQ61: =BO61-BP61 -> 0 | BS61: =BQ61-BR61 -> 0 | BU61: =BS61-BT61 -> 0 | BW61: =BU61-BV61 -> 0 | BY61: =BW61-BX61 -> 0 | CA61: =BY61-BZ61 -> 0 | CC61: =CA61-CB61 -> 0 | CE61: =CC61-CD61 -> 0 | CG61: =CE61-CF61 -> 0 | CI61: =CG61-CH61 -> 0 | CK61: =CI61-CJ61 -> 0 | CM61: =CK61-CL61 -> 0 | CO61: =CM61-CN61 -> 0 | CQ61: =CO61-CP61 -> 0 | CS61: =CQ61-CR61 -> 0 | CU61: =CS61-CT61 -> 0 | CW61: =CU61-CV61 -> 0 | CZ61: =CW61-CX61 -> 0 | DB61: =CZ61-DA61 -> 0 | DD61: =DB61-DC61 -> 0 | DF61: =DD61-DE61 -> 0 | DH61: =DF61-DG61 -> 0 | DJ61: =DH61-DI61 -> 0 | DL61: =DJ61-DK61 -> 0 | DM61: 0 | DN61: =DL61-DM61 -> 0 | DO61: 0 | DP61: =DN61-DO61 -> 0 | DQ61: 0 | DR61: =DP61-DQ61 -> 0 | DS61: 0 | DT61: =DR61-DS61 -> 0 | DU61: 0 | DV61: =DT61-DU61 -> 0
A62: SE1008 | B62: ERADHEY SHYAM | C62: {=_xlfn.XLOOKUP(A62,'Emp Master'!A:A,'Emp Master'!F:F)} -> SNP | D62: {=_xlfn.XLOOKUP(A62,'Emp Master'!A:A,'Emp Master'!D:D)} -> Cutting | E62: =_xlfn.XLOOKUP(A62,INDIRECT($D$1),INDIRECT($E$1),0) -> #REF! | F62: 2000 | G62: 14000 | H62: 2000 | I62: =G62-H62 -> 12000 | J62: 2000 | K62: =I62-J62 -> 10000 | L62: 2000 | M62: =K62-L62 -> 8000 | N62: 2000 | O62: =M62-N62 -> 6000 | P62: 2000 | Q62: =O62-P62 -> 4000 | R62: 2000 | S62: =Q62-R62 -> 2000 | T62: 2000 | U62: =S62-T62+20000 -> 20000 | V62: 2000 | W62: =U62-V62 -> 18000 | X62: 2000 | Y62: =W62-X62 -> 16000 | Z62: 2000 | AA62: =Y62-Z62 -> 14000 | AB62: 2000 | AC62: =AA62-AB62 -> 12000 | AD62: 2000 | AE62: =AC62-AD62 -> 10000 | AF62: 2000 | AG62: =AE62-AF62 -> 8000 | AI62: =AG62-AH62 -> 8000 | AJ62: 2000 | AK62: =AI62-AJ62 -> 6000 | AL62: 0 | AM62: =AK62-AL62 -> 6000 | AN62: 2000 | AO62: =AM62-AN62 -> 4000 | AP62: 2000 | AQ62: =AO62-AP62 -> 2000 | AR62: 2000 | AS62: =AQ62-AR62 -> 0 | AU62: =AS62-AT62 -> 0 | AW62: =AU62-AV62+20000 -> 20000 | AY62: =AW62-AX62 -> 20000 | AZ62: 3000 | BA62: =AY62-AZ62 -> 17000 | BB62: 3000 | BC62: =BA62-BB62 -> 14000 | BD62: 3000 | BE62: =BC62-BD62 -> 11000 | BF62: 3000 | BG62: =BE62-BF62 -> 8000 | BH62: 3000 | BI62: =BG62-BH62 -> 5000 | BJ62: 3000 | BK62: =BI62-BJ62 -> 2000 | BL62: 2000 | BM62: =BK62-BL62 -> 0 | BO62: =BM62-BN62 -> 0 | BQ62: =BO62-BP62 -> 0 | BS62: =BQ62-BR62 -> 0 | BU62: =BS62-BT62 -> 0 | BW62: =BU62-BV62 -> 0 | BY62: =BW62-BX62 -> 0 | CA62: =BY62-BZ62 -> 0 | CC62: =1500+(CA62-CB62) -> 1500 | CD62: 1500 | CE62: =CC62-CD62 -> 0 | CG62: =15000+(CE62-CF62) -> 15000 | CH62: 4000 | CI62: =CG62-CH62 -> 11000 | CJ62: 4000 | CK62: =CI62-CJ62 -> 7000 | CM62: =CK62-CL62 -> 7000 | CN62: 4000 | CO62: =CM62-CN62 -> 3000 | CP62: 3000 | CQ62: =CO62-CP62 -> 0 | CS62: =CQ62-CR62 -> 0 | CU62: =CS62-CT62+25000 -> 25000 | CV62: 5000 | CW62: =CU62-CV62 -> 20000 | CX62: 5000 | CY62: 15000 | CZ62: =CW62-CX62-CY62 -> 0 | DB62: =CZ62-DA62 -> 0 | DD62: =DB62-DC62+20000+6000 -> 26000 | DE62: =5000+6000 -> 11000 | DF62: =DD62-DE62 -> 15000 | DG62: 10000 | DH62: =DF62-DG62 -> 5000 | DI62: 5000 | DJ62: =DH62-DI62 -> 0 | DL62: 1572 | DM62: 300 | DN62: =DL62-DM62 -> 1272 | DO62: 500 | DP62: =DN62-DO62 -> 772 | DQ62: 772 | DR62: =DP62-DQ62 -> 0 | DS62: 0 | DT62: =DR62-DS62 -> 0 | DU62: 0 | DV62: =DT62-DU62 -> 0
